Workbook

Sheet Summary
G2: 44926 | H2: 45291 | I2: 45657 | J2: 46022 | K2: 46387 | L2: 46752 | M2: 47118 | N2: 47483
C3: COKE | D3: COKE US Equity | G3: 2022 | H3: =G3+1 -> 2023 | I3: =H3+1 -> 2024 | J3: =I3+1 -> 2025 | K3: =J3+1 -> 2026 | L3: =K3+1 -> 2027 | M3: =L3+1 -> 2028 | N3: =M3+1 -> 2029 | Q3: 2026 YE return scenarios
C4: Scenario | D4: 2 - Base | F4: WH Revenue | G4: ='WH Model'!BQ17 -> 6200.957 | H4: ='WH Model'!BR17 -> 6653.858 | I4: ='WH Model'!BS17 -> 6899.716 | J4: ='WH Model'!BT17 -> 7228.055 | K4: ='WH Model'!BU17 -> 7420.7786 | L4: ='WH Model'!BV17 -> 7644.7594 | M4: ='WH Model'!BW17 -> 7875.5006 | N4: ='WH Model'!BX17 -> 8113.2062 | Q4: EPS | R4: P/E | S4: Target | T4: NPV | U4: % Return | V4: IRR
C5: Last Updated | D5: =TODAY() -> 46148 | F5: % yoy | H5: =IF(G4=0,0,H4/G4-1) -> 0.073037275 | I5: =IF(H4=0,0,I4/H4-1) -> 0.036949691 | J5: =IF(I4=0,0,J4/I4-1) -> 0.047587321 | K5: =IF(J4=0,0,K4/J4-1) -> 0.026663279 | L5: =IF(K4=0,0,L4/K4-1) -> 0.030182918 | M5: =IF(L4=0,0,M4/L4-1) -> 0.030182921 | N5: =IF(M4=0,0,N4/M4-1) -> 0.030182924 | P5: Bull | Q5: =IF(VALUE(LEFT($D$4,1))=1,$L$22,Q5) -> 8.8284404 | R5: 24 | S5: =Q5*R5 -> 211.88257 | T5: =S5/1.1^(($L$2-$D$5)/365) -> 180.96677 | U5: =S5/$D$7-1 -> -0.016329756 | V5: =(1+U5)^(1/(($L$2-$D$5)/365))-1 -> -0.0099002737
C6: Cap Table (USD) | F6: Expected Delta | P6: Base | Q6: =IF(VALUE(LEFT($D$4,1))=2,$L$22,Q6) -> 6.3732891 | R6: 17 | S6: =Q6*R6 -> 108.34591 | T6: =S6/1.1^(($L$2-$D$5)/365) -> 92.537157 | U6: =S6/$D$7-1 -> -0.49700133 | V6: =(1+U6)^(1/(($L$2-$D$5)/365))-1 -> -0.3398305
C7: ="Price as of "&TEXT(TODAY(),"mm/dd/yyyy") -> Price as of 05/06/2026 | D7: {=_xll.BQL("COKE US EQUITY","PX_LAST")} -> 215.4 | P7: Bear | Q7: =IF(VALUE(LEFT($D$4,1))=3,$L$22,Q7) -> 3.7673979 | R7: 15 | S7: =Q7*R7 -> 56.510969 | T7: =S7/1.1^(($L$2-$D$5)/365) -> 48.265451 | U7: =S7/$D$7-1 -> -0.73764638 | V7: =(1+U7)^(1/(($L$2-$D$5)/365))-1 -> -0.55451739
C8: Diluted Shares | D8: ='WH Model'!AT50 -> 57.020861
C9: Market Cap | D9: =D7*D8 -> 12282.294 | F9: Street Revenue | G9: =G4 -> 6200.957 | H9: =H4 -> 6653.858 | I9: =I4 -> 6899.716 | J9: =J4 -> 7228.055 | Q9: 2026 YE return scenarios
C10: Total Debt | D10: ='WH Model'!AS55 -> 2787.753 | F10: % yoy | H10: =IF(G9=0,0,H9/G9-1) -> 0.073037275 | I10: =IF(H9=0,0,I9/H9-1) -> 0.036949691 | J10: =IF(I9=0,0,J9/I9-1) -> 0.047587321 | Q10: EBITDA | R10: EV/EBITDA | S10: Target | T10: NPV | U10: % Return | V10: IRR
C11: Cash | D11: ='WH Model'!AS54 -> 281.918 | P11: Bull | Q11: =IF(VALUE(LEFT($D$4,1))=1,$L$12,Q11) -> 1107.1949 | R11: 14 | S11: =((Q11*R11)-$L$37)/$L$36 -> 226.84572 | T11: =S11/1.1^(($L$2-$D$5)/365) -> 193.74665 | U11: =S11/$D$7-1 -> 0.05313706 | V11: =(1+U11)^(1/(($L$2-$D$5)/365))-1 -> 0.031781477
C12: Net Debt | D12: =D10-D11 -> 2505.835 | F12: WH EBITDA | G12: ='WH Model'!BQ35 -> 812.637 | H12: ='WH Model'!BR35 -> 1011.417 | I12: ='WH Model'!BS35 -> 1114.141 | J12: ='WH Model'!BT35 -> 1169.186 | K12: ='WH Model'!BU35 -> 872.08423 | L12: ='WH Model'!BV35 -> 914.7749 | M12: ='WH Model'!BW35 -> 949.49929 | N12: ='WH Model'!BX35 -> 948.28863 | P12: Base | Q12: =IF(VALUE(LEFT($D$4,1))=2,$L$12,Q12) -> 914.7749 | R12: 12 | S12: =((Q12*R12)-$L$37)/$L$36 -> 146.74344 | T12: =S12/1.1^(($L$2-$D$5)/365) -> 125.33209 | U12: =S12/$D$7-1 -> -0.31873985 | V12: =(1+U12)^(1/(($L$2-$D$5)/365))-1 -> -0.20700534
C13: NCI | D13: 0 | F13: % margin | G13: =IF(G4=0,0,G12/G4) -> 0.13105026 | H13: =IF(H4=0,0,H12/H4) -> 0.1520046 | I13: =IF(I4=0,0,I12/I4) -> 0.16147636 | J13: =IF(J4=0,0,J12/J4) -> 0.16175666 | K13: =IF(K4=0,0,K12/K4) -> 0.11751924 | L13: =IF(L4=0,0,L12/L4) -> 0.11966039 | M13: =IF(M4=0,0,M12/M4) -> 0.12056368 | N13: =IF(N4=0,0,N12/N4) -> 0.11688211 | P13: Bear | Q13: =IF(VALUE(LEFT($D$4,1))=3,$L$12,Q13) -> 708.72245 | R13: 8 | S13: =((Q13*R13)-$L$37)/$L$36 -> 52.756263 | T13: =S13/1.1^(($L$2-$D$5)/365) -> 45.058594 | U13: =S13/$D$7-1 -> -0.7550777 | V13: =(1+U13)^(1/(($L$2-$D$5)/365))-1 -> -0.57264677
C14: Enterprise Value | D14: =D9+D12+D13 -> 14788.129 | F14: % yoy | H14: =IF(G12=0,0,H12/G12-1) -> 0.24461106 | I14: =IF(H12=0,0,I12/H12-1) -> 0.10156444 | J14: =IF(I12=0,0,J12/I12-1) -> 0.049405775 | K14: =IF(J12=0,0,K12/J12-1) -> -0.25410993 | L14: =IF(K12=0,0,L12/K12-1) -> 0.048952457 | M14: =IF(L12=0,0,M12/L12-1) -> 0.037959497 | N14: =IF(M12=0,0,N12/M12-1) -> -0.0012750506
F15: Expected Delta
Q16: Quick Valuation
Q17: Metric | R17: Multiple | S17: Implied Price
F18: Street EBITDA | G18: =G12 -> 812.637 | H18: =H12 -> 1011.417 | I18: =I12 -> 1114.141 | J18: =J12 -> 1169.186 | P18: P/E | S18: =Q18*R18 -> 0
F19: % margin | G19: =IF(G9=0,0,G18/G9) -> 0.13105026 | H19: =IF(H9=0,0,H18/H9) -> 0.1520046 | I19: =IF(I9=0,0,I18/I9) -> 0.16147636 | J19: =IF(J9=0,0,J18/J9) -> 0.16175666 | P19: EV/EBITDA | Q19: 1100 | R19: 11 | S19: =((Q19*R19)-$D$12)/$D$8 -> 168.2571
F20: % yoy | H20: =IF(G18=0,0,H18/G18-1) -> 0.24461106 | I20: =IF(H18=0,0,I18/H18-1) -> 0.10156444 | J20: =IF(I18=0,0,J18/I18-1) -> 0.049405775
F22: WH EPS | G22: ='WH Model'!BQ51 -> 4.8638753 | H22: ='WH Model'!BR51 -> 6.5353207 | I22: ='WH Model'!BS51 -> 7.4929137 | J22: ='WH Model'!BT51 -> 7.9609262 | K22: ='WH Model'!BU51 -> 5.8541141 | L22: ='WH Model'!BV51 -> 6.3732891 | M22: ='WH Model'!BW51 -> 6.8028388 | N22: ='WH Model'!BX51 -> 6.7569824
F23: % yoy | H23: =IF(G22=0,0,H22/G22-1) -> 0.3436448 | I23: =IF(H22=0,0,I22/H22-1) -> 0.14652578 | J23: =IF(I22=0,0,J22/I22-1) -> 0.062460674 | K23: =IF(J22=0,0,K22/J22-1) -> -0.26464409 | L23: =IF(K22=0,0,L22/K22-1) -> 0.088685492 | M23: =IF(L22=0,0,M22/L22-1) -> 0.067398442 | N23: =IF(M22=0,0,N22/M22-1) -> -0.0067407738
F24: Street EPS | G24: =G22 -> 4.8638753 | H24: =H22 -> 6.5353207 | I24: =I22 -> 7.4929137 | J24: =J22 -> 7.9609262
F25: % yoy | H25: =IF(G24=0,0,H24/G24-1) -> 0.3436448 | I25: =IF(H24=0,0,I24/H24-1) -> 0.14652578 | J25: =IF(I24=0,0,J24/I24-1) -> 0.062460674
F26: Expected Delta
F29: Valuation | G29: 2022 | H29: 2023 | I29: 2024 | J29: 2025 | K29: 2026 | L29: 2027 | M29: 2028 | N29: 2029
F30: EV/Sales | G30: =IF(G4=0,0,$D$14/G4) -> 2.3848139 | H30: =IF(H4=0,0,$D$14/H4) -> 2.2224893 | I30: =IF(I4=0,0,$D$14/I4) -> 2.1432953 | J30: =IF(J4=0,0,$D$14/J4) -> 2.0459347 | K30: =IF(K4=0,0,$D$14/K4) -> 1.9928001 | L30: =IF(L4=0,0,$D$14/L4) -> 1.9344139 | M30: =IF(M4=0,0,$D$14/M4) -> 1.8777382 | N30: =IF(N4=0,0,$D$14/N4) -> 1.8227231
F31: Street EV/Sales | G31: =IF(G9=0,0,$D$14/G9) -> 2.3848139 | H31: =IF(H9=0,0,$D$14/H9) -> 2.2224893 | I31: =IF(I9=0,0,$D$14/I9) -> 2.1432953 | J31: =IF(J9=0,0,$D$14/J9) -> 2.0459347 | K31: =IF(K9=0,0,$D$14/K9) -> 0 | L31: =IF(L9=0,0,$D$14/L9) -> 0 | M31: =IF(M9=0,0,$D$14/M9) -> 0 | N31: =IF(N9=0,0,$D$14/N9) -> 0
F32: Street EV/EBITDA | G32: =IF(G18=0,0,$D$14/G18) -> 18.197705 | H32: =IF(H18=0,0,$D$14/H18) -> 14.621198 | I32: =IF(I18=0,0,$D$14/I18) -> 13.273121 | J32: =IF(J18=0,0,$D$14/J18) -> 12.648226 | K32: =IF(K18=0,0,$D$14/K18) -> 0 | L32: =IF(L18=0,0,$D$14/L18) -> 0 | M32: =IF(M18=0,0,$D$14/M18) -> 0 | N32: =IF(N18=0,0,$D$14/N18) -> 0
F33: WH EV/EBITDA | G33: =IF(G12=0,0,$D$14/G12) -> 18.197705 | H33: =IF(H12=0,0,$D$14/H12) -> 14.621198 | I33: =IF(I12=0,0,$D$14/I12) -> 13.273121 | J33: =IF(J12=0,0,$D$14/J12) -> 12.648226 | K33: =IF(K12=0,0,$D$14/K12) -> 16.957225 | L33: =IF(L12=0,0,$D$14/L12) -> 16.165866 | M33: =IF(M12=0,0,$D$14/M12) -> 15.57466 | N33: =IF(N12=0,0,$D$14/N12) -> 15.594544
F34: WH P/E | G34: =IF(G22=0,0,$D$7/G22) -> 44.285675 | H34: =IF(H22=0,0,$D$7/H22) -> 32.959362 | I34: =IF(I22=0,0,$D$7/I22) -> 28.747161 | J34: =IF(J22=0,0,$D$7/J22) -> 27.057153 | K34: =IF(K22=0,0,$D$7/K22) -> 36.794636 | L34: =IF(L22=0,0,$D$7/L22) -> 33.797306 | M34: =IF(M22=0,0,$D$7/M22) -> 31.663252 | N34: =IF(N22=0,0,$D$7/N22) -> 31.878135
F35: Street P/E | G35: =IF(G24=0,0,$D$7/G24) -> 44.285675 | H35: =IF(H24=0,0,$D$7/H24) -> 32.959362 | I35: =IF(I24=0,0,$D$7/I24) -> 28.747161 | J35: =IF(J24=0,0,$D$7/J24) -> 27.057153 | K35: =IF(K24=0,0,$D$7/K24) -> 0 | L35: =IF(L24=0,0,$D$7/L24) -> 0 | M35: =IF(M24=0,0,$D$7/M24) -> 0 | N35: =IF(N24=0,0,$D$7/N24) -> 0
F36: Shares Outstanding | G36: ='WH Model'!BQ50 -> 93.98 | H36: ='WH Model'!BR50 -> 93.925 | I36: ='WH Model'!BS50 -> 90.5625 | J36: ='WH Model'!BT50 -> 83.96925 | K36: ='WH Model'!BU50 -> 56.879453 | L36: ='WH Model'!BV50 -> 56.470676 | M36: ='WH Model'!BW50 -> 55.962029 | N36: ='WH Model'!BX50 -> 55.407533
F37: Net Debt | G37: ='WH Model'!BQ57 -> 647.05775 | H37: ='WH Model'!BR57 -> 247.9245 | I37: ='WH Model'!BS57 -> 492.52625 | J37: ='WH Model'!BT57 -> 1110.5345 | K37: ='WH Model'!BU57 -> 2653.2905 | L37: ='WH Model'!BV57 -> 2690.5977 | M37: ='WH Model'!BW57 -> 2716.0026 | N37: ='WH Model'!BX57 -> 2742.4803
F38: Adj. TEV | G38: =G37+$D$9 -> 12929.351 | H38: =H37+$D$9 -> 12530.218 | I38: =I37+$D$9 -> 12774.82 | J38: =J37+$D$9 -> 13392.828 | K38: =K37+$D$9 -> 14935.584 | L38: =L37+$D$9 -> 14972.891 | M38: =M37+$D$9 -> 14998.296 | N38: =N37+$D$9 -> 15024.774

Sheet WH Model
A1: COKE | F1: 16 | G1: =F1 -> 16 | H1: =G1 -> 16 | I1: =H1 -> 16 | J1: =I1+1 -> 17 | K1: =J1 -> 17 | L1: =K1 -> 17 | M1: =L1 -> 17 | N1: =M1+1 -> 18 | O1: =N1 -> 18 | P1: =O1 -> 18 | Q1: =P1 -> 18 | R1: =Q1+1 -> 19 | S1: =R1 -> 19 | T1: =S1 -> 19 | U1: =T1 -> 19 | V1: =U1+1 -> 20 | W1: =V1 -> 20 | X1: =W1 -> 20 | Y1: =X1 -> 20 | Z1: =Y1+1 -> 21 | AA1: =Z1 -> 21 | AB1: =AA1 -> 21 | AC1: =AB1 -> 21 | AD1: =AC1+1 -> 22 | AE1: =AD1 -> 22 | AF1: =AE1 -> 22 | AG1: =AF1 -> 22 | AH1: =AG1+1 -> 23 | AI1: =AH1 -> 23 | AJ1: =AI1 -> 23 | AK1: =AJ1 -> 23 | AL1: =AK1+1 -> 24 | AM1: =AL1 -> 24 | AN1: =AM1 -> 24 | AO1: =AN1 -> 24 | AP1: =AO1+1 -> 25 | AQ1: =AP1 -> 25 | AR1: =AQ1 -> 25 | AS1: =AR1 -> 25 | AT1: =AS1+1 -> 26 | AU1: =AT1 -> 26 | AV1: =AU1 -> 26 | AW1: =AV1 -> 26 | AX1: =AW1+1 -> 27 | AY1: =AX1 -> 27 | AZ1: =AY1 -> 27 | BA1: =AZ1 -> 27 | BB1: =BA1+1 -> 28 | BC1: =BB1 -> 28 | BD1: =BC1 -> 28 | BE1: =BD1 -> 28 | BF1: =BE1+1 -> 29 | BG1: =BF1 -> 29 | BH1: =BG1 -> 29 | BI1: =BH1 -> 29 | BK1: 16 | BL1: 17 | BM1: 18 | BN1: 19 | BO1: 20 | BP1: 21 | BQ1: 22 | BR1: 23 | BS1: 24 | BT1: 25 | BU1: 26 | BV1: 27 | BW1: 28 | BX1: 29
A2: Coca-Cola Consolidated, Inc. | F2: Q1 | G2: Q2 | H2: Q3 | I2: Q4 | J2: =F2 -> Q1 | K2: =G2 -> Q2 | L2: =H2 -> Q3 | M2: =I2 -> Q4 | N2: =J2 -> Q1 | O2: =K2 -> Q2 | P2: =L2 -> Q3 | Q2: =M2 -> Q4 | ... BI2: =BE2 -> Q4 | BK2: Q4 | BL2: Q4 | BM2: Q4 | BN2: Q4 | BO2: Q4 | BP2: Q4 | BQ2: Q4 | BR2: Q4 | BS2: Q4 | BT2: Q4 | BU2: Q4 | BV2: Q4 | BW2: Q4 | BX2: Q4
A3: ($ in mm, except per share values) | F3: 90 | G3: 91 | H3: 92 | I3: 92 | J3: 90 | K3: 91 | L3: 92 | M3: 92 | N3: 90 | O3: 91 | P3: 92 | Q3: 92 | R3: 90 | S3: 91 | T3: 92 | U3: 92 | V3: 90 | W3: 91 | X3: 92 | Y3: 92 | Z3: 90 | AA3: 91 | AB3: 92 | AC3: 92 | AD3: 90 | AE3: 91 | AF3: 92 | AG3: 92 | AH3: 90 | AI3: 91 | AJ3: 92 | AK3: 92 | AL3: 90 | AM3: 91 | AN3: 92 | AO3: 92 | AP3: 90 | AQ3: 91 | AR3: 92 | AS3: 92 | AT3: 90 | AU3: 91 | AV3: 92 | AW3: 92 | AX3: 90 | AY3: 91 | AZ3: 92 | BA3: 92 | BB3: 90 | BC3: 91 | BD3: 92 | BE3: 92 | BF3: 90 | BG3: 91 | BH3: 92 | BI3: 92
F4: 42460 | G4: =EOMONTH(F4,3) -> 42551 | H4: =EOMONTH(G4,3) -> 42643 | I4: =EOMONTH(H4,3) -> 42735 | J4: =EOMONTH(I4,3) -> 42825 | K4: =EOMONTH(J4,3) -> 42916 | L4: =EOMONTH(K4,3) -> 43008 | M4: =EOMONTH(L4,3) -> 43100 | N4: =EOMONTH(M4,3) -> 43190 | ... BI4: =EOMONTH(BH4,3) -> 47483
F5: Q1 16 | G5: =G2&" "&G1 -> Q2 16 | H5: =H2&" "&H1 -> Q3 16 | I5: =I2&" "&I1 -> Q4 16 | J5: =J2&" "&J1 -> Q1 17 | K5: =K2&" "&K1 -> Q2 17 | L5: =L2&" "&L1 -> Q3 17 | M5: =M2&" "&M1 -> Q4 17 | N5: =N2&" "&N1 -> Q1 18 | ... BI5: =BI2&" "&BI1 -> Q4 29 | BK5: 2016 | BL5: 2017 | BM5: 2018 | BN5: 2019 | BO5: 2020 | BP5: 2021 | BQ5: 2022 | BR5: 2023 | BS5: 2024 | BT5: 2025 | BU5: 2026 | BV5: 2027 | BW5: 2028 | BX5: 2029
A6: x | B6: Drivers
B7: Tax Rate | F7: =F25/F24 -> 0.3598611 | G7: =G25/G24 -> 0.38044489 | H7: =H25/H24 -> 0.33927186 | I7: =I25/I24 -> 0.43217956 | J7: =J25/J24 -> 0.4552294 | K7: =K25/K24 -> 0.33053691 | L7: =L25/L24 -> 0.38318275 | M7: =M25/M24 -> -1.7727164 | ... AS7: =AS25/AS24 -> 0.27081175 | AT7: 0.25 | AU7: 0.25 | AV7: 0.25 | AW7: 0.25 | AX7: 0.25 | AY7: 0.25 | AZ7: 0.25 | BA7: 0.25 | BB7: 0.25 | BC7: 0.25 | BD7: 0.25 | BE7: 0.25 | BF7: 0.25 | BG7: 0.25 | BH7: 0.25 | BI7: 0.25 | BK7: =BK25/BK24 -> 0.38882777 | BL7: =BL25/BL24 -> -0.6323366 | BM7: =BM25/BM24 -> -0.14066381 | BN7: =BN25/BN24 -> 0.45770636 | BO7: =BO25/BO24 -> 0.24453618 | BP7: =BP25/BP24 -> 0.25698317 | BQ7: =BQ25/BQ24 -> 0.2520123 | BR7: =BR25/BR24 -> 0.26746382 | ... BX7: =BX25/BX24 -> 0.25
B8: SBC % of Rev | F8: =F32/F17 -> 0.0026013021 | G8: =G32/G17 -> 0.001510024 | H8: =H32/H17 -> 0.0018244392 | I8: =I32/I17 -> 0.0032190218 | J8: =J32/J17 -> 0.0023795717 | K8: =K32/K17 -> 0.0021525865 | L8: =L32/L17 -> 0.0016309313 | M8: =M32/M17 -> 0.0012866859 | ... AS8: =AS32/AS17 -> 0 | AT8: 0 | AU8: 0 | AV8: 0 | AW8: 0 | AX8: 0 | AY8: 0 | AZ8: 0 | BA8: 0 | BB8: 0 | BC8: 0 | BD8: 0 | BE8: 0 | BF8: 0 | BG8: 0 | BH8: 0 | BI8: 0 | BK8: =BK32/BK17 -> 0.002266486 | BL8: =BL32/BL17 -> 0.0018322406 | BM8: =BM32/BM17 -> 0.0012120127 | BN8: =BN32/BN17 -> 0.00042369817 | BO8: =BO32/BO17 -> 0 | BP8: =BP32/BP17 -> 0 | BQ8: =BQ32/BQ17 -> 0 | BR8: =BR32/BR17 -> 0 | ... BX8: =BX32/BX17 -> 0
B9: D&A % of Rev | F9: =F33/F17 -> 0.03899395 | G9: =G33/G17 -> 0.033246706 | H9: =H33/H17 -> 0.036579477 | I9: =I33/I17 -> 0.03949451 | J9: =J33/J17 -> 0.040407669 | K9: =K33/K17 -> 0.035975647 | L9: =L33/L17 -> 0.037200028 | M9: =M33/M17 -> 0.043109748 | ... AS9: =AS33/AS17 -> 0.029043577 | AT9: =AP9 -> 0.033780871 | AU9: =AQ9 -> 0.029514653 | AV9: =AR9 -> 0.029172009 | AW9: =AS9 -> 0.029043577 | AX9: =AT9 -> 0.033780871 | AY9: =AU9 -> 0.029514653 | AZ9: =AV9 -> 0.029172009 | BA9: =AW9 -> 0.029043577 | ... BI9: =BE9 -> 0.029043577 | BK9: =BK33/BK17 -> 0.036947778 | BL9: =BL33/BL17 -> 0.039050408 | BM9: =BM33/BM17 -> 0.040484598 | BN9: =BN33/BN17 -> 0.037276323 | BO9: =BO33/BO17 -> 0.035750796 | BP9: =BP33/BP17 -> 0.032459875 | BQ9: =BQ33/BQ17 -> 0.027671535 | BR9: =BR33/BR17 -> 0.026595999 | ... BX9: =BX33/BX17 -> 0.030317214
B10: Change in NWC % of Rev | F10: =F64/F17 -> -0.072414366 | G10: =G64/G17 -> 0.0088078783 | H10: =H64/H17 -> 0.0097405504 | I10: =I64/I17 -> -0.042424783 | J10: =J64/J17 -> -0.0011713038 | K10: =K64/K17 -> 0.0018199063 | L10: =L64/L17 -> -0.032074121 | M10: =M64/M17 -> 0.015465094 | ... AS10: =AS64/AS17 -> -0.013792365 | AT10: =AP10 -> -0.024698461 | AU10: =AQ10 -> 0.0038630701 | AV10: =AR10 -> 0.027175522 | AW10: =AS10 -> -0.013792365 | AX10: =AT10 -> -0.024698461 | AY10: =AU10 -> 0.0038630701 | AZ10: =AV10 -> 0.027175522 | BA10: =AW10 -> -0.013792365 | ... BI10: =BE10 -> -0.013792365 | BK10: =BK64/BK17 -> -0.020695229 | BL10: =BL64/BL17 -> -0.0043382147 | BM10: =BM64/BM17 -> -0.010196387 | BN10: =BN64/BN17 -> -0.0049068185 | BO10: =BO64/BO17 -> 0.01559066 | BP10: =BP64/BP17 -> 0.0041113025 | BQ10: =BQ64/BQ17 -> -0.012326323 | BR10: =BR64/BR17 -> -0.00089451864 | ... BX10: =BX64/BX17 -> -0.0015017027
B11: Adj. EBITDA Margins % | F11: =IF(F17=0,0,F35/F17) -> 0.061422386 | G11: =IF(G17=0,0,G35/G17) -> 0.09988886 | H11: =IF(H17=0,0,H35/H17) -> 0.085282229 | I11: =IF(I17=0,0,I35/I17) -> 0.067573316 | J11: =IF(J17=0,0,J35/J17) -> 0.058506276 | K11: =IF(K17=0,0,K35/K17) -> 0.078591215 | L11: =IF(L17=0,0,L35/L17) -> 0.069909834 | M11: =IF(M17=0,0,M35/M17) -> 0.043622114 | ... BI11: =IF(BI17=0,0,BI35/BI17) -> 0.11630295 | BK11: =BK35/BK17 -> 0.079721761 | BL11: =BL35/BL17 -> 0.063127419 | BM11: =BM35/BM17 -> 0.054214976 | BN11: =BN35/BN17 -> 0.075149967 | BO11: =BO35/BO17 -> 0.098334311 | BP11: =BP35/BP17 -> 0.11140893 | BQ11: =BQ35/BQ17 -> 0.13105026 | BR11: =BR35/BR17 -> 0.1520046 | ... BX11: =BX35/BX17 -> 0.11688211
B12: Gross Profit Margin % | F12: =F19/F17 -> 0.38995229 | G12: =G19/G17 -> 0.38042966 | H12: =H19/H17 -> 0.38537009 | I12: =I19/I17 -> 0.38610081 | J12: =J19/J17 -> 0.38352805 | K12: =K19/K17 -> 0.35506816 | L12: =L19/L17 -> 0.35295899 | M12: =M19/M17 -> 0.3404736 | ... BI12: =BI19/BI17 -> 0.3751909 | BK12: =BK41/BK17 -> 0.38515753 | BL12: =BL41/BL17 -> 0.35639809 | BM12: =BM41/BM17 -> 0.33634369 | BN12: =BN41/BN17 -> 0.34610692 | BO12: =BO41/BO17 -> 0.35326201 | BP12: =BP41/BP17 -> 0.351301 | BQ12: =BQ41/BQ17 -> 0.36735523 | BR12: =BR41/BR17 -> 0.39055703 | ... BX12: =BX41/BX17 -> 0.36492837
B13: SD&A % of Rev | J13: =J20/F20-1 -> 0.37545195 | K13: =K20/G20-1 -> 0.38832174 | L13: =L20/H20-1 -> 0.30204705 | M13: =M20/I20-1 -> 0.26410663 | N13: =N20/J20-1 -> 0.18286 | O13: =O20/K20-1 -> 0.046658421 | P13: =P20/L20-1 -> -0.015719119 | Q13: =Q20/M20-1 -> -0.042844578 | ... AS13: =AS20/AO20-1 -> 0.068881816 | AT13: 0.035 | AU13: 0.035 | AV13: 0.035 | AW13: 0.035 | AX13: 0.035 | AY13: 0.035 | AZ13: 0.035 | BA13: 0.035 | BB13: 0.035 | BC13: 0.035 | BD13: 0.035 | BE13: 0.035 | BF13: 0.035 | BG13: 0.035 | BH13: 0.035 | BI13: 0.035 | BK13: =BK20/BK17 -> 0.34465003 | BL13: =BL20/BL17 -> 0.33415332 | BM13: =BM20/BM17 -> 0.32382532 | BN13: =BN20/BN17 -> 0.30865697 | BO13: =BO20/BO17 -> 0.2906785 | BP13: =BP20/BP17 -> 0.27235195 | BQ13: =BQ20/BQ17 -> 0.26397651 | BR13: =BR20/BR17 -> 0.26514843 | ... BX13: =BX20/BX17 -> 0.27836348
B14: Interest Rate % | F14: =F22*4/F55 -> 0.045994689 | G14: =G22*4/G55 -> 0.044474977 | H14: =H22*4/H55 -> 0.038834416 | I14: =I22*4/I55 -> 0.036419362 | J14: =J22*4/J55 -> 0.036103629 | K14: =K22*4/K55 -> 0.037100081 | L14: =L22*4/L55 -> 0.036540521 | M14: =M22*4/M55 -> 0.039813096 | ... AS14: =AS22*4/AS55 -> 0.036113673 | AT14: 0.06 | AU14: 0.06 | AV14: 0.06 | AW14: 0.06 | AX14: 0.06 | AY14: 0.06 | AZ14: 0.06 | BA14: 0.06 | BB14: 0.06 | BC14: 0.06 | BD14: 0.06 | BE14: 0.06 | BF14: 0.06 | BG14: 0.06 | BH14: 0.06 | BI14: 0.06 | BK14: =BK22/BK58 -> 0.043182859 | BL14: =BL22/BL58 -> 0.038297832 | BM14: =BM22/BM58 -> 0.042593573 | BN14: =BN22/BN58 -> 0.042014398 | BO14: =BO22/BO58 -> 0.038672736 | BP14: =BP22/BP58 -> 0.043718182 | BQ14: =BQ22/BQ58 -> 0.049323719 | BR14: =BR22/BR58 -> -0.0080125687 | ... BX14: =BX22/BX58 -> 0.06376884
A16: x | B16: GAAP P&L
B17: Revenue | F17: ='Canalyst HC - Q'!C401 -> 625.456 | G17: ='Canalyst HC - Q'!D401 -> 840.384 | H17: ='Canalyst HC - Q'!E401 -> 849.028 | I17: ='Canalyst HC - Q'!F401 -> 841.56 | J17: ='Canalyst HC - Q'!G401 -> 865.702 | K17: ='Canalyst HC - Q'!H401 -> 1169.291 | L17: ='Canalyst HC - Q'!I401 -> 1162.526 | M17: ='Canalyst HC - Q'!J401 -> 1126.149 | ... AS17: ='Canalyst HC - Q'!AP401 -> 1904.242 | AT17: ='Segment Build'!AT8 -> 1758.8331 | AU17: ='Segment Build'!AU8 -> 1859.8329 | AV17: ='Segment Build'!AV8 -> 1893.0011 | AW17: ='Segment Build'!AW8 -> 1909.1116 | AX17: ='Segment Build'!AX8 -> 1811.9216 | AY17: ='Segment Build'!AY8 -> 1915.9691 | AZ17: ='Segment Build'!AZ8 -> 1950.1364 | BA17: ='Segment Build'!BA8 -> 1966.7323 | ... BI17: ='Segment Build'!BI8 -> 2087.2437 | BK17: =SUMIF($F$1:$BI$1,BK$1,$F17:$BI17) -> 3156.428 | BL17: =SUMIF($F$1:$BI$1,BL$1,$F17:$BI17) -> 4323.668 | BM17: =SUMIF($F$1:$BI$1,BM$1,$F17:$BI17) -> 4625.364 | BN17: =SUMIF($F$1:$BI$1,BN$1,$F17:$BI17) -> 4826.549 | BO17: =SUMIF($F$1:$BI$1,BO$1,$F17:$BI17) -> 5007.357 | BP17: =SUMIF($F$1:$BI$1,BP$1,$F17:$BI17) -> 5562.714 | BQ17: =SUMIF($F$1:$BI$1,BQ$1,$F17:$BI17) -> 6200.957 | BR17: =SUMIF($F$1:$BI$1,BR$1,$F17:$BI17) -> 6653.858 | ... BX17: =SUMIF($F$1:$BI$1,BX$1,$F17:$BI17) -> 8113.2062
C18: COGS | F18: ='Canalyst HC - Q'!C404 -> 381.558 | G18: ='Canalyst HC - Q'!D404 -> 520.677 | H18: ='Canalyst HC - Q'!E404 -> 521.838 | I18: ='Canalyst HC - Q'!F404 -> 516.633 | J18: ='Canalyst HC - Q'!G404 -> 533.681 | K18: ='Canalyst HC - Q'!H404 -> 754.113 | L18: ='Canalyst HC - Q'!I404 -> 752.202 | M18: ='Canalyst HC - Q'!J404 -> 742.725 | ... AS18: ='Canalyst HC - Q'!AP404 -> 1149.996 | AT18: ='COGS Sensitivity'!AT7 -> 1129.9912 | AU18: ='COGS Sensitivity'!AU7 -> 1196.7167 | AV18: ='COGS Sensitivity'!AV7 -> 1206.5883 | AW18: ='COGS Sensitivity'!AW7 -> 1203.4099 | AX18: ='COGS Sensitivity'!AX7 -> 1177.6653 | AY18: ='COGS Sensitivity'!AY7 -> 1222.2684 | AZ18: ='COGS Sensitivity'!AZ7 -> 1230.3595 | BA18: ='COGS Sensitivity'!BA7 -> 1223.1996 | ... BI18: ='COGS Sensitivity'!BI7 -> 1304.1289 | BK18: =SUMIF($F$1:$BI$1,BK$1,$F18:$BI18) -> 1940.706 | BL18: =SUMIF($F$1:$BI$1,BL$1,$F18:$BI18) -> 2782.721 | BM18: =SUMIF($F$1:$BI$1,BM$1,$F18:$BI18) -> 3069.652 | BN18: =SUMIF($F$1:$BI$1,BN$1,$F18:$BI18) -> 3156.047 | BO18: =SUMIF($F$1:$BI$1,BO$1,$F18:$BI18) -> 3238.448 | BP18: =SUMIF($F$1:$BI$1,BP$1,$F18:$BI18) -> 3608.527 | BQ18: =SUMIF($F$1:$BI$1,BQ$1,$F18:$BI18) -> 3923.003 | BR18: =SUMIF($F$1:$BI$1,BR$1,$F18:$BI18) -> 4055.147 | ... BX18: =SUMIF($F$1:$BI$1,BX$1,$F18:$BI18) -> 5152.4671
B19: Gross Profit | F19: =F17-F18 -> 243.898 | G19: =G17-G18 -> 319.707 | H19: =H17-H18 -> 327.19 | I19: =I17-I18 -> 324.927 | J19: =J17-J18 -> 332.021 | K19: =K17-K18 -> 415.178 | L19: =L17-L18 -> 410.324 | M19: =M17-M18 -> 383.424 | ... BI19: =BI17-BI18 -> 783.11485 | BK19: =SUMIF($F$1:$BI$1,BK$1,$F19:$BI19) -> 1215.722 | BL19: =SUMIF($F$1:$BI$1,BL$1,$F19:$BI19) -> 1540.947 | BM19: =SUMIF($F$1:$BI$1,BM$1,$F19:$BI19) -> 1555.712 | BN19: =SUMIF($F$1:$BI$1,BN$1,$F19:$BI19) -> 1670.502 | BO19: =SUMIF($F$1:$BI$1,BO$1,$F19:$BI19) -> 1768.909 | BP19: =SUMIF($F$1:$BI$1,BP$1,$F19:$BI19) -> 1954.187 | BQ19: =SUMIF($F$1:$BI$1,BQ$1,$F19:$BI19) -> 2277.954 | BR19: =SUMIF($F$1:$BI$1,BR$1,$F19:$BI19) -> 2598.711 | ... BX19: =SUMIF($F$1:$BI$1,BX$1,$F19:$BI19) -> 2960.7391
C20: SD&A | F20: ='Canalyst HC - Q'!C407 -> 231.497 | G20: ='Canalyst HC - Q'!D407 -> 264.971 | H20: ='Canalyst HC - Q'!E407 -> 287.389 | I20: ='Canalyst HC - Q'!F407 -> 304.006 | J20: ='Canalyst HC - Q'!G407 -> 318.413 | K20: ='Canalyst HC - Q'!H407 -> 367.865 | L20: ='Canalyst HC - Q'!I407 -> 374.194 | M20: ='Canalyst HC - Q'!J407 -> 384.296 | ... AS20: ='Canalyst HC - Q'!AP407 -> 512.128 | AT20: =AP20*(1+AT13)+12 -> 464.58894 | AU20: =AQ20*(1+AU13)+12 -> 498.87642 | AV20: =AR20*(1+AV13)+12 -> 531.44787 | AW20: =AS20*(1+AW13)+12 -> 542.05248 | AX20: =AT20*(1+AX13) -> 480.84955 | AY20: =AU20*(1+AY13) -> 516.33709 | AZ20: =AV20*(1+AZ13) -> 550.04855 | BA20: =AW20*(1+BA13) -> 561.02432 | BB20: =AX20*(1+BB13) -> 497.67929 | BC20: =AY20*(1+BC13) -> 534.40889 | BD20: =AZ20*(1+BD13) -> 569.30024 | BE20: =BA20*(1+BE13) -> 580.66017 | ... BI20: =BE20*(1+BI13) -> 600.98327 | BK20: =SUMIF($F$1:$BI$1,BK$1,$F20:$BI20) -> 1087.863 | BL20: =SUMIF($F$1:$BI$1,BL$1,$F20:$BI20) -> 1444.768 | BM20: =SUMIF($F$1:$BI$1,BM$1,$F20:$BI20) -> 1497.81 | BN20: =SUMIF($F$1:$BI$1,BN$1,$F20:$BI20) -> 1489.748 | BO20: =SUMIF($F$1:$BI$1,BO$1,$F20:$BI20) -> 1455.531 | BP20: =SUMIF($F$1:$BI$1,BP$1,$F20:$BI20) -> 1515.016 | BQ20: =SUMIF($F$1:$BI$1,BQ$1,$F20:$BI20) -> 1636.907 | BR20: =SUMIF($F$1:$BI$1,BR$1,$F20:$BI20) -> 1764.26 | ... BX20: =SUMIF($F$1:$BI$1,BX$1,$F20:$BI20) -> 2258.4203
B21: EBIT | F21: =F19-F20 -> 12.401 | G21: =G19-G20 -> 54.736 | H21: =H19-H20 -> 39.801 | I21: =I19-I20 -> 20.921 | J21: =J19-J20 -> 13.608 | K21: =K19-K20 -> 47.313 | L21: =L19-L20 -> 36.13 | M21: =M19-M20 -> -0.872 | ... BI21: =BI19-BI20 -> 182.13158 | BK21: =SUMIF($F$1:$BI$1,BK$1,$F21:$BI21) -> 127.859 | BL21: =SUMIF($F$1:$BI$1,BL$1,$F21:$BI21) -> 96.179 | BM21: =SUMIF($F$1:$BI$1,BM$1,$F21:$BI21) -> 57.902 | BN21: =SUMIF($F$1:$BI$1,BN$1,$F21:$BI21) -> 180.754 | BO21: =SUMIF($F$1:$BI$1,BO$1,$F21:$BI21) -> 313.378 | BP21: =SUMIF($F$1:$BI$1,BP$1,$F21:$BI21) -> 439.171 | BQ21: =SUMIF($F$1:$BI$1,BQ$1,$F21:$BI21) -> 641.047 | BR21: =SUMIF($F$1:$BI$1,BR$1,$F21:$BI21) -> 834.451 | ... BX21: =SUMIF($F$1:$BI$1,BX$1,$F21:$BI21) -> 702.31882
C22: Interest Expense / (Income) | F22: ='Canalyst HC - Q'!C419 -> 9.361 | G22: ='Canalyst HC - Q'!D419 -> 9.808 | H22: ='Canalyst HC - Q'!E419 -> 8.452 | I22: ='Canalyst HC - Q'!F419 -> 8.704 | J22: ='Canalyst HC - Q'!G419 -> 9.47 | K22: ='Canalyst HC - Q'!H419 -> 10.44 | L22: ='Canalyst HC - Q'!I419 -> 10.697 | M22: ='Canalyst HC - Q'!J419 -> 11.262 | ... AS22: ='Canalyst HC - Q'!AP419 -> 25.169 | AT22: =AT14*AS55/4 -> 41.816295 | AU22: =AU14*AT55/4 -> 41.816295 | AV22: =AV14*AU55/4 -> 41.816295 | AW22: =AW14*AV55/4 -> 41.816295 | AX22: =AX14*AW55/4 -> 41.816295 | AY22: =AY14*AX55/4 -> 41.816295 | AZ22: =AZ14*AY55/4 -> 41.816295 | BA22: =BA14*AZ55/4 -> 41.816295 | ... BI22: =BI14*BH55/4 -> 41.816295 | BK22: =SUMIF($F$1:$BI$1,BK$1,$F22:$BI22) -> 36.325 | BL22: =SUMIF($F$1:$BI$1,BL$1,$F22:$BI22) -> 41.869 | BM22: =SUMIF($F$1:$BI$1,BM$1,$F22:$BI22) -> 50.506 | BN22: =SUMIF($F$1:$BI$1,BN$1,$F22:$BI22) -> 45.99 | BO22: =SUMIF($F$1:$BI$1,BO$1,$F22:$BI22) -> 36.735 | BP22: =SUMIF($F$1:$BI$1,BP$1,$F22:$BI22) -> 33.449 | BQ22: =SUMIF($F$1:$BI$1,BQ$1,$F22:$BI22) -> 24.792 | BR22: =SUMIF($F$1:$BI$1,BR$1,$F22:$BI22) -> -0.918 | ... BX22: =SUMIF($F$1:$BI$1,BX$1,$F22:$BI22) -> 167.26518
C23: Other | F23: ='Canalyst HC - Q'!C420+'Canalyst HC - Q'!C421 -> 17.151 | G23: ='Canalyst HC - Q'!D420+'Canalyst HC - Q'!D421 -> 16.966 | H23: ='Canalyst HC - Q'!E420+'Canalyst HC - Q'!E421 -> -7.325 | I23: ='Canalyst HC - Q'!F420+'Canalyst HC - Q'!F421 -> -27.97 | J23: ='Canalyst HC - Q'!G420+'Canalyst HC - Q'!G421 -> 12.246 | K23: ='Canalyst HC - Q'!H420+'Canalyst HC - Q'!H421 -> 25.549 | L23: ='Canalyst HC - Q'!I420+'Canalyst HC - Q'!I421 -> -5.226 | M23: ='Canalyst HC - Q'!J420+'Canalyst HC - Q'!J421 -> -41.265 | ... AS23: ='Canalyst HC - Q'!AP420+'Canalyst HC - Q'!AP421 -> 28.726 | AT23: =AP23 -> 43.473 | AU23: =AQ23 -> 13.144 | AV23: =AR23 -> 49.717 | AW23: =AS23 -> 28.726 | AX23: =AT23 -> 43.473 | AY23: =AU23 -> 13.144 | AZ23: =AV23 -> 49.717 | BA23: =AW23 -> 28.726 | ... BI23: =BE23 -> 28.726 | BK23: =SUMIF($F$1:$BI$1,BK$1,$F23:$BI23) -> -1.178 | BL23: =SUMIF($F$1:$BI$1,BL$1,$F23:$BI23) -> -8.696 | BM23: =SUMIF($F$1:$BI$1,BM$1,$F23:$BI23) -> 20.683 | BN23: =SUMIF($F$1:$BI$1,BN$1,$F23:$BI23) -> 100.539 | BO23: =SUMIF($F$1:$BI$1,BO$1,$F23:$BI23) -> 35.603 | BP23: =SUMIF($F$1:$BI$1,BP$1,$F23:$BI23) -> 150.573 | BQ23: =SUMIF($F$1:$BI$1,BQ$1,$F23:$BI23) -> 41.168 | BR23: =SUMIF($F$1:$BI$1,BR$1,$F23:$BI23) -> 277.888 | ... BX23: =SUMIF($F$1:$BI$1,BX$1,$F23:$BI23) -> 135.06
B24: EBT | F24: =F21-SUM(F22:F23) -> -14.111 | G24: =G21-SUM(G22:G23) -> 27.962 | H24: =H21-SUM(H22:H23) -> 38.674 | I24: =I21-SUM(I22:I23) -> 40.187 | J24: =J21-SUM(J22:J23) -> -8.108 | K24: =K21-SUM(K22:K23) -> 11.324 | L24: =L21-SUM(L22:L23) -> 30.659 | M24: =M21-SUM(M22:M23) -> 29.131 | ... BI24: =BI21-SUM(BI22:BI23) -> 111.58928 | BK24: =SUMIF($F$1:$BI$1,BK$1,$F24:$BI24) -> 92.712 | BL24: =SUMIF($F$1:$BI$1,BL$1,$F24:$BI24) -> 63.006 | BM24: =SUMIF($F$1:$BI$1,BM$1,$F24:$BI24) -> -13.287 | BN24: =SUMIF($F$1:$BI$1,BN$1,$F24:$BI24) -> 34.225 | BO24: =SUMIF($F$1:$BI$1,BO$1,$F24:$BI24) -> 241.04 | BP24: =SUMIF($F$1:$BI$1,BP$1,$F24:$BI24) -> 255.149 | BQ24: =SUMIF($F$1:$BI$1,BQ$1,$F24:$BI24) -> 575.087 | BR24: =SUMIF($F$1:$BI$1,BR$1,$F24:$BI24) -> 557.481 | ... BX24: =SUMIF($F$1:$BI$1,BX$1,$F24:$BI24) -> 399.99364
C25: Taxes | F25: ='Canalyst HC - Q'!C424+'Canalyst HC - Q'!C425 -> -5.078 | G25: ='Canalyst HC - Q'!D424+'Canalyst HC - Q'!D425 -> 10.638 | H25: ='Canalyst HC - Q'!E424+'Canalyst HC - Q'!E425 -> 13.121 | I25: ='Canalyst HC - Q'!F424+'Canalyst HC - Q'!F425 -> 17.368 | J25: ='Canalyst HC - Q'!G424+'Canalyst HC - Q'!G425 -> -3.691 | K25: ='Canalyst HC - Q'!H424+'Canalyst HC - Q'!H425 -> 3.743 | L25: ='Canalyst HC - Q'!I424+'Canalyst HC - Q'!I425 -> 11.748 | M25: ='Canalyst HC - Q'!J424+'Canalyst HC - Q'!J425 -> -51.641 | ... AS25: ='Canalyst HC - Q'!AP424+'Canalyst HC - Q'!AP425 -> 50.973 | AT25: =AT24*AT7 -> 19.740916 | AU25: =AU24*AU7 -> 27.319891 | AV25: =AV24*AV7 -> 15.857912 | AW25: =AW24*AW7 -> 23.276717 | AX25: =AX24*AX7 -> 17.029354 | AY25: =AY24*AY7 -> 30.60084 | AZ25: =AZ24*AZ7 -> 19.548766 | BA25: =BA24*BA7 -> 27.991521 | ... BI25: =BI24*BI7 -> 27.89732 | BK25: =SUMIF($F$1:$BI$1,BK$1,$F25:$BI25) -> 36.049 | BL25: =SUMIF($F$1:$BI$1,BL$1,$F25:$BI25) -> -39.841 | BM25: =SUMIF($F$1:$BI$1,BM$1,$F25:$BI25) -> 1.869 | BN25: =SUMIF($F$1:$BI$1,BN$1,$F25:$BI25) -> 15.665 | BO25: =SUMIF($F$1:$BI$1,BO$1,$F25:$BI25) -> 58.943 | BP25: =SUMIF($F$1:$BI$1,BP$1,$F25:$BI25) -> 65.569 | BQ25: =SUMIF($F$1:$BI$1,BQ$1,$F25:$BI25) -> 144.929 | BR25: =SUMIF($F$1:$BI$1,BR$1,$F25:$BI25) -> 149.106 | ... BX25: =SUMIF($F$1:$BI$1,BX$1,$F25:$BI25) -> 99.99841
B26: Net Income | F26: ='Canalyst HC - Q'!C426 -> -9.033 | G26: ='Canalyst HC - Q'!D426 -> 17.324 | H26: ='Canalyst HC - Q'!E426 -> 25.553 | I26: ='Canalyst HC - Q'!F426 -> 22.819 | J26: ='Canalyst HC - Q'!G426 -> -4.417 | K26: ='Canalyst HC - Q'!H426 -> 7.581 | L26: ='Canalyst HC - Q'!I426 -> 18.911 | M26: ='Canalyst HC - Q'!J426 -> 80.772 | ... AS26: ='Canalyst HC - Q'!AP426 -> 137.25 | AT26: =AT24-AT25 -> 59.222747 | AU26: =AU24-AU25 -> 81.959673 | AV26: =AV24-AV25 -> 47.573735 | AW26: =AW24-AW25 -> 69.830151 | AX26: =AX24-AX25 -> 51.088062 | AY26: =AY24-AY25 -> 91.80252 | AZ26: =AZ24-AZ25 -> 58.646299 | BA26: =BA24-BA25 -> 83.974563 | ... BI26: =BI24-BI25 -> 83.691961 | BK26: =SUMIF($F$1:$BI$1,BK$1,$F26:$BI26) -> 56.663 | BL26: =SUMIF($F$1:$BI$1,BL$1,$F26:$BI26) -> 102.847 | BM26: =SUMIF($F$1:$BI$1,BM$1,$F26:$BI26) -> -15.156 | BN26: =SUMIF($F$1:$BI$1,BN$1,$F26:$BI26) -> 18.56 | BO26: =SUMIF($F$1:$BI$1,BO$1,$F26:$BI26) -> 182.097 | BP26: =SUMIF($F$1:$BI$1,BP$1,$F26:$BI26) -> 189.58 | BQ26: =SUMIF($F$1:$BI$1,BQ$1,$F26:$BI26) -> 430.158 | BR26: =SUMIF($F$1:$BI$1,BR$1,$F26:$BI26) -> 408.375 | ... BX26: =SUMIF($F$1:$BI$1,BX$1,$F26:$BI26) -> 299.99523
C27: discontinued operations | F27: ='Canalyst HC - Q'!C427 -> 0 | G27: ='Canalyst HC - Q'!D427 -> 0 | H27: ='Canalyst HC - Q'!E427 -> 0 | I27: ='Canalyst HC - Q'!F427 -> 0 | J27: ='Canalyst HC - Q'!G427 -> 0 | K27: ='Canalyst HC - Q'!H427 -> 0 | L27: ='Canalyst HC - Q'!I427 -> 0 | M27: ='Canalyst HC - Q'!J427 -> 0 | ... AS27: ='Canalyst HC - Q'!AP427 -> 0 | AT27: =0 -> 0 | AU27: =0 -> 0 | AV27: =0 -> 0 | AW27: =0 -> 0 | AX27: =0 -> 0 | AY27: =0 -> 0 | AZ27: =0 -> 0 | BA27: =0 -> 0 | ... BI27: =0 -> 0 | BK27: =SUMIF($F$1:$BI$1,BK$1,$F27:$BI27) -> 0 | BL27: =SUMIF($F$1:$BI$1,BL$1,$F27:$BI27) -> 0 | BM27: =SUMIF($F$1:$BI$1,BM$1,$F27:$BI27) -> 0 | BN27: =SUMIF($F$1:$BI$1,BN$1,$F27:$BI27) -> 0 | BO27: =SUMIF($F$1:$BI$1,BO$1,$F27:$BI27) -> 0 | BP27: =SUMIF($F$1:$BI$1,BP$1,$F27:$BI27) -> 0 | BQ27: =SUMIF($F$1:$BI$1,BQ$1,$F27:$BI27) -> 0 | BR27: =SUMIF($F$1:$BI$1,BR$1,$F27:$BI27) -> 0 | ... BX27: =SUMIF($F$1:$BI$1,BX$1,$F27:$BI27) -> 0
C28: NCI | F28: ='Canalyst HC - Q'!C428+'Canalyst HC - Q'!C429 -> -1.322 | G28: ='Canalyst HC - Q'!D428+'Canalyst HC - Q'!D429 -> 5.322 | H28: ='Canalyst HC - Q'!E428+'Canalyst HC - Q'!E429 -> 7.808 | I28: ='Canalyst HC - Q'!F428+'Canalyst HC - Q'!F429 -> 6.386 | J28: ='Canalyst HC - Q'!G428+'Canalyst HC - Q'!G429 -> -0.548 | K28: ='Canalyst HC - Q'!H428+'Canalyst HC - Q'!H429 -> 2.724 | L28: ='Canalyst HC - Q'!I428+'Canalyst HC - Q'!I429 -> 5.663 | M28: ='Canalyst HC - Q'!J428+'Canalyst HC - Q'!J429 -> 21.113 | ... AS28: ='Canalyst HC - Q'!AP428+'Canalyst HC - Q'!AP429 -> 18.05 | AT28: =0 -> 0 | AU28: =0 -> 0 | AV28: =0 -> 0 | AW28: =0 -> 0 | AX28: =0 -> 0 | AY28: =0 -> 0 | AZ28: =0 -> 0 | BA28: =0 -> 0 | ... BI28: =0 -> 0 | BK28: =SUMIF($F$1:$BI$1,BK$1,$F28:$BI28) -> 18.194 | BL28: =SUMIF($F$1:$BI$1,BL$1,$F28:$BI28) -> 28.952 | BM28: =SUMIF($F$1:$BI$1,BM$1,$F28:$BI28) -> 0.068 | BN28: =SUMIF($F$1:$BI$1,BN$1,$F28:$BI28) -> 9.89 | BO28: =SUMIF($F$1:$BI$1,BO$1,$F28:$BI28) -> 50.681 | BP28: =SUMIF($F$1:$BI$1,BP$1,$F28:$BI28) -> 45.146 | BQ28: =SUMIF($F$1:$BI$1,BQ$1,$F28:$BI28) -> 57.737 | BR28: =SUMIF($F$1:$BI$1,BR$1,$F28:$BI28) -> 43.782 | ... BX28: =SUMIF($F$1:$BI$1,BX$1,$F28:$BI28) -> 0
B29: Net Income to Common | F29: =F26-SUM(F27:F28) -> -7.711 | G29: =G26-SUM(G27:G28) -> 12.002 | H29: =H26-SUM(H27:H28) -> 17.745 | I29: =I26-SUM(I27:I28) -> 16.433 | J29: =J26-SUM(J27:J28) -> -3.869 | K29: =K26-SUM(K27:K28) -> 4.857 | L29: =L26-SUM(L27:L28) -> 13.248 | M29: =M26-SUM(M27:M28) -> 59.659 | ... BI29: =BI26-SUM(BI27:BI28) -> 83.691961 | BK29: =SUMIF($F$1:$BI$1,BK$1,$F29:$BI29) -> 38.469 | BL29: =SUMIF($F$1:$BI$1,BL$1,$F29:$BI29) -> 73.895 | BM29: =SUMIF($F$1:$BI$1,BM$1,$F29:$BI29) -> -15.224 | BN29: =SUMIF($F$1:$BI$1,BN$1,$F29:$BI29) -> 8.67 | BO29: =SUMIF($F$1:$BI$1,BO$1,$F29:$BI29) -> 131.416 | BP29: =SUMIF($F$1:$BI$1,BP$1,$F29:$BI29) -> 144.434 | BQ29: =SUMIF($F$1:$BI$1,BQ$1,$F29:$BI29) -> 372.421 | BR29: =SUMIF($F$1:$BI$1,BR$1,$F29:$BI29) -> 364.593 | ... BX29: =SUMIF($F$1:$BI$1,BX$1,$F29:$BI29) -> 299.99523
A31: x | B31: Adjustments / D&A / EBITDA
C32: SBC | F32: ='Canalyst HC - Q'!C414 -> 1.627 | G32: ='Canalyst HC - Q'!D414 -> 1.269 | H32: ='Canalyst HC - Q'!E414 -> 1.549 | I32: ='Canalyst HC - Q'!F414 -> 2.709 | J32: ='Canalyst HC - Q'!G414 -> 2.06 | K32: ='Canalyst HC - Q'!H414 -> 2.517 | L32: ='Canalyst HC - Q'!I414 -> 1.896 | M32: ='Canalyst HC - Q'!J414 -> 1.449 | ... AS32: ='Canalyst HC - Q'!AP414 -> 0 | AT32: =AT8*AT17 -> 0 | AU32: =AU8*AU17 -> 0 | AV32: =AV8*AV17 -> 0 | AW32: =AW8*AW17 -> 0 | AX32: =AX8*AX17 -> 0 | AY32: =AY8*AY17 -> 0 | AZ32: =AZ8*AZ17 -> 0 | BA32: =BA8*BA17 -> 0 | ... BI32: =BI8*BI17 -> 0 | BK32: =SUMIF($F$1:$BI$1,BK$1,$F32:$BI32) -> 7.154 | BL32: =SUMIF($F$1:$BI$1,BL$1,$F32:$BI32) -> 7.922 | BM32: =SUMIF($F$1:$BI$1,BM$1,$F32:$BI32) -> 5.606 | BN32: =SUMIF($F$1:$BI$1,BN$1,$F32:$BI32) -> 2.045 | BO32: =SUMIF($F$1:$BI$1,BO$1,$F32:$BI32) -> 0 | BP32: =SUMIF($F$1:$BI$1,BP$1,$F32:$BI32) -> 0 | BQ32: =SUMIF($F$1:$BI$1,BQ$1,$F32:$BI32) -> 0 | BR32: =SUMIF($F$1:$BI$1,BR$1,$F32:$BI32) -> 0 | ... BX32: =SUMIF($F$1:$BI$1,BX$1,$F32:$BI32) -> 0
C33: D&A | F33: ='Canalyst HC - Q'!C412+'Canalyst HC - Q'!C413 -> 24.389 | G33: ='Canalyst HC - Q'!D412+'Canalyst HC - Q'!D413 -> 27.94 | H33: ='Canalyst HC - Q'!E412+'Canalyst HC - Q'!E413 -> 31.057 | I33: ='Canalyst HC - Q'!F412+'Canalyst HC - Q'!F413 -> 33.237 | J33: ='Canalyst HC - Q'!G412+'Canalyst HC - Q'!G413 -> 34.981 | K33: ='Canalyst HC - Q'!H412+'Canalyst HC - Q'!H413 -> 42.066 | L33: ='Canalyst HC - Q'!I412+'Canalyst HC - Q'!I413 -> 43.246 | M33: ='Canalyst HC - Q'!J412+'Canalyst HC - Q'!J413 -> 48.548 | ... AS33: ='Canalyst HC - Q'!AP412+'Canalyst HC - Q'!AP413 -> 55.306 | AT33: =AT9*AT17 -> 59.414914 | AU33: =AU9*AU17 -> 54.892325 | AV33: =AV9*AV17 -> 55.222644 | AW33: =AW9*AW17 -> 55.447429 | AX33: =AX9*AX17 -> 61.208291 | AY33: =AY9*AY17 -> 56.549164 | AZ33: =AZ9*AZ17 -> 56.889395 | BA33: =BA9*BA17 -> 57.120942 | ... BI33: =BI9*BI17 -> 60.621024 | BK33: =SUMIF($F$1:$BI$1,BK$1,$F33:$BI33) -> 116.623 | BL33: =SUMIF($F$1:$BI$1,BL$1,$F33:$BI33) -> 168.841 | BM33: =SUMIF($F$1:$BI$1,BM$1,$F33:$BI33) -> 187.256 | BN33: =SUMIF($F$1:$BI$1,BN$1,$F33:$BI33) -> 179.916 | BO33: =SUMIF($F$1:$BI$1,BO$1,$F33:$BI33) -> 179.017 | BP33: =SUMIF($F$1:$BI$1,BP$1,$F33:$BI33) -> 180.565 | BQ33: =SUMIF($F$1:$BI$1,BQ$1,$F33:$BI33) -> 171.59 | BR33: =SUMIF($F$1:$BI$1,BR$1,$F33:$BI33) -> 176.966 | ... BX33: =SUMIF($F$1:$BI$1,BX$1,$F33:$BI33) -> 245.96981
C34: Other | F34: =F35-(F21+F33+F32) -> 0 | G34: =G35-(G21+G33+G32) -> 0 | H34: =H35-(H21+H33+H32) -> 0 | I34: =I35-(I21+I33+I32) -> 0 | J34: =J35-(J21+J33+J32) -> 0 | K34: =K35-(K21+K33+K32) -> 0 | L34: =L35-(L21+L33+L32) -> 0 | M34: =M35-(M21+M33+M32) -> 4.0500936e-13 | ... AS34: =AS35-(AS21+AS33+AS32) -> 6.8212103e-13 | AT34: 0 | AU34: 0 | AV34: 0 | AW34: 0 | AX34: 0 | AY34: 0 | AZ34: 0 | BA34: 0 | BB34: 0 | BC34: 0 | BD34: 0 | BE34: 0 | BF34: 0 | BG34: 0 | BH34: 0 | BI34: 0 | BK34: =SUMIF($F$1:$BI$1,BK$1,$F34:$BI34) -> 0 | BL34: =SUMIF($F$1:$BI$1,BL$1,$F34:$BI34) -> 4.0500936e-13 | BM34: =SUMIF($F$1:$BI$1,BM$1,$F34:$BI34) -> 4.0500936e-13 | BN34: =SUMIF($F$1:$BI$1,BN$1,$F34:$BI34) -> 0 | BO34: =SUMIF($F$1:$BI$1,BO$1,$F34:$BI34) -> 0 | BP34: =SUMIF($F$1:$BI$1,BP$1,$F34:$BI34) -> 0 | BQ34: =SUMIF($F$1:$BI$1,BQ$1,$F34:$BI34) -> 0 | BR34: =SUMIF($F$1:$BI$1,BR$1,$F34:$BI34) -> 2.8421709e-13 | ... BX34: =SUMIF($F$1:$BI$1,BX$1,$F34:$BI34) -> 0
B35: Adj. EBITDA | F35: ='Canalyst HC - Q'!C416 -> 38.417 | G35: ='Canalyst HC - Q'!D416 -> 83.945 | H35: ='Canalyst HC - Q'!E416 -> 72.407 | I35: ='Canalyst HC - Q'!F416 -> 56.867 | J35: ='Canalyst HC - Q'!G416 -> 50.649 | K35: ='Canalyst HC - Q'!H416 -> 91.896 | L35: ='Canalyst HC - Q'!I416 -> 81.272 | M35: ='Canalyst HC - Q'!J416 -> 49.125 | ... AS35: ='Canalyst HC - Q'!AP416 -> 297.424 | AT35: =AT21+AT33+AT32+AT34 -> 223.66787 | AU35: =AU21+AU33+AU32+AU34 -> 219.13218 | AV35: =AV21+AV33+AV32+AV34 -> 210.18759 | AW35: =AW21+AW33+AW32+AW34 -> 219.09659 | AX35: =AX21+AX33+AX32+AX34 -> 214.615 | AY35: =AY21+AY33+AY32+AY34 -> 233.91282 | AZ35: =AZ21+AZ33+AZ32+AZ34 -> 226.61776 | BA35: =BA21+BA33+BA32+BA34 -> 239.62932 | ... BI35: =BI21+BI33+BI32+BI34 -> 242.7526 | BK35: =SUMIF($F$1:$BI$1,BK$1,$F35:$BI35) -> 251.636 | BL35: =SUMIF($F$1:$BI$1,BL$1,$F35:$BI35) -> 272.942 | BM35: =SUMIF($F$1:$BI$1,BM$1,$F35:$BI35) -> 250.764 | BN35: =SUMIF($F$1:$BI$1,BN$1,$F35:$BI35) -> 362.715 | BO35: =SUMIF($F$1:$BI$1,BO$1,$F35:$BI35) -> 492.395 | BP35: =SUMIF($F$1:$BI$1,BP$1,$F35:$BI35) -> 619.736 | BQ35: =SUMIF($F$1:$BI$1,BQ$1,$F35:$BI35) -> 812.637 | BR35: =SUMIF($F$1:$BI$1,BR$1,$F35:$BI35) -> 1011.417 | ... BX35: =SUMIF($F$1:$BI$1,BX$1,$F35:$BI35) -> 948.28863
C36: MTM on acquisition related | F36: ='Canalyst HC - Q'!C382 -> 10.531 | G36: ='Canalyst HC - Q'!D382 -> 9.992 | H36: ='Canalyst HC - Q'!E382 -> -4.53 | I36: ='Canalyst HC - Q'!F382 -> -17.202 | J36: ='Canalyst HC - Q'!G382 -> 7.519 | K36: ='Canalyst HC - Q'!H382 -> 9.897 | L36: ='Canalyst HC - Q'!I382 -> -3.208 | M36: ='Canalyst HC - Q'!J382 -> -8.583 | ... AS36: ='Canalyst HC - Q'!AP382 -> 20.63 | AT36: =AP36 -> 32.174 | AU36: =AQ36 -> 9.275 | AV36: =AR36 -> 37.111 | AW36: =AS36 -> 20.63 | AX36: =AT36 -> 32.174 | AY36: =AU36 -> 9.275 | AZ36: =AV36 -> 37.111 | BA36: =AW36 -> 20.63 | ... BI36: =BE36 -> 20.63 | BK36: =SUMIF($F$1:$BI$1,BK$1,$F36:$BI36) -> -1.209 | BL36: =SUMIF($F$1:$BI$1,BL$1,$F36:$BI36) -> 5.625 | BM36: =SUMIF($F$1:$BI$1,BM$1,$F36:$BI36) -> 21.92 | BN36: =SUMIF($F$1:$BI$1,BN$1,$F36:$BI36) -> 69.591 | BO36: =SUMIF($F$1:$BI$1,BO$1,$F36:$BI36) -> 23.408 | BP36: =SUMIF($F$1:$BI$1,BP$1,$F36:$BI36) -> 109.731 | BQ36: =SUMIF($F$1:$BI$1,BQ$1,$F36:$BI36) -> 24.306 | BR36: =SUMIF($F$1:$BI$1,BR$1,$F36:$BI36) -> 119.834 | ... BX36: =SUMIF($F$1:$BI$1,BX$1,$F36:$BI36) -> 99.19
A38: x | B38: non-GAAP P&L
B39: Revenue | F39: =F17 -> 625.456 | G39: =G17 -> 840.384 | H39: =H17 -> 849.028 | I39: =I17 -> 841.56 | J39: =J17 -> 865.702 | K39: =K17 -> 1169.291 | L39: =L17 -> 1162.526 | M39: =M17 -> 1126.149 | ... BI39: =BI17 -> 2087.2437 | BK39: =SUMIF($F$1:$BI$1,BK$1,$F39:$BI39) -> 3156.428 | BL39: =SUMIF($F$1:$BI$1,BL$1,$F39:$BI39) -> 4323.668 | BM39: =SUMIF($F$1:$BI$1,BM$1,$F39:$BI39) -> 4625.364 | BN39: =SUMIF($F$1:$BI$1,BN$1,$F39:$BI39) -> 4826.549 | BO39: =SUMIF($F$1:$BI$1,BO$1,$F39:$BI39) -> 5007.357 | BP39: =SUMIF($F$1:$BI$1,BP$1,$F39:$BI39) -> 5562.714 | BQ39: =SUMIF($F$1:$BI$1,BQ$1,$F39:$BI39) -> 6200.957 | BR39: =SUMIF($F$1:$BI$1,BR$1,$F39:$BI39) -> 6653.858 | ... BX39: =SUMIF($F$1:$BI$1,BX$1,$F39:$BI39) -> 8113.2062
C40: COGS | F40: =F18 -> 381.558 | G40: =G18 -> 520.677 | H40: =H18 -> 521.838 | I40: =I18 -> 516.633 | J40: =J18 -> 533.681 | K40: =K18 -> 754.113 | L40: =L18 -> 752.202 | M40: =M18 -> 742.725 | ... BI40: =BI18 -> 1304.1289 | BK40: =SUMIF($F$1:$BI$1,BK$1,$F40:$BI40) -> 1940.706 | BL40: =SUMIF($F$1:$BI$1,BL$1,$F40:$BI40) -> 2782.721 | BM40: =SUMIF($F$1:$BI$1,BM$1,$F40:$BI40) -> 3069.652 | BN40: =SUMIF($F$1:$BI$1,BN$1,$F40:$BI40) -> 3156.047 | BO40: =SUMIF($F$1:$BI$1,BO$1,$F40:$BI40) -> 3238.448 | BP40: =SUMIF($F$1:$BI$1,BP$1,$F40:$BI40) -> 3608.527 | BQ40: =SUMIF($F$1:$BI$1,BQ$1,$F40:$BI40) -> 3923.003 | BR40: =SUMIF($F$1:$BI$1,BR$1,$F40:$BI40) -> 4055.147 | ... BX40: =SUMIF($F$1:$BI$1,BX$1,$F40:$BI40) -> 5152.4671
B41: Gross Profit | F41: =F39-F40 -> 243.898 | G41: =G39-G40 -> 319.707 | H41: =H39-H40 -> 327.19 | I41: =I39-I40 -> 324.927 | J41: =J39-J40 -> 332.021 | K41: =K39-K40 -> 415.178 | L41: =L39-L40 -> 410.324 | M41: =M39-M40 -> 383.424 | ... BI41: =BI39-BI40 -> 783.11485 | BK41: =SUMIF($F$1:$BI$1,BK$1,$F41:$BI41) -> 1215.722 | BL41: =SUMIF($F$1:$BI$1,BL$1,$F41:$BI41) -> 1540.947 | BM41: =SUMIF($F$1:$BI$1,BM$1,$F41:$BI41) -> 1555.712 | BN41: =SUMIF($F$1:$BI$1,BN$1,$F41:$BI41) -> 1670.502 | BO41: =SUMIF($F$1:$BI$1,BO$1,$F41:$BI41) -> 1768.909 | BP41: =SUMIF($F$1:$BI$1,BP$1,$F41:$BI41) -> 1954.187 | BQ41: =SUMIF($F$1:$BI$1,BQ$1,$F41:$BI41) -> 2277.954 | BR41: =SUMIF($F$1:$BI$1,BR$1,$F41:$BI41) -> 2598.711 | ... BX41: =SUMIF($F$1:$BI$1,BX$1,$F41:$BI41) -> 2960.7391
C42: SG&A | F42: =F20-F32-F34 -> 229.87 | G42: =G20-G32-G34 -> 263.702 | H42: =H20-H32-H34 -> 285.84 | I42: =I20-I32-I34 -> 301.297 | J42: =J20-J32-J34 -> 316.353 | K42: =K20-K32-K34 -> 365.348 | L42: =L20-L32-L34 -> 372.298 | M42: =M20-M32-M34 -> 382.847 | ... AS42: =AS20-AS32-AS34 -> 512.128 | AT42: =AT20-AT32 -> 464.58894 | AU42: =AU20-AU32 -> 498.87642 | AV42: =AV20-AV32 -> 531.44787 | AW42: =AW20-AW32 -> 542.05248 | AX42: =AX20-AX32 -> 480.84955 | AY42: =AY20-AY32 -> 516.33709 | AZ42: =AZ20-AZ32 -> 550.04855 | BA42: =BA20-BA32 -> 561.02432 | ... BI42: =BI20-BI32 -> 600.98327 | BK42: =SUMIF($F$1:$BI$1,BK$1,$F42:$BI42) -> 1080.709 | BL42: =SUMIF($F$1:$BI$1,BL$1,$F42:$BI42) -> 1436.846 | BM42: =SUMIF($F$1:$BI$1,BM$1,$F42:$BI42) -> 1492.204 | BN42: =SUMIF($F$1:$BI$1,BN$1,$F42:$BI42) -> 1487.703 | BO42: =SUMIF($F$1:$BI$1,BO$1,$F42:$BI42) -> 1455.531 | BP42: =SUMIF($F$1:$BI$1,BP$1,$F42:$BI42) -> 1515.016 | BQ42: =SUMIF($F$1:$BI$1,BQ$1,$F42:$BI42) -> 1636.907 | BR42: =SUMIF($F$1:$BI$1,BR$1,$F42:$BI42) -> 1764.26 | ... BX42: =SUMIF($F$1:$BI$1,BX$1,$F42:$BI42) -> 2258.4203
B43: Adj. EBIT | F43: =F41-F42 -> 14.028 | G43: =G41-G42 -> 56.005 | H43: =H41-H42 -> 41.35 | I43: =I41-I42 -> 23.63 | J43: =J41-J42 -> 15.668 | K43: =K41-K42 -> 49.83 | L43: =L41-L42 -> 38.026 | M43: =M41-M42 -> 0.577 | ... BI43: =BI41-BI42 -> 182.13158 | BK43: =SUMIF($F$1:$BI$1,BK$1,$F43:$BI43) -> 135.013 | BL43: =SUMIF($F$1:$BI$1,BL$1,$F43:$BI43) -> 104.101 | BM43: =SUMIF($F$1:$BI$1,BM$1,$F43:$BI43) -> 63.508 | BN43: =SUMIF($F$1:$BI$1,BN$1,$F43:$BI43) -> 182.799 | BO43: =SUMIF($F$1:$BI$1,BO$1,$F43:$BI43) -> 313.378 | BP43: =SUMIF($F$1:$BI$1,BP$1,$F43:$BI43) -> 439.171 | BQ43: =SUMIF($F$1:$BI$1,BQ$1,$F43:$BI43) -> 641.047 | BR43: =SUMIF($F$1:$BI$1,BR$1,$F43:$BI43) -> 834.451 | ... BX43: =SUMIF($F$1:$BI$1,BX$1,$F43:$BI43) -> 702.31882
C44: Interest Expense / (Income) | F44: =F22 -> 9.361 | G44: =G22 -> 9.808 | H44: =H22 -> 8.452 | I44: =I22 -> 8.704 | J44: =J22 -> 9.47 | K44: =K22 -> 10.44 | L44: =L22 -> 10.697 | M44: =M22 -> 11.262 | ... BI44: =BI22 -> 41.816295 | BK44: =SUMIF($F$1:$BI$1,BK$1,$F44:$BI44) -> 36.325 | BL44: =SUMIF($F$1:$BI$1,BL$1,$F44:$BI44) -> 41.869 | BM44: =SUMIF($F$1:$BI$1,BM$1,$F44:$BI44) -> 50.506 | BN44: =SUMIF($F$1:$BI$1,BN$1,$F44:$BI44) -> 45.99 | BO44: =SUMIF($F$1:$BI$1,BO$1,$F44:$BI44) -> 36.735 | BP44: =SUMIF($F$1:$BI$1,BP$1,$F44:$BI44) -> 33.449 | BQ44: =SUMIF($F$1:$BI$1,BQ$1,$F44:$BI44) -> 24.792 | BR44: =SUMIF($F$1:$BI$1,BR$1,$F44:$BI44) -> -0.918 | ... BX44: =SUMIF($F$1:$BI$1,BX$1,$F44:$BI44) -> 167.26518
C45: Other | F45: =F23-F36 -> 6.62 | G45: =G23-G36 -> 6.974 | H45: =H23-H36 -> -2.795 | I45: =I23-I36 -> -10.768 | J45: =J23-J36 -> 4.727 | K45: =K23-K36 -> 15.652 | L45: =L23-L36 -> -2.018 | M45: =M23-M36 -> -32.682 | ... BI45: =BI23-BI36 -> 8.096 | BK45: =SUMIF($F$1:$BI$1,BK$1,$F45:$BI45) -> 0.031 | BL45: =SUMIF($F$1:$BI$1,BL$1,$F45:$BI45) -> -14.321 | BM45: =SUMIF($F$1:$BI$1,BM$1,$F45:$BI45) -> -1.237 | BN45: =SUMIF($F$1:$BI$1,BN$1,$F45:$BI45) -> 30.948 | BO45: =SUMIF($F$1:$BI$1,BO$1,$F45:$BI45) -> 12.195 | BP45: =SUMIF($F$1:$BI$1,BP$1,$F45:$BI45) -> 40.842 | BQ45: =SUMIF($F$1:$BI$1,BQ$1,$F45:$BI45) -> 16.862 | BR45: =SUMIF($F$1:$BI$1,BR$1,$F45:$BI45) -> 158.054 | ... BX45: =SUMIF($F$1:$BI$1,BX$1,$F45:$BI45) -> 35.87
B46: EBT | F46: =F43-SUM(F44:F45) -> -1.953 | G46: =G43-SUM(G44:G45) -> 39.223 | H46: =H43-SUM(H44:H45) -> 35.693 | I46: =I43-SUM(I44:I45) -> 25.694 | J46: =J43-SUM(J44:J45) -> 1.471 | K46: =K43-SUM(K44:K45) -> 23.738 | L46: =L43-SUM(L44:L45) -> 29.347 | M46: =M43-SUM(M44:M45) -> 21.997 | ... BI46: =BI43-SUM(BI44:BI45) -> 132.21928 | BK46: =SUMIF($F$1:$BI$1,BK$1,$F46:$BI46) -> 98.657 | BL46: =SUMIF($F$1:$BI$1,BL$1,$F46:$BI46) -> 76.553 | BM46: =SUMIF($F$1:$BI$1,BM$1,$F46:$BI46) -> 14.239 | BN46: =SUMIF($F$1:$BI$1,BN$1,$F46:$BI46) -> 105.861 | BO46: =SUMIF($F$1:$BI$1,BO$1,$F46:$BI46) -> 264.448 | BP46: =SUMIF($F$1:$BI$1,BP$1,$F46:$BI46) -> 364.88 | BQ46: =SUMIF($F$1:$BI$1,BQ$1,$F46:$BI46) -> 599.393 | BR46: =SUMIF($F$1:$BI$1,BR$1,$F46:$BI46) -> 677.315 | ... BX46: =SUMIF($F$1:$BI$1,BX$1,$F46:$BI46) -> 499.18364
C47: Taxes | F47: =F46-F48 -> -8.172 | G47: =G46-G48 -> 20.362 | H47: =H46-H48 -> 12.8 | I47: =I46-I48 -> 19.075 | J47: =J46-J48 -> -2.762 | K47: =K46-K48 -> 1.572 | L47: =L46-L48 -> 13.901 | M47: =M46-M48 -> 20.125 | ... AS47: =AS46-AS48 -> 51.017 | AT47: =AT46*AT7 -> 27.784416 | AU47: =AU46*AU7 -> 29.638641 | AV47: =AV46*AV7 -> 25.135662 | AW47: =AW46*AW7 -> 28.434217 | AX47: =AX46*AX7 -> 25.072854 | AY47: =AY46*AY7 -> 32.91959 | AZ47: =AZ46*AZ7 -> 28.826516 | BA47: =BA46*BA7 -> 33.149021 | ... BI47: =BI46*BI7 -> 33.05482 | BK47: =SUMIF($F$1:$BI$1,BK$1,$F47:$BI47) -> 44.065 | BL47: =SUMIF($F$1:$BI$1,BL$1,$F47:$BI47) -> 32.836 | BM47: =SUMIF($F$1:$BI$1,BM$1,$F47:$BI47) -> -32.941 | BN47: =SUMIF($F$1:$BI$1,BN$1,$F47:$BI47) -> 13.887 | BO47: =SUMIF($F$1:$BI$1,BO$1,$F47:$BI47) -> 72.862 | BP47: =SUMIF($F$1:$BI$1,BP$1,$F47:$BI47) -> 63.133 | BQ47: =SUMIF($F$1:$BI$1,BQ$1,$F47:$BI47) -> 142.286 | BR47: =SUMIF($F$1:$BI$1,BR$1,$F47:$BI47) -> 63.485 | ... BX47: =SUMIF($F$1:$BI$1,BX$1,$F47:$BI47) -> 124.79591
B48: Adj. Net Income | F48: ='Canalyst HC - Q'!C435 -> 6.219 | G48: ='Canalyst HC - Q'!D435 -> 18.861 | H48: ='Canalyst HC - Q'!E435 -> 22.893 | I48: ='Canalyst HC - Q'!F435 -> 6.619 | J48: ='Canalyst HC - Q'!G435 -> 4.233 | K48: ='Canalyst HC - Q'!H435 -> 22.166 | L48: ='Canalyst HC - Q'!I435 -> 15.446 | M48: ='Canalyst HC - Q'!J435 -> 1.872 | ... AS48: ='Canalyst HC - Q'!AP435 -> 157.836 | AT48: =AT46-AT47 -> 83.353247 | AU48: =AU46-AU47 -> 88.915923 | AV48: =AV46-AV47 -> 75.406985 | AW48: =AW46-AW47 -> 85.302651 | AX48: =AX46-AX47 -> 75.218562 | AY48: =AY46-AY47 -> 98.75877 | AZ48: =AZ46-AZ47 -> 86.479549 | BA48: =BA46-BA47 -> 99.447063 | ... BI48: =BI46-BI47 -> 99.164461 | BK48: =SUMIF($F$1:$BI$1,BK$1,$F48:$BI48) -> 54.592 | BL48: =SUMIF($F$1:$BI$1,BL$1,$F48:$BI48) -> 43.717 | BM48: =SUMIF($F$1:$BI$1,BM$1,$F48:$BI48) -> 47.18 | BN48: =SUMIF($F$1:$BI$1,BN$1,$F48:$BI48) -> 91.974 | BO48: =SUMIF($F$1:$BI$1,BO$1,$F48:$BI48) -> 191.586 | BP48: =SUMIF($F$1:$BI$1,BP$1,$F48:$BI48) -> 301.747 | BQ48: =SUMIF($F$1:$BI$1,BQ$1,$F48:$BI48) -> 457.107 | BR48: =SUMIF($F$1:$BI$1,BR$1,$F48:$BI48) -> 613.83 | ... BX48: =SUMIF($F$1:$BI$1,BX$1,$F48:$BI48) -> 374.38773
B50: FDSO | F50: ='Canalyst HC - Q'!C448 -> 92.98 | G50: ='Canalyst HC - Q'!D448 -> 93.53 | H50: ='Canalyst HC - Q'!E448 -> 93.53 | I50: ='Canalyst HC - Q'!F448 -> 93.53 | J50: ='Canalyst HC - Q'!G448 -> 93.19 | K50: ='Canalyst HC - Q'!H448 -> 93.74 | L50: ='Canalyst HC - Q'!I448 -> 93.74 | M50: ='Canalyst HC - Q'!J448 -> 93.74 | ... AS50: ='Canalyst HC - Q'!AP448 -> 74.732 | AT50: =AT84 -> 57.020861 | AU50: =AU84 -> 57.020861 | AV50: =AV84 -> 56.844247 | AW50: =AW84 -> 56.631841 | AX50: =AX84 -> 56.631841 | AY50: =AY84 -> 56.631841 | AZ50: =AZ84 -> 56.431891 | BA50: =BA84 -> 56.187133 | ... BI50: =BI84 -> 55.08336 | BK50: =AVERAGEIF($F$1:$BI$1,BK$1,$F50:$BI50) -> 93.3925 | BL50: =AVERAGEIF($F$1:$BI$1,BL$1,$F50:$BI50) -> 93.6025 | BM50: =AVERAGEIF($F$1:$BI$1,BM$1,$F50:$BI50) -> 93.6325 | BN50: =AVERAGEIF($F$1:$BI$1,BN$1,$F50:$BI50) -> 93.9175 | BO50: =AVERAGEIF($F$1:$BI$1,BO$1,$F50:$BI50) -> 94.2975 | BP50: =AVERAGEIF($F$1:$BI$1,BP$1,$F50:$BI50) -> 94.035 | BQ50: =AVERAGEIF($F$1:$BI$1,BQ$1,$F50:$BI50) -> 93.98 | BR50: =AVERAGEIF($F$1:$BI$1,BR$1,$F50:$BI50) -> 93.925 | ... BX50: =AVERAGEIF($F$1:$BI$1,BX$1,$F50:$BI50) -> 55.40754
B51: Adj. EPS | F51: =F48/F50 -> 0.066885352 | G51: =G48/G50 -> 0.20165722 | H51: =H48/H50 -> 0.24476639 | I51: =I48/I50 -> 0.070768737 | J51: =J48/J50 -> 0.045423329 | K51: =K48/K50 -> 0.23646256 | L51: =L48/L50 -> 0.16477491 | M51: =M48/M50 -> 0.01997013 | ... BI51: =BI48/BI50 -> 1.8002617 | BK51: =BK48/BK50 -> 0.58454373 | BL51: =BL48/BL50 -> 0.46704949 | BM51: =BM48/BM50 -> 0.50388487 | BN51: =BN48/BN50 -> 0.97930631 | BO51: =BO48/BO50 -> 2.0317188 | BP51: =BP48/BP50 -> 3.2088797 | BQ51: =BQ48/BQ50 -> 4.8638753 | BR51: =BR48/BR50 -> 6.5353207 | ... BX51: =BX48/BX50 -> 6.7569817
A53: x | B53: Balance Sheet / Cash Flow
C54: Cash | F54: ='Canalyst HC - Q'!C505 -> 32.6 | G54: ='Canalyst HC - Q'!D505 -> 49.323 | H54: ='Canalyst HC - Q'!E505 -> 54.217 | I54: ='Canalyst HC - Q'!F505 -> 21.85 | J54: ='Canalyst HC - Q'!G505 -> 31.94 | K54: ='Canalyst HC - Q'!H505 -> 43.514 | L54: ='Canalyst HC - Q'!I505 -> 11.922 | M54: ='Canalyst HC - Q'!J505 -> 16.902 | ... AS54: ='Canalyst HC - Q'!AP505 -> 281.918 | AT54: =AS54+AT77 -> 254.79419 | AU54: =AT54+AU77 -> 254.79419 | AV54: =AU54+AV77 -> 254.79419 | AW54: =AV54+AW77 -> 251.41961 | AX54: =AW54+AX77 -> 216.64329 | AY54: =AX54+AY77 -> 216.64329 | AZ54: =AY54+AZ77 -> 216.64329 | BA54: =AZ54+BA77 -> 216.64329 | ... BI54: =BH54+BI77 -> 164.76066 | BK54: =AVERAGEIF($F$1:$BI$1,BK$1,$F54:$BI54) -> 39.4975 | BL54: =AVERAGEIF($F$1:$BI$1,BL$1,$F54:$BI54) -> 26.0695 | BM54: =AVERAGEIF($F$1:$BI$1,BM$1,$F54:$BI54) -> 12.772 | BN54: =AVERAGEIF($F$1:$BI$1,BN$1,$F54:$BI54) -> 7.448 | BO54: =AVERAGEIF($F$1:$BI$1,BO$1,$F54:$BI54) -> 86.2285 | BP54: =AVERAGEIF($F$1:$BI$1,BP$1,$F54:$BI54) -> 108.806 | BQ54: =AVERAGEIF($F$1:$BI$1,BQ$1,$F54:$BI54) -> 169.195 | BR54: =AVERAGEIF($F$1:$BI$1,BR$1,$F54:$BI54) -> 492.85975 | ... BX54: =AVERAGEIF($F$1:$BI$1,BX$1,$F54:$BI54) -> 164.76066
C55: Debt | F55: ='Canalyst HC - Q'!C508 -> 814.094 | G55: ='Canalyst HC - Q'!D508 -> 882.114 | H55: ='Canalyst HC - Q'!E508 -> 870.568 | I55: ='Canalyst HC - Q'!F508 -> 955.975 | J55: ='Canalyst HC - Q'!G508 -> 1049.202 | K55: ='Canalyst HC - Q'!H508 -> 1125.604 | L55: ='Canalyst HC - Q'!I508 -> 1170.974 | M55: ='Canalyst HC - Q'!J508 -> 1131.487 | ... AS55: ='Canalyst HC - Q'!AP508 -> 2787.753 | AT55: =AS55+AT70+AT71 -> 2787.753 | AU55: =AT55+AU70+AU71 -> 2787.753 | AV55: =AU55+AV70+AV71 -> 2787.753 | AW55: =AV55+AW70+AW71 -> 2787.753 | AX55: =AW55+AX70+AX71 -> 2787.753 | AY55: =AX55+AY70+AY71 -> 2787.753 | AZ55: =AY55+AZ70+AZ71 -> 2787.753 | BA55: =AZ55+BA70+BA71 -> 2787.753 | ... BI55: =BH55+BI70+BI71 -> 2787.753 | BK55: =AVERAGEIF($F$1:$BI$1,BK$1,$F55:$BI55) -> 880.68775 | BL55: =AVERAGEIF($F$1:$BI$1,BL$1,$F55:$BI55) -> 1119.3167 | BM55: =AVERAGEIF($F$1:$BI$1,BM$1,$F55:$BI55) -> 1198.5377 | BN55: =AVERAGEIF($F$1:$BI$1,BN$1,$F55:$BI55) -> 1102.0728 | BO55: =AVERAGEIF($F$1:$BI$1,BO$1,$F55:$BI55) -> 1036.1225 | BP55: =AVERAGEIF($F$1:$BI$1,BP$1,$F55:$BI55) -> 873.911 | BQ55: =AVERAGEIF($F$1:$BI$1,BQ$1,$F55:$BI55) -> 671.8335 | BR55: =AVERAGEIF($F$1:$BI$1,BR$1,$F55:$BI55) -> 607.42975 | ... BX55: =AVERAGEIF($F$1:$BI$1,BX$1,$F55:$BI55) -> 2787.753
C56: Operating Lease Liabilities | F56: ='Canalyst HC - Q'!C509 -> 0 | G56: ='Canalyst HC - Q'!D509 -> 0 | H56: ='Canalyst HC - Q'!E509 -> 0 | I56: ='Canalyst HC - Q'!F509 -> 0 | J56: ='Canalyst HC - Q'!G509 -> 0 | K56: ='Canalyst HC - Q'!H509 -> 0 | L56: ='Canalyst HC - Q'!I509 -> 0 | M56: ='Canalyst HC - Q'!J509 -> 0 | ... AS56: ='Canalyst HC - Q'!AP509 -> 119.488 | AT56: =AS56 -> 119.488 | AU56: =AT56 -> 119.488 | AV56: =AU56 -> 119.488 | AW56: =AV56 -> 119.488 | AX56: =AW56 -> 119.488 | AY56: =AX56 -> 119.488 | AZ56: =AY56 -> 119.488 | BA56: =AZ56 -> 119.488 | ... BI56: =BH56 -> 119.488 | BK56: =AVERAGEIF($F$1:$BI$1,BK$1,$F56:$BI56) -> 0 | BL56: =AVERAGEIF($F$1:$BI$1,BL$1,$F56:$BI56) -> 0 | BM56: =AVERAGEIF($F$1:$BI$1,BM$1,$F56:$BI56) -> 0 | BN56: =AVERAGEIF($F$1:$BI$1,BN$1,$F56:$BI56) -> 104.26925 | BO56: =AVERAGEIF($F$1:$BI$1,BO$1,$F56:$BI56) -> 140.49475 | BP56: =AVERAGEIF($F$1:$BI$1,BP$1,$F56:$BI56) -> 139.81025 | BQ56: =AVERAGEIF($F$1:$BI$1,BQ$1,$F56:$BI56) -> 144.41925 | BR56: =AVERAGEIF($F$1:$BI$1,BR$1,$F56:$BI56) -> 133.3545 | ... BX56: =AVERAGEIF($F$1:$BI$1,BX$1,$F56:$BI56) -> 119.488
B57: Net Debt (incl. lease liabilities) | F57: =F55+F56-F54 -> 781.494 | G57: =G55+G56-G54 -> 832.791 | H57: =H55+H56-H54 -> 816.351 | I57: =I55+I56-I54 -> 934.125 | J57: =J55+J56-J54 -> 1017.262 | K57: =K55+K56-K54 -> 1082.09 | L57: =L55+L56-L54 -> 1159.052 | M57: =M55+M56-M54 -> 1114.585 | ... BI57: =BI55+BI56-BI54 -> 2742.4803 | BK57: =BK55+BK56-BK54 -> 841.19025 | BL57: =BL55+BL56-BL54 -> 1093.2472 | BM57: =BM55+BM56-BM54 -> 1185.7658 | BN57: =BN55+BN56-BN54 -> 1198.894 | BO57: =BO55+BO56-BO54 -> 1090.3888 | BP57: =BP55+BP56-BP54 -> 904.91525 | BQ57: =BQ55+BQ56-BQ54 -> 647.05775 | BR57: =BR55+BR56-BR54 -> 247.9245 | ... BX57: =BX55+BX56-BX54 -> 2742.4803
B58: Net Debt (ex. Lease liabilities) | F58: =F55-F54 -> 781.494 | G58: =G55-G54 -> 832.791 | H58: =H55-H54 -> 816.351 | I58: =I55-I54 -> 934.125 | J58: =J55-J54 -> 1017.262 | K58: =K55-K54 -> 1082.09 | L58: =L55-L54 -> 1159.052 | M58: =M55-M54 -> 1114.585 | ... BI58: =BI55-BI54 -> 2622.9923 | BK58: =BK55-BK54 -> 841.19025 | BL58: =BL55-BL54 -> 1093.2472 | BM58: =BM55-BM54 -> 1185.7658 | BN58: =BN55-BN54 -> 1094.6247 | BO58: =BO55-BO54 -> 949.894 | BP58: =BP55-BP54 -> 765.105 | BQ58: =BQ55-BQ54 -> 502.6385 | BR58: =BR55-BR54 -> 114.57 | ... BX58: =BX55-BX54 -> 2622.9923
B60: Net Income | F60: =F26 -> -9.033 | G60: =G26 -> 17.324 | H60: =H26 -> 25.553 | I60: =I26 -> 22.819 | J60: =J26 -> -4.417 | K60: =K26 -> 7.581 | L60: =L26 -> 18.911 | M60: =M26 -> 80.772 | ... BI60: =BI26 -> 83.691961 | BK60: =SUMIF($F$1:$BI$1,BK$1,$F60:$BI60) -> 56.663 | BL60: =SUMIF($F$1:$BI$1,BL$1,$F60:$BI60) -> 102.847 | BM60: =SUMIF($F$1:$BI$1,BM$1,$F60:$BI60) -> -15.156 | BN60: =SUMIF($F$1:$BI$1,BN$1,$F60:$BI60) -> 18.56 | BO60: =SUMIF($F$1:$BI$1,BO$1,$F60:$BI60) -> 182.097 | BP60: =SUMIF($F$1:$BI$1,BP$1,$F60:$BI60) -> 189.58 | BQ60: =SUMIF($F$1:$BI$1,BQ$1,$F60:$BI60) -> 430.158 | BR60: =SUMIF($F$1:$BI$1,BR$1,$F60:$BI60) -> 408.375 | ... BX60: =SUMIF($F$1:$BI$1,BX$1,$F60:$BI60) -> 299.99523
C61: D&A | F61: =F33 -> 24.389 | G61: =G33 -> 27.94 | H61: =H33 -> 31.057 | I61: =I33 -> 33.237 | J61: =J33 -> 34.981 | K61: =K33 -> 42.066 | L61: =L33 -> 43.246 | M61: =M33 -> 48.548 | ... BI61: =BI33 -> 60.621024 | BK61: =SUMIF($F$1:$BI$1,BK$1,$F61:$BI61) -> 116.623 | BL61: =SUMIF($F$1:$BI$1,BL$1,$F61:$BI61) -> 168.841 | BM61: =SUMIF($F$1:$BI$1,BM$1,$F61:$BI61) -> 187.256 | BN61: =SUMIF($F$1:$BI$1,BN$1,$F61:$BI61) -> 179.916 | BO61: =SUMIF($F$1:$BI$1,BO$1,$F61:$BI61) -> 179.017 | BP61: =SUMIF($F$1:$BI$1,BP$1,$F61:$BI61) -> 180.565 | BQ61: =SUMIF($F$1:$BI$1,BQ$1,$F61:$BI61) -> 171.59 | BR61: =SUMIF($F$1:$BI$1,BR$1,$F61:$BI61) -> 176.966 | ... BX61: =SUMIF($F$1:$BI$1,BX$1,$F61:$BI61) -> 245.96981
C62: SBC | F62: =F32 -> 1.627 | G62: =G32 -> 1.269 | H62: =H32 -> 1.549 | I62: =I32 -> 2.709 | J62: =J32 -> 2.06 | K62: =K32 -> 2.517 | L62: =L32 -> 1.896 | M62: =M32 -> 1.449 | ... BI62: =BI32 -> 0 | BK62: =SUMIF($F$1:$BI$1,BK$1,$F62:$BI62) -> 7.154 | BL62: =SUMIF($F$1:$BI$1,BL$1,$F62:$BI62) -> 7.922 | BM62: =SUMIF($F$1:$BI$1,BM$1,$F62:$BI62) -> 5.606 | BN62: =SUMIF($F$1:$BI$1,BN$1,$F62:$BI62) -> 2.045 | BO62: =SUMIF($F$1:$BI$1,BO$1,$F62:$BI62) -> 0 | BP62: =SUMIF($F$1:$BI$1,BP$1,$F62:$BI62) -> 0 | BQ62: =SUMIF($F$1:$BI$1,BQ$1,$F62:$BI62) -> 0 | BR62: =SUMIF($F$1:$BI$1,BR$1,$F62:$BI62) -> 0 | ... BX62: =SUMIF($F$1:$BI$1,BX$1,$F62:$BI62) -> 0
C63: Other | F63: =F65-F60-F61-F62-F64 -> 13.092 | G63: =G65-G60-G61-G62-G64 -> 22.479 | H63: =H65-H60-H61-H62-H64 -> 0.499 | I63: =I65-I60-I61-I62-I64 -> 10.808 | J63: =J65-J60-J61-J62-J64 -> 84.908 | K63: =K65-K60-K61-K62-K64 -> 8.161 | L63: =L65-L60-L61-L62-L64 -> -3.312 | M63: =M65-M60-M61-M62-M64 -> -42.794 | ... AS63: =AS65-AS60-AS61-AS62-AS64 -> 42.699 | AT63: 0 | AU63: 0 | AV63: 0 | AW63: 0 | AX63: 0 | AY63: 0 | AZ63: 0 | BA63: 0 | BB63: 0 | BC63: 0 | BD63: 0 | BE63: 0 | BF63: 0 | BG63: 0 | BH63: 0 | BI63: 0 | BK63: =SUMIF($F$1:$BI$1,BK$1,$F63:$BI63) -> 46.878 | BL63: =SUMIF($F$1:$BI$1,BL$1,$F63:$BI63) -> 46.963 | BM63: =SUMIF($F$1:$BI$1,BM$1,$F63:$BI63) -> 38.335 | BN63: =SUMIF($F$1:$BI$1,BN$1,$F63:$BI63) -> 113.532 | BO63: =SUMIF($F$1:$BI$1,BO$1,$F63:$BI63) -> 55.279 | BP63: =SUMIF($F$1:$BI$1,BP$1,$F63:$BI63) -> 128.74 | BQ63: =SUMIF($F$1:$BI$1,BQ$1,$F63:$BI63) -> 29.193 | BR63: =SUMIF($F$1:$BI$1,BR$1,$F63:$BI63) -> 231.301 | ... BX63: =SUMIF($F$1:$BI$1,BX$1,$F63:$BI63) -> 0
C64: Change in NWC | F64: ='Canalyst HC - Q'!C479 -> -45.292 | G64: ='Canalyst HC - Q'!D479 -> 7.402 | H64: ='Canalyst HC - Q'!E479 -> 8.27 | I64: ='Canalyst HC - Q'!F479 -> -35.703 | J64: ='Canalyst HC - Q'!G479 -> -1.014 | K64: ='Canalyst HC - Q'!H479 -> 2.128 | L64: ='Canalyst HC - Q'!I479 -> -37.287 | M64: ='Canalyst HC - Q'!J479 -> 17.416 | ... AS64: ='Canalyst HC - Q'!AP479 -> -26.264 | AT64: =AT10*AT17 -> -43.440469 | AU64: =AU10*AU17 -> 7.1846651 | AV64: =AV10*AV17 -> 51.443293 | AW64: =AW10*AW17 -> -26.331163 | AX64: =AX10*AX17 -> -44.751675 | AY64: =AY10*AY17 -> 7.401523 | AZ64: =AZ10*AZ17 -> 52.995974 | BA64: =BA10*BA17 -> -27.125889 | ... BI64: =BI10*BI17 -> -28.788026 | BK64: =SUMIF($F$1:$BI$1,BK$1,$F64:$BI64) -> -65.323 | BL64: =SUMIF($F$1:$BI$1,BL$1,$F64:$BI64) -> -18.757 | BM64: =SUMIF($F$1:$BI$1,BM$1,$F64:$BI64) -> -47.162 | BN64: =SUMIF($F$1:$BI$1,BN$1,$F64:$BI64) -> -23.683 | BO64: =SUMIF($F$1:$BI$1,BO$1,$F64:$BI64) -> 78.068 | BP64: =SUMIF($F$1:$BI$1,BP$1,$F64:$BI64) -> 22.87 | BQ64: =SUMIF($F$1:$BI$1,BQ$1,$F64:$BI64) -> -76.435 | BR64: =SUMIF($F$1:$BI$1,BR$1,$F64:$BI64) -> -5.952 | ... BX64: =SUMIF($F$1:$BI$1,BX$1,$F64:$BI64) -> -12.183624
B65: CFO | F65: ='Canalyst HC - Q'!C664 -> -15.217 | G65: ='Canalyst HC - Q'!D664 -> 76.414 | H65: ='Canalyst HC - Q'!E664 -> 66.928 | I65: ='Canalyst HC - Q'!F664 -> 33.87 | J65: ='Canalyst HC - Q'!G664 -> 116.518 | K65: ='Canalyst HC - Q'!H664 -> 62.453 | L65: ='Canalyst HC - Q'!I664 -> 23.454 | M65: ='Canalyst HC - Q'!J664 -> 105.391 | ... AS65: ='Canalyst HC - Q'!AP664 -> 208.991 | AT65: =SUM(AT60:AT64) -> 75.197191 | AU65: =SUM(AU60:AU64) -> 144.03666 | AV65: =SUM(AV60:AV64) -> 154.23967 | AW65: =SUM(AW60:AW64) -> 98.946417 | AX65: =SUM(AX60:AX64) -> 67.544678 | AY65: =SUM(AY60:AY64) -> 155.75321 | AZ65: =SUM(AZ60:AZ64) -> 168.53167 | BA65: =SUM(BA60:BA64) -> 113.96962 | ... BI65: =SUM(BI60:BI64) -> 115.52496 | BK65: =SUMIF($F$1:$BI$1,BK$1,$F65:$BI65) -> 161.995 | BL65: =SUMIF($F$1:$BI$1,BL$1,$F65:$BI65) -> 307.816 | BM65: =SUMIF($F$1:$BI$1,BM$1,$F65:$BI65) -> 168.879 | BN65: =SUMIF($F$1:$BI$1,BN$1,$F65:$BI65) -> 290.37 | BO65: =SUMIF($F$1:$BI$1,BO$1,$F65:$BI65) -> 494.461 | BP65: =SUMIF($F$1:$BI$1,BP$1,$F65:$BI65) -> 521.755 | BQ65: =SUMIF($F$1:$BI$1,BQ$1,$F65:$BI65) -> 554.506 | BR65: =SUMIF($F$1:$BI$1,BR$1,$F65:$BI65) -> 810.69 | ... BX65: =SUMIF($F$1:$BI$1,BX$1,$F65:$BI65) -> 533.78142
C66: Capex | F66: ='Canalyst HC - Q'!C484 -> -36.785 | G66: ='Canalyst HC - Q'!D484 -> -42.84 | H66: ='Canalyst HC - Q'!E484 -> -44.974 | I66: ='Canalyst HC - Q'!F484 -> -47.987 | J66: ='Canalyst HC - Q'!G484 -> -41.58 | K66: ='Canalyst HC - Q'!H484 -> -38.027 | L66: ='Canalyst HC - Q'!I484 -> -35.346 | M66: ='Canalyst HC - Q'!J484 -> -61.648 | ... AS66: ='Canalyst HC - Q'!AP484 -> -102.321 | AT66: =AS66 -> -102.321 | AU66: =AT66 -> -102.321 | AV66: =AU66 -> -102.321 | AW66: =AV66 -> -102.321 | AX66: =AW66 -> -102.321 | AY66: =AX66 -> -102.321 | AZ66: =AY66 -> -102.321 | BA66: =AZ66 -> -102.321 | ... BI66: =BH66 -> -102.321 | BK66: =SUMIF($F$1:$BI$1,BK$1,$F66:$BI66) -> -172.586 | BL66: =SUMIF($F$1:$BI$1,BL$1,$F66:$BI66) -> -176.601 | BM66: =SUMIF($F$1:$BI$1,BM$1,$F66:$BI66) -> -138.235 | BN66: =SUMIF($F$1:$BI$1,BN$1,$F66:$BI66) -> -171.374 | BO66: =SUMIF($F$1:$BI$1,BO$1,$F66:$BI66) -> -202.034 | BP66: =SUMIF($F$1:$BI$1,BP$1,$F66:$BI66) -> -155.693 | BQ66: =SUMIF($F$1:$BI$1,BQ$1,$F66:$BI66) -> -298.611 | BR66: =SUMIF($F$1:$BI$1,BR$1,$F66:$BI66) -> -282.304 | ... BX66: =SUMIF($F$1:$BI$1,BX$1,$F66:$BI66) -> -409.284
C67: Acquisitions | F67: ='Canalyst HC - Q'!C486 -> -107.07 | G67: ='Canalyst HC - Q'!D486 -> -82.185 | H67: ='Canalyst HC - Q'!E486 -> -3.002 | I67: ='Canalyst HC - Q'!F486 -> -101.805 | J67: ='Canalyst HC - Q'!G486 -> -140.092 | K67: ='Canalyst HC - Q'!H486 -> -95.224 | L67: ='Canalyst HC - Q'!I486 -> -62.577 | M67: ='Canalyst HC - Q'!J486 -> -6.913 | ... AS67: ='Canalyst HC - Q'!AP486 -> -22.136 | AT67: =0 -> 0 | AU67: =0 -> 0 | AV67: =0 -> 0 | AW67: =0 -> 0 | AX67: =0 -> 0 | AY67: =0 -> 0 | AZ67: =0 -> 0 | BA67: =0 -> 0 | ... BI67: =0 -> 0 | BK67: =SUMIF($F$1:$BI$1,BK$1,$F67:$BI67) -> -294.062 | BL67: =SUMIF($F$1:$BI$1,BL$1,$F67:$BI67) -> -304.806 | BM67: =SUMIF($F$1:$BI$1,BM$1,$F67:$BI67) -> -39.441 | BN67: =SUMIF($F$1:$BI$1,BN$1,$F67:$BI67) -> -28.895 | BO67: =SUMIF($F$1:$BI$1,BO$1,$F67:$BI67) -> -45.17 | BP67: =SUMIF($F$1:$BI$1,BP$1,$F67:$BI67) -> -41.628 | BQ67: =SUMIF($F$1:$BI$1,BQ$1,$F67:$BI67) -> -39.609 | BR67: =SUMIF($F$1:$BI$1,BR$1,$F67:$BI67) -> -41.949 | ... BX67: =SUMIF($F$1:$BI$1,BX$1,$F67:$BI67) -> 0
C68: Other | F68: =F69-F66-F67 -> 5.09 | G68: =G69-G66-G67 -> 3.118 | H68: =H69-H66-H67 -> 2.595 | I68: =I69-I66-I67 -> 3.819 | J68: =J69-J66-J67 -> -15.387 | K68: =K69-K66-K67 -> 15.129 | L68: =L69-L66-L67 -> 5.203 | M68: =M69-M66-M67 -> 17.567 | ... AS68: =AS69-AS66-AS67 -> 167.115 | AT68: 0 | AU68: 0 | AV68: 0 | AW68: 0 | AX68: 0 | AY68: 0 | AZ68: 0 | BA68: 0 | BB68: 0 | BC68: 0 | BD68: 0 | BE68: 0 | BF68: 0 | BG68: 0 | BH68: 0 | BI68: 0 | BK68: =SUMIF($F$1:$BI$1,BK$1,$F68:$BI68) -> 14.622 | BL68: =SUMIF($F$1:$BI$1,BL$1,$F68:$BI68) -> 22.512 | BM68: =SUMIF($F$1:$BI$1,BM$1,$F68:$BI68) -> 33.731 | BN68: =SUMIF($F$1:$BI$1,BN$1,$F68:$BI68) -> 26.592 | BO68: =SUMIF($F$1:$BI$1,BO$1,$F68:$BI68) -> 46.785 | BP68: =SUMIF($F$1:$BI$1,BP$1,$F68:$BI68) -> 35.378 | BQ68: =SUMIF($F$1:$BI$1,BQ$1,$F68:$BI68) -> 13.235 | BR68: =SUMIF($F$1:$BI$1,BR$1,$F68:$BI68) -> 28.903 | ... BX68: =SUMIF($F$1:$BI$1,BX$1,$F68:$BI68) -> 0
B69: CFI | F69: ='Canalyst HC - Q'!C681 -> -138.765 | G69: ='Canalyst HC - Q'!D681 -> -121.907 | H69: ='Canalyst HC - Q'!E681 -> -45.381 | I69: ='Canalyst HC - Q'!F681 -> -145.973 | J69: ='Canalyst HC - Q'!G681 -> -197.059 | K69: ='Canalyst HC - Q'!H681 -> -118.122 | L69: ='Canalyst HC - Q'!I681 -> -92.72 | M69: ='Canalyst HC - Q'!J681 -> -50.994 | ... AS69: ='Canalyst HC - Q'!AP681 -> 42.658 | AT69: =SUM(AT66:AT68) -> -102.321 | AU69: =SUM(AU66:AU68) -> -102.321 | AV69: =SUM(AV66:AV68) -> -102.321 | AW69: =SUM(AW66:AW68) -> -102.321 | AX69: =SUM(AX66:AX68) -> -102.321 | AY69: =SUM(AY66:AY68) -> -102.321 | AZ69: =SUM(AZ66:AZ68) -> -102.321 | BA69: =SUM(BA66:BA68) -> -102.321 | ... BI69: =SUM(BI66:BI68) -> -102.321 | BK69: =SUMIF($F$1:$BI$1,BK$1,$F69:$BI69) -> -452.026 | BL69: =SUMIF($F$1:$BI$1,BL$1,$F69:$BI69) -> -458.895 | BM69: =SUMIF($F$1:$BI$1,BM$1,$F69:$BI69) -> -143.945 | BN69: =SUMIF($F$1:$BI$1,BN$1,$F69:$BI69) -> -173.677 | BO69: =SUMIF($F$1:$BI$1,BO$1,$F69:$BI69) -> -200.419 | BP69: =SUMIF($F$1:$BI$1,BP$1,$F69:$BI69) -> -161.943 | BQ69: =SUMIF($F$1:$BI$1,BQ$1,$F69:$BI69) -> -324.985 | BR69: =SUMIF($F$1:$BI$1,BR$1,$F69:$BI69) -> -295.35 | ... BX69: =SUMIF($F$1:$BI$1,BX$1,$F69:$BI69) -> -409.284
C70: Debt Issuance | F70: ='Canalyst HC - Q'!C598+'Canalyst HC - Q'!C599+'Canalyst HC - Q'!C605 -> 0 | G70: ='Canalyst HC - Q'!D598+'Canalyst HC - Q'!D599+'Canalyst HC - Q'!D605 -> 300 | H70: ='Canalyst HC - Q'!E598+'Canalyst HC - Q'!E599+'Canalyst HC - Q'!E605 -> 300 | I70: ='Canalyst HC - Q'!F598+'Canalyst HC - Q'!F599+'Canalyst HC - Q'!F605 -> 300 | J70: ='Canalyst HC - Q'!G598+'Canalyst HC - Q'!G599+'Canalyst HC - Q'!G605 -> 125 | K70: ='Canalyst HC - Q'!H598+'Canalyst HC - Q'!H599+'Canalyst HC - Q'!H605 -> 125 | L70: ='Canalyst HC - Q'!I598+'Canalyst HC - Q'!I599+'Canalyst HC - Q'!I605 -> 125 | M70: ='Canalyst HC - Q'!J598+'Canalyst HC - Q'!J599+'Canalyst HC - Q'!J605 -> 125 | ... AS70: ='Canalyst HC - Q'!AP598+'Canalyst HC - Q'!AP599+'Canalyst HC - Q'!AP605 -> 0 | AT70: =0 -> 0 | AU70: =0 -> 0 | AV70: =0 -> 0 | AW70: =0 -> 0 | AX70: =0 -> 0 | AY70: =0 -> 0 | AZ70: =0 -> 0 | BA70: =0 -> 0 | ... BI70: =0 -> 0 | BK70: =SUMIF($F$1:$BI$1,BK$1,$F70:$BI70) -> 900 | BL70: =SUMIF($F$1:$BI$1,BL$1,$F70:$BI70) -> 500 | BM70: =SUMIF($F$1:$BI$1,BM$1,$F70:$BI70) -> 600 | BN70: =SUMIF($F$1:$BI$1,BN$1,$F70:$BI70) -> 300 | BO70: =SUMIF($F$1:$BI$1,BO$1,$F70:$BI70) -> 0 | BP70: =SUMIF($F$1:$BI$1,BP$1,$F70:$BI70) -> 140 | BQ70: =SUMIF($F$1:$BI$1,BQ$1,$F70:$BI70) -> 0 | BR70: =SUMIF($F$1:$BI$1,BR$1,$F70:$BI70) -> 0 | ... BX70: =SUMIF($F$1:$BI$1,BX$1,$F70:$BI70) -> 0
C71: Debt Paydown | F71: ='Canalyst HC - Q'!C602+'Canalyst HC - Q'!C603+'Canalyst HC - Q'!C606 -> 0 | G71: ='Canalyst HC - Q'!D602+'Canalyst HC - Q'!D603+'Canalyst HC - Q'!D606 -> -164.757 | H71: ='Canalyst HC - Q'!E602+'Canalyst HC - Q'!E603+'Canalyst HC - Q'!E606 -> -164.757 | I71: ='Canalyst HC - Q'!F602+'Canalyst HC - Q'!F603+'Canalyst HC - Q'!F606 -> -164.757 | J71: ='Canalyst HC - Q'!G602+'Canalyst HC - Q'!G603+'Canalyst HC - Q'!G606 -> 0 | K71: ='Canalyst HC - Q'!H602+'Canalyst HC - Q'!H603+'Canalyst HC - Q'!H606 -> 0 | L71: ='Canalyst HC - Q'!I602+'Canalyst HC - Q'!I603+'Canalyst HC - Q'!I606 -> 0 | M71: ='Canalyst HC - Q'!J602+'Canalyst HC - Q'!J603+'Canalyst HC - Q'!J606 -> 0 | ... AS71: ='Canalyst HC - Q'!AP602+'Canalyst HC - Q'!AP603+'Canalyst HC - Q'!AP606 -> 0 | AT71: =0 -> 0 | AU71: =0 -> 0 | AV71: =0 -> 0 | AW71: =0 -> 0 | AX71: =0 -> 0 | AY71: =0 -> 0 | AZ71: =0 -> 0 | BA71: =0 -> 0 | ... BI71: =0 -> 0 | BK71: =SUMIF($F$1:$BI$1,BK$1,$F71:$BI71) -> -494.271 | BL71: =SUMIF($F$1:$BI$1,BL$1,$F71:$BI71) -> 0 | BM71: =SUMIF($F$1:$BI$1,BM$1,$F71:$BI71) -> -15 | BN71: =SUMIF($F$1:$BI$1,BN$1,$F71:$BI71) -> -420 | BO71: =SUMIF($F$1:$BI$1,BO$1,$F71:$BI71) -> -90 | BP71: =SUMIF($F$1:$BI$1,BP$1,$F71:$BI71) -> -753.75 | BQ71: =SUMIF($F$1:$BI$1,BQ$1,$F71:$BI71) -> -250 | BR71: =SUMIF($F$1:$BI$1,BR$1,$F71:$BI71) -> 0 | ... BX71: =SUMIF($F$1:$BI$1,BX$1,$F71:$BI71) -> 0
C72: Share Repurchases | F72: ='Canalyst HC - Q'!C619 -> 0 | G72: ='Canalyst HC - Q'!D619 -> 0 | H72: ='Canalyst HC - Q'!E619 -> 0 | I72: ='Canalyst HC - Q'!F619 -> 0 | J72: ='Canalyst HC - Q'!G619 -> 0 | K72: ='Canalyst HC - Q'!H619 -> 0 | L72: ='Canalyst HC - Q'!I619 -> 0 | M72: ='Canalyst HC - Q'!J619 -> 0 | ... AS72: ='Canalyst HC - Q'!AP619 -> -2606.031 | AT72: =IF(AT$79>0,AT$79*-0.5,0) -> 0 | AU72: =IF(AU$79>0,AU$79*-0.5,0) -> -20.857832 | AV72: =IF(AV$79>0,AV$79*-0.5,0) -> -25.959336 | AW72: =IF(AW$79>0,AW$79*-0.5,0) -> 0 | AX72: =IF(AX$79>0,AX$79*-0.5,0) -> 0 | AY72: =IF(AY$79>0,AY$79*-0.5,0) -> -26.716103 | AZ72: =IF(AZ$79>0,AZ$79*-0.5,0) -> -33.105334 | BA72: =IF(BA$79>0,BA$79*-0.5,0) -> -5.8243082 | ... BI72: =IF(BI$79>0,BI$79*-0.5,0) -> -6.6019794 | BK72: =SUMIF($F$1:$BI$1,BK$1,$F72:$BI72) -> 0 | BL72: =SUMIF($F$1:$BI$1,BL$1,$F72:$BI72) -> 0 | BM72: =SUMIF($F$1:$BI$1,BM$1,$F72:$BI72) -> 0 | BN72: =SUMIF($F$1:$BI$1,BN$1,$F72:$BI72) -> 0 | BO72: =SUMIF($F$1:$BI$1,BO$1,$F72:$BI72) -> 0 | BP72: =SUMIF($F$1:$BI$1,BP$1,$F72:$BI72) -> 0 | BQ72: =SUMIF($F$1:$BI$1,BQ$1,$F72:$BI72) -> 0 | BR72: =SUMIF($F$1:$BI$1,BR$1,$F72:$BI72) -> 0 | ... BX72: =SUMIF($F$1:$BI$1,BX$1,$F72:$BI72) -> -75.487585
C73: Dividends | F73: ='Canalyst HC - Q'!C613 -> -2.323 | G73: ='Canalyst HC - Q'!D613 -> -4.652 | H73: ='Canalyst HC - Q'!E613 -> -6.98 | I73: ='Canalyst HC - Q'!F613 -> -9.307 | J73: ='Canalyst HC - Q'!G613 -> -2.328 | K73: ='Canalyst HC - Q'!H613 -> -4.662 | L73: ='Canalyst HC - Q'!I613 -> -6.995 | M73: ='Canalyst HC - Q'!J613 -> -9.328 | ... AS73: ='Canalyst HC - Q'!AP613 -> -86.673 | AT73: =IF(AT$79>0,AT$79*-0.5,0) -> 0 | AU73: =IF(AU$79>0,AU$79*-0.5,0) -> -20.857832 | AV73: =IF(AV$79>0,AV$79*-0.5,0) -> -25.959336 | AW73: =IF(AW$79>0,AW$79*-0.5,0) -> 0 | AX73: =IF(AX$79>0,AX$79*-0.5,0) -> 0 | AY73: =IF(AY$79>0,AY$79*-0.5,0) -> -26.716103 | AZ73: =IF(AZ$79>0,AZ$79*-0.5,0) -> -33.105334 | BA73: =IF(BA$79>0,BA$79*-0.5,0) -> -5.8243082 | ... BI73: =IF(BI$79>0,BI$79*-0.5,0) -> -6.6019794 | BK73: =SUMIF($F$1:$BI$1,BK$1,$F73:$BI73) -> -23.262 | BL73: =SUMIF($F$1:$BI$1,BL$1,$F73:$BI73) -> -23.313 | BM73: =SUMIF($F$1:$BI$1,BM$1,$F73:$BI73) -> -23.371 | BN73: =SUMIF($F$1:$BI$1,BN$1,$F73:$BI73) -> -23.416 | BO73: =SUMIF($F$1:$BI$1,BO$1,$F73:$BI73) -> -23.434 | BP73: =SUMIF($F$1:$BI$1,BP$1,$F73:$BI73) -> -23.434 | BQ73: =SUMIF($F$1:$BI$1,BQ$1,$F73:$BI73) -> -23.435 | BR73: =SUMIF($F$1:$BI$1,BR$1,$F73:$BI73) -> -159.353 | ... BX73: =SUMIF($F$1:$BI$1,BX$1,$F73:$BI73) -> -75.487585
C74: Other | F74: =F75-F70-F71-F72-F73 -> 133.407 | G74: =G75-G70-G71-G72-G73 -> 62.709 | H74: =H75-H70-H71-H72-H73 -> 48.384 | I74: =I75-I70-I71-I72-I73 -> 130.447 | J74: =J75-J70-J71-J72-J73 -> -32.041 | K74: =K75-K70-K71-K72-K73 -> 37.536 | L74: =L75-L70-L71-L72-L73 -> 77.543 | M74: =M75-M70-M71-M72-M73 -> 30.459 | ... AS74: =AS75-AS70-AS71-AS72-AS73 -> 925.911 | AT74: 0 | AU74: 0 | AV74: 0 | AW74: 0 | AX74: 0 | AY74: 0 | AZ74: 0 | BA74: 0 | BB74: 0 | BC74: 0 | BD74: 0 | BE74: 0 | BF74: 0 | BG74: 0 | BH74: 0 | BI74: 0 | BK74: =SUMIF($F$1:$BI$1,BK$1,$F74:$BI74) -> 374.947 | BL74: =SUMIF($F$1:$BI$1,BL$1,$F74:$BI74) -> 113.497 | BM74: =SUMIF($F$1:$BI$1,BM$1,$F74:$BI74) -> -383.581 | BN74: =SUMIF($F$1:$BI$1,BN$1,$F74:$BI74) -> -98.684 | BO74: =SUMIF($F$1:$BI$1,BO$1,$F74:$BI74) -> -296.721 | BP74: =SUMIF($F$1:$BI$1,BP$1,$F74:$BI74) -> -58.155 | BQ74: =SUMIF($F$1:$BI$1,BQ$1,$F74:$BI74) -> -102.884 | BR74: =SUMIF($F$1:$BI$1,BR$1,$F74:$BI74) -> -75.657 | ... BX74: =SUMIF($F$1:$BI$1,BX$1,$F74:$BI74) -> 0
B75: CFF | F75: ='Canalyst HC - Q'!C622 -> 131.084 | G75: ='Canalyst HC - Q'!D622 -> 193.3 | H75: ='Canalyst HC - Q'!E622 -> 176.647 | I75: ='Canalyst HC - Q'!F622 -> 256.383 | J75: ='Canalyst HC - Q'!G622 -> 90.631 | K75: ='Canalyst HC - Q'!H622 -> 157.874 | L75: ='Canalyst HC - Q'!I622 -> 195.548 | M75: ='Canalyst HC - Q'!J622 -> 146.131 | ... AS75: ='Canalyst HC - Q'!AP622 -> -1766.793 | AT75: =SUM(AT70:AT74) -> 0 | AU75: =SUM(AU70:AU74) -> -41.715663 | AV75: =SUM(AV70:AV74) -> -51.918671 | AW75: =SUM(AW70:AW74) -> 0 | AX75: =SUM(AX70:AX74) -> 0 | AY75: =SUM(AY70:AY74) -> -53.432207 | AZ75: =SUM(AZ70:AZ74) -> -66.210668 | BA75: =SUM(BA70:BA74) -> -11.648616 | ... BI75: =SUM(BI70:BI74) -> -13.203959 | BK75: =SUMIF($F$1:$BI$1,BK$1,$F75:$BI75) -> 757.414 | BL75: =SUMIF($F$1:$BI$1,BL$1,$F75:$BI75) -> 590.184 | BM75: =SUMIF($F$1:$BI$1,BM$1,$F75:$BI75) -> 178.048 | BN75: =SUMIF($F$1:$BI$1,BN$1,$F75:$BI75) -> -242.1 | BO75: =SUMIF($F$1:$BI$1,BO$1,$F75:$BI75) -> -410.155 | BP75: =SUMIF($F$1:$BI$1,BP$1,$F75:$BI75) -> -695.339 | BQ75: =SUMIF($F$1:$BI$1,BQ$1,$F75:$BI75) -> -376.319 | BR75: =SUMIF($F$1:$BI$1,BR$1,$F75:$BI75) -> -235.01 | ... BX75: =SUMIF($F$1:$BI$1,BX$1,$F75:$BI75) -> -150.97517
B77: Net Change in Cash | F77: =SUM(F65,F69,F75) -> -22.898 | G77: =SUM(G65,G69,G75) -> 147.807 | H77: =SUM(H65,H69,H75) -> 198.194 | I77: =SUM(I65,I69,I75) -> 144.28 | J77: =SUM(J65,J69,J75) -> 10.09 | K77: =SUM(K65,K69,K75) -> 102.205 | L77: =SUM(L65,L69,L75) -> 126.282 | M77: =SUM(M65,M69,M75) -> 200.528 | ... BI77: =SUM(BI65,BI69,BI75) -> 0 | BK77: =SUMIF($F$1:$BI$1,BK$1,$F77:$BI77) -> 467.383 | BL77: =SUMIF($F$1:$BI$1,BL$1,$F77:$BI77) -> 439.105 | BM77: =SUMIF($F$1:$BI$1,BM$1,$F77:$BI77) -> 202.982 | BN77: =SUMIF($F$1:$BI$1,BN$1,$F77:$BI77) -> -125.407 | BO77: =SUMIF($F$1:$BI$1,BO$1,$F77:$BI77) -> -116.113 | BP77: =SUMIF($F$1:$BI$1,BP$1,$F77:$BI77) -> -335.527 | BQ77: =SUMIF($F$1:$BI$1,BQ$1,$F77:$BI77) -> -146.798 | BR77: =SUMIF($F$1:$BI$1,BR$1,$F77:$BI77) -> 280.33 | ... BX77: =SUMIF($F$1:$BI$1,BX$1,$F77:$BI77) -> -26.47775
B79: Free Cash Flow | F79: =F65+F66 -> -52.002 | G79: =G65+G66 -> 33.574 | H79: =H65+H66 -> 21.954 | I79: =I65+I66 -> -14.117 | J79: =J65+J66 -> 74.938 | K79: =K65+K66 -> 24.426 | L79: =L65+L66 -> -11.892 | M79: =M65+M66 -> 43.743 | ... BI79: =BI65+BI66 -> 13.203959 | BK79: =SUMIF($F$1:$BI$1,BK$1,$F79:$BI79) -> -10.591 | BL79: =SUMIF($F$1:$BI$1,BL$1,$F79:$BI79) -> 131.215 | BM79: =SUMIF($F$1:$BI$1,BM$1,$F79:$BI79) -> 30.644 | BN79: =SUMIF($F$1:$BI$1,BN$1,$F79:$BI79) -> 118.996 | BO79: =SUMIF($F$1:$BI$1,BO$1,$F79:$BI79) -> 292.427 | BP79: =SUMIF($F$1:$BI$1,BP$1,$F79:$BI79) -> 366.062 | BQ79: =SUMIF($F$1:$BI$1,BQ$1,$F79:$BI79) -> 255.895 | BR79: =SUMIF($F$1:$BI$1,BR$1,$F79:$BI79) -> 528.386 | ... BX79: =SUMIF($F$1:$BI$1,BX$1,$F79:$BI79) -> 124.49742
C80: EBITDA Conversion % | F80: =IF(F35=0,0,F79/F35) -> -1.3536195 | G80: =IF(G35=0,0,G79/G35) -> 0.39995235 | H80: =IF(H35=0,0,H79/H35) -> 0.30320273 | I80: =IF(I35=0,0,I79/I35) -> -0.24824591 | J80: =IF(J35=0,0,J79/J35) -> 1.4795554 | K80: =IF(K35=0,0,K79/K35) -> 0.26580047 | L80: =IF(L35=0,0,L79/L35) -> -0.14632346 | M80: =IF(M35=0,0,M79/M35) -> 0.89044275 | ... BI80: =IF(BI35=0,0,BI79/BI35) -> 0.054392656 | BK80: =AVERAGEIF($F$1:$BI$1,BK$1,$F80:$BI80) -> -0.22467758 | BL80: =AVERAGEIF($F$1:$BI$1,BL$1,$F80:$BI80) -> 0.62236878 | BM80: =AVERAGEIF($F$1:$BI$1,BM$1,$F80:$BI80) -> -0.38019281 | BN80: =AVERAGEIF($F$1:$BI$1,BN$1,$F80:$BI80) -> 0.26138772 | BO80: =AVERAGEIF($F$1:$BI$1,BO$1,$F80:$BI80) -> 0.53751877 | BP80: =AVERAGEIF($F$1:$BI$1,BP$1,$F80:$BI80) -> 0.56423621 | BQ80: =AVERAGEIF($F$1:$BI$1,BQ$1,$F80:$BI80) -> 0.30577521 | BR80: =AVERAGEIF($F$1:$BI$1,BR$1,$F80:$BI80) -> 0.50911947 | ... BX80: =AVERAGEIF($F$1:$BI$1,BX$1,$F80:$BI80) -> 0.12925976
B81: FCFPS | F81: =F79/F50 -> -0.55928157 | G81: =G79/G50 -> 0.35896504 | H81: =H79/H50 -> 0.23472683 | I81: =I79/I50 -> -0.15093553 | J81: =J79/J50 -> 0.80414208 | K81: =K79/K50 -> 0.26057179 | L81: =L79/L50 -> -0.12686153 | M81: =M79/M50 -> 0.46664178 | ... BI81: =BI79/BI50 -> 0.23970867 | BK81: =BK79/BK50 -> -0.11340311 | BL81: =BL79/BL50 -> 1.4018322 | BM81: =BM79/BM50 -> 0.32727952 | BN81: =BN79/BN50 -> 1.2670269 | BO81: =BO79/BO50 -> 3.1011108 | BP81: =BP79/BP50 -> 3.8928271 | BQ81: =BQ79/BQ50 -> 2.7228666 | BR81: =BR79/BR50 -> 5.6256162 | ... BX81: =BX79/BX50 -> 2.24694
A83: x | B83: Share Dilution / Buybacks
C84: Shares Outstanding | F84: ='Canalyst HC - Q'!C448 -> 92.98 | G84: ='Canalyst HC - Q'!D448 -> 93.53 | H84: ='Canalyst HC - Q'!E448 -> 93.53 | I84: ='Canalyst HC - Q'!F448 -> 93.53 | J84: ='Canalyst HC - Q'!G448 -> 93.19 | K84: ='Canalyst HC - Q'!H448 -> 93.74 | L84: ='Canalyst HC - Q'!I448 -> 93.74 | M84: ='Canalyst HC - Q'!J448 -> 93.74 | ... AS84: ='Canalyst HC - Q'!AP448 -> 74.732 | AT84: =AS84+AS96 -> 57.020861 | AU84: =AT84+AT96 -> 57.020861 | AV84: =AU84+AU96 -> 56.844247 | AW84: =AV84+AV96 -> 56.631841 | AX84: =AW84+AW96 -> 56.631841 | AY84: =AX84+AX96 -> 56.631841 | AZ84: =AY84+AY96 -> 56.431891 | BA84: =AZ84+AZ96 -> 56.187133 | ... BI84: =BH84+BH96 -> 55.08336 | BK84: =AVERAGEIF($F$1:$BI$1,BK$1,$F84:$BI84) -> 93.3925 | BL84: =AVERAGEIF($F$1:$BI$1,BL$1,$F84:$BI84) -> 93.6025 | BM84: =AVERAGEIF($F$1:$BI$1,BM$1,$F84:$BI84) -> 93.6325 | BN84: =AVERAGEIF($F$1:$BI$1,BN$1,$F84:$BI84) -> 93.9175 | BO84: =AVERAGEIF($F$1:$BI$1,BO$1,$F84:$BI84) -> 94.2975 | BP84: =AVERAGEIF($F$1:$BI$1,BP$1,$F84:$BI84) -> 94.035 | BQ84: =AVERAGEIF($F$1:$BI$1,BQ$1,$F84:$BI84) -> 93.98 | BR84: =AVERAGEIF($F$1:$BI$1,BR$1,$F84:$BI84) -> 93.925 | ... BX84: =AVERAGEIF($F$1:$BI$1,BX$1,$F84:$BI84) -> 55.40754
C85: Mkt Cap | F85: =F84*F87 -> 1581.2849 | G85: =G84*G87 -> 1367.5379 | H85: =H84*H87 -> 1383.8654 | I85: =I84*I87 -> 1466.9097 | J85: =J84*J87 -> 1661.5206 | K85: =K84*K87 -> 2024.7275 | L85: =L84*L87 -> 2069.7085 | M85: =M84*M87 -> 2041.0375 | ... AS85: =AS84*AS87 -> 10996.126 | AT85: =AT87*AT84 -> 6523.6215 | AU85: =AU84*AU87 -> 6734.0465 | AV85: =AV84*AV87 -> 6947.2783 | AW85: =AW84*AW87 -> 7219.9493 | AX85: =AX84*AX87 -> 7412.0476 | AY85: =AY84*AY87 -> 7566.7967 | AZ85: =AZ84*AZ87 -> 7632.8215 | BA85: =BA84*BA87 -> 7645.3445 | BB85: =BB84*BB87 -> 7624.1922 | ... BI85: =BI84*BI87 -> 7444.6501 | BK85: =AVERAGEIF($F$1:$BI$1,BK$1,$F85:$BI85) -> 1449.8995 | BL85: =AVERAGEIF($F$1:$BI$1,BL$1,$F85:$BI85) -> 1949.2485 | BM85: =AVERAGEIF($F$1:$BI$1,BM$1,$F85:$BI85) -> 1601.0155 | BN85: =AVERAGEIF($F$1:$BI$1,BN$1,$F85:$BI85) -> 2661.3469 | BO85: =AVERAGEIF($F$1:$BI$1,BO$1,$F85:$BI85) -> 2331.0267 | BP85: =AVERAGEIF($F$1:$BI$1,BP$1,$F85:$BI85) -> 3573.5481 | BQ85: =AVERAGEIF($F$1:$BI$1,BQ$1,$F85:$BI85) -> 4772.1171 | BR85: =AVERAGEIF($F$1:$BI$1,BR$1,$F85:$BI85) -> 5925.7546 | ... BX85: =AVERAGEIF($F$1:$BI$1,BX$1,$F85:$BI85) -> 7488.4639
C86: TEV | F86: =F85+F57 -> 2362.7789 | G86: =G85+G57 -> 2200.3289 | H86: =H85+H57 -> 2200.2164 | I86: =I85+I57 -> 2401.0347 | J86: =J85+J57 -> 2678.7826 | K86: =K85+K57 -> 3106.8175 | L86: =L85+L57 -> 3228.7605 | M86: =M85+M57 -> 3155.6225 | ... AS86: =AS85+AS57 -> 13621.449 | AT86: =AT85+AT58 -> 9056.5803 | AU86: =AU85+AU57 -> 9386.4933 | AV86: =AV85+AV57 -> 9599.7251 | AW86: =AW85+AW57 -> 9875.7707 | AX86: =AX85+AX57 -> 10102.645 | AY86: =AY85+AY57 -> 10257.394 | AZ86: =AZ85+AZ57 -> 10323.419 | BA86: =BA85+BA57 -> 10335.942 | BB86: =BB85+BB57 -> 10340.195 | ... BI86: =BI85+BI57 -> 10187.13 | BK86: =AVERAGEIF($F$1:$BI$1,BK$1,$F86:$BI86) -> 2291.0897 | BL86: =AVERAGEIF($F$1:$BI$1,BL$1,$F86:$BI86) -> 3042.4958 | BM86: =AVERAGEIF($F$1:$BI$1,BM$1,$F86:$BI86) -> 2786.7812 | BN86: =AVERAGEIF($F$1:$BI$1,BN$1,$F86:$BI86) -> 3860.2409 | BO86: =AVERAGEIF($F$1:$BI$1,BO$1,$F86:$BI86) -> 3421.4155 | BP86: =AVERAGEIF($F$1:$BI$1,BP$1,$F86:$BI86) -> 4478.4634 | BQ86: =AVERAGEIF($F$1:$BI$1,BQ$1,$F86:$BI86) -> 5419.1749 | BR86: =AVERAGEIF($F$1:$BI$1,BR$1,$F86:$BI86) -> 6173.6791 | ... BX86: =AVERAGEIF($F$1:$BI$1,BX$1,$F86:$BI86) -> 10230.944
C87: Share Price | F87: =_xll.BDP("COKE US Equity","INTERVAL_AVG","CALC_INTERVAL=1Q","END_DATE_OVERRIDE",F4) -> 17.006721 | G87: =_xll.BDP("COKE US Equity","INTERVAL_AVG","CALC_INTERVAL=1Q","END_DATE_OVERRIDE",G4) -> 14.621383 | H87: =_xll.BDP("COKE US Equity","INTERVAL_AVG","CALC_INTERVAL=1Q","END_DATE_OVERRIDE",H4) -> 14.795952 | I87: =_xll.BDP("COKE US Equity","INTERVAL_AVG","CALC_INTERVAL=1Q","END_DATE_OVERRIDE",I4) -> 15.683841 | J87: =_xll.BDP("COKE US Equity","INTERVAL_AVG","CALC_INTERVAL=1Q","END_DATE_OVERRIDE",J4) -> 17.829387 | K87: =_xll.BDP("COKE US Equity","INTERVAL_AVG","CALC_INTERVAL=1Q","END_DATE_OVERRIDE",K4) -> 21.599397 | L87: =_xll.BDP("COKE US Equity","INTERVAL_AVG","CALC_INTERVAL=1Q","END_DATE_OVERRIDE",L4) -> 22.079246 | M87: =_xll.BDP("COKE US Equity","INTERVAL_AVG","CALC_INTERVAL=1Q","END_DATE_OVERRIDE",M4) -> 21.773389 | ... AS87: =_xll.BDP("COKE US Equity","INTERVAL_AVG","CALC_INTERVAL=1Q","END_DATE_OVERRIDE",AS4) -> 147.14079 | AT87: =AT88*SUM(AU51:AX51) -> 114.40763 | AU87: =AU88*SUM(AV51:AY51) -> 118.09794 | AV87: =AV88*SUM(AW51:AZ51) -> 122.21603 | AW87: =AW88*SUM(AX51:BA51) -> 127.48922 | AX87: =AX88*SUM(AY51:BB51) -> 130.88127 | AY87: =AY88*SUM(AZ51:BC51) -> 133.61382 | AZ87: =AZ88*SUM(BA51:BD51) -> 135.25723 | BA87: =BA88*SUM(BB51:BE51) -> 136.06931 | ... BD87: =BD88*SUM(BE51:BH51) -> 135.35778 | BE87: =BE88*SUM($BF$51:$BI$51) -> 135.15242 | BF87: =BF88*SUM($BF$51:$BI$51) -> 135.15242 | BG87: =BG88*SUM($BF$51:$BI$51) -> 135.15242 | BH87: =BH88*SUM($BF$51:$BI$51) -> 135.15242 | BI87: =BI88*SUM($BF$51:$BI$51) -> 135.15242 | BK87: =AVERAGEIF($F$1:$BI$1,BK$1,$F87:$BI87) -> 15.526974 | BL87: =AVERAGEIF($F$1:$BI$1,BL$1,$F87:$BI87) -> 20.820355 | BM87: =AVERAGEIF($F$1:$BI$1,BM$1,$F87:$BI87) -> 17.10115 | BN87: =AVERAGEIF($F$1:$BI$1,BN$1,$F87:$BI87) -> 28.328184 | BO87: =AVERAGEIF($F$1:$BI$1,BO$1,$F87:$BI87) -> 24.720675 | BP87: =AVERAGEIF($F$1:$BI$1,BP$1,$F87:$BI87) -> 38.008297 | BQ87: =AVERAGEIF($F$1:$BI$1,BQ$1,$F87:$BI87) -> 50.777951 | BR87: =AVERAGEIF($F$1:$BI$1,BR$1,$F87:$BI87) -> 63.09304 | ... BX87: =AVERAGEIF($F$1:$BI$1,BX$1,$F87:$BI87) -> 135.15242
C88: Multiple | F88: =F87/SUM(G51:J51) -> 30.227955 | G88: =G87/SUM(H51:K51) -> 24.474169 | H88: =H87/SUM(I51:L51) -> 28.595106 | I88: =I87/SUM(J51:M51) -> 33.610806 | J88: =J87/SUM(K51:N51) -> 54.588483 | K88: =K87/SUM(L51:O51) -> 107.82518 | L88: =L87/SUM(M51:P51) -> 66.601251 | M88: =M87/SUM(N51:Q51) -> 43.319103 | ... AS88: =AS87/SUM(AT51:AW51) -> 25.135166 | AT88: 20 | AU88: 20 | AV88: 20 | AW88: 20 | AX88: 20 | AY88: 20 | AZ88: 20 | BA88: 20 | BB88: 20 | BC88: 20 | BD88: 20 | BE88: 20 | BF88: 20 | BG88: 20 | BH88: 20 | BI88: 20 | BK88: =AVERAGEIF($F$1:$BI$1,BK$1,$F88:$BI88) -> 29.227009 | BL88: =AVERAGEIF($F$1:$BI$1,BL$1,$F88:$BI88) -> 68.083505 | BM88: =AVERAGEIF($F$1:$BI$1,BM$1,$F88:$BI88) -> 20.015129 | BN88: =AVERAGEIF($F$1:$BI$1,BN$1,$F88:$BI88) -> 19.948764 | BO88: =AVERAGEIF($F$1:$BI$1,BO$1,$F88:$BI88) -> 8.5306298 | BP88: =AVERAGEIF($F$1:$BI$1,BP$1,$F88:$BI88) -> 9.316027 | BQ88: =AVERAGEIF($F$1:$BI$1,BQ$1,$F88:$BI88) -> 8.1746217 | BR88: =AVERAGEIF($F$1:$BI$1,BR$1,$F88:$BI88) -> 8.9665049 | ... BX88: =AVERAGEIF($F$1:$BI$1,BX$1,$F88:$BI88) -> 20
C90: Share Buybacks | F90: =F72 -> 0 | G90: =G72 -> 0 | H90: =H72 -> 0 | I90: =I72 -> 0 | J90: =J72 -> 0 | K90: =K72 -> 0 | L90: =L72 -> 0 | M90: =M72 -> 0 | ... BI90: =BI72 -> -6.6019794 | BK90: =SUMIF($F$1:$BI$1,BK$1,$F90:$BI90) -> 0 | BL90: =SUMIF($F$1:$BI$1,BL$1,$F90:$BI90) -> 0 | BM90: =SUMIF($F$1:$BI$1,BM$1,$F90:$BI90) -> 0 | BN90: =SUMIF($F$1:$BI$1,BN$1,$F90:$BI90) -> 0 | BO90: =SUMIF($F$1:$BI$1,BO$1,$F90:$BI90) -> 0 | BP90: =SUMIF($F$1:$BI$1,BP$1,$F90:$BI90) -> 0 | BQ90: =SUMIF($F$1:$BI$1,BQ$1,$F90:$BI90) -> 0 | BR90: =SUMIF($F$1:$BI$1,BR$1,$F90:$BI90) -> 0 | ... BX90: =SUMIF($F$1:$BI$1,BX$1,$F90:$BI90) -> -75.487585
C91: Implied Shares Bought | F91: =IFERROR(IF(F87=0,0,F90/F87),0) -> 0 | G91: =IFERROR(IF(G87=0,0,G90/G87),0) -> 0 | H91: =IFERROR(IF(H87=0,0,H90/H87),0) -> 0 | I91: =IFERROR(IF(I87=0,0,I90/I87),0) -> 0 | J91: =IFERROR(IF(J87=0,0,J90/J87),0) -> 0 | K91: =IFERROR(IF(K87=0,0,K90/K87),0) -> 0 | L91: =IFERROR(IF(L87=0,0,L90/L87),0) -> 0 | M91: =IFERROR(IF(M87=0,0,M90/M87),0) -> 0 | ... BI91: =IFERROR(IF(BI87=0,0,BI90/BI87),0) -> -0.0488484 | BK91: =SUMIF($F$1:$BI$1,BK$1,$F91:$BI91) -> 0 | BL91: =SUMIF($F$1:$BI$1,BL$1,$F91:$BI91) -> 0 | BM91: =SUMIF($F$1:$BI$1,BM$1,$F91:$BI91) -> 0 | BN91: =SUMIF($F$1:$BI$1,BN$1,$F91:$BI91) -> 0 | BO91: =SUMIF($F$1:$BI$1,BO$1,$F91:$BI91) -> 0 | BP91: =SUMIF($F$1:$BI$1,BP$1,$F91:$BI91) -> 0 | BQ91: =SUMIF($F$1:$BI$1,BQ$1,$F91:$BI91) -> 0 | BR91: =SUMIF($F$1:$BI$1,BR$1,$F91:$BI91) -> 0 | ... BX91: =SUMIF($F$1:$BI$1,BX$1,$F91:$BI91) -> -0.5585367
C93: SBC | F93: =F32 -> 1.627 | G93: =G32 -> 1.269 | H93: =H32 -> 1.549 | I93: =I32 -> 2.709 | J93: =J32 -> 2.06 | K93: =K32 -> 2.517 | L93: =L32 -> 1.896 | M93: =M32 -> 1.449 | ... BI93: =BI32 -> 0 | BK93: =SUMIF($F$1:$BI$1,BK$1,$F93:$BI93) -> 7.154 | BL93: =SUMIF($F$1:$BI$1,BL$1,$F93:$BI93) -> 7.922 | BM93: =SUMIF($F$1:$BI$1,BM$1,$F93:$BI93) -> 5.606 | BN93: =SUMIF($F$1:$BI$1,BN$1,$F93:$BI93) -> 2.045 | BO93: =SUMIF($F$1:$BI$1,BO$1,$F93:$BI93) -> 0 | BP93: =SUMIF($F$1:$BI$1,BP$1,$F93:$BI93) -> 0 | BQ93: =SUMIF($F$1:$BI$1,BQ$1,$F93:$BI93) -> 0 | BR93: =SUMIF($F$1:$BI$1,BR$1,$F93:$BI93) -> 0 | ... BX93: =SUMIF($F$1:$BI$1,BX$1,$F93:$BI93) -> 0
C94: Implied Shares Issued | F94: =IFERROR(IF(F87=0,0,F93/F87),0) -> 0.095668058 | G94: =IFERROR(IF(G87=0,0,G93/G87),0) -> 0.086790697 | H94: =IFERROR(IF(H87=0,0,H93/H87),0) -> 0.10469079 | I94: =IFERROR(IF(I87=0,0,I93/I87),0) -> 0.17272554 | J94: =IFERROR(IF(J87=0,0,J93/J87),0) -> 0.11553959 | K94: =IFERROR(IF(K87=0,0,K93/K87),0) -> 0.11653103 | L94: =IFERROR(IF(L87=0,0,L93/L87),0) -> 0.085872498 | M94: =IFERROR(IF(M87=0,0,M93/M87),0) -> 0.066549126 | ... BI94: =IFERROR(IF(BI87=0,0,BI93/BI87),0) -> 0 | BK94: =SUMIF($F$1:$BI$1,BK$1,$F94:$BI94) -> 0.45987509 | BL94: =SUMIF($F$1:$BI$1,BL$1,$F94:$BI94) -> 0.38449224 | BM94: =SUMIF($F$1:$BI$1,BM$1,$F94:$BI94) -> 0.33820281 | BN94: =SUMIF($F$1:$BI$1,BN$1,$F94:$BI94) -> 0.08980613 | BO94: =SUMIF($F$1:$BI$1,BO$1,$F94:$BI94) -> 0 | BP94: =SUMIF($F$1:$BI$1,BP$1,$F94:$BI94) -> 0 | BQ94: =SUMIF($F$1:$BI$1,BQ$1,$F94:$BI94) -> 0 | BR94: =SUMIF($F$1:$BI$1,BR$1,$F94:$BI94) -> 0 | ... BX94: =SUMIF($F$1:$BI$1,BX$1,$F94:$BI94) -> 0
C96: Net Share Impact | F96: =F91+F94 -> 0.095668058 | G96: =G91+G94 -> 0.086790697 | H96: =H91+H94 -> 0.10469079 | I96: =I91+I94 -> 0.17272554 | J96: =J91+J94 -> 0.11553959 | K96: =K91+K94 -> 0.11653103 | L96: =L91+L94 -> 0.085872498 | M96: =M91+M94 -> 0.066549126 | ... BI96: =BI91+BI94 -> -0.0488484 | BK96: =SUMIF($F$1:$BI$1,BK$1,$F96:$BI96) -> 0.45987509 | BL96: =SUMIF($F$1:$BI$1,BL$1,$F96:$BI96) -> 0.38449224 | BM96: =SUMIF($F$1:$BI$1,BM$1,$F96:$BI96) -> 0.33820281 | BN96: =SUMIF($F$1:$BI$1,BN$1,$F96:$BI96) -> 0.08980613 | BO96: =SUMIF($F$1:$BI$1,BO$1,$F96:$BI96) -> 0 | BP96: =SUMIF($F$1:$BI$1,BP$1,$F96:$BI96) -> 0 | BQ96: =SUMIF($F$1:$BI$1,BQ$1,$F96:$BI96) -> 0 | BR96: =SUMIF($F$1:$BI$1,BR$1,$F96:$BI96) -> 0 | ... BX96: =SUMIF($F$1:$BI$1,BX$1,$F96:$BI96) -> -0.5585367

Sheet Segment Build
A1: COKE | F1: 16 | G1: =F1 -> 16 | H1: =G1 -> 16 | I1: =H1 -> 16 | J1: =I1+1 -> 17 | K1: =J1 -> 17 | L1: =K1 -> 17 | M1: =L1 -> 17 | N1: =M1+1 -> 18 | O1: =N1 -> 18 | P1: =O1 -> 18 | Q1: =P1 -> 18 | R1: =Q1+1 -> 19 | S1: =R1 -> 19 | T1: =S1 -> 19 | U1: =T1 -> 19 | V1: =U1+1 -> 20 | W1: =V1 -> 20 | X1: =W1 -> 20 | Y1: =X1 -> 20 | Z1: =Y1+1 -> 21 | AA1: =Z1 -> 21 | AB1: =AA1 -> 21 | AC1: =AB1 -> 21 | AD1: =AC1+1 -> 22 | AE1: =AD1 -> 22 | AF1: =AE1 -> 22 | AG1: =AF1 -> 22 | AH1: =AG1+1 -> 23 | AI1: =AH1 -> 23 | AJ1: =AI1 -> 23 | AK1: =AJ1 -> 23 | AL1: =AK1+1 -> 24 | AM1: =AL1 -> 24 | AN1: =AM1 -> 24 | AO1: =AN1 -> 24 | AP1: =AO1+1 -> 25 | AQ1: =AP1 -> 25 | AR1: =AQ1 -> 25 | AS1: =AR1 -> 25 | AT1: =AS1+1 -> 26 | AU1: =AT1 -> 26 | AV1: =AU1 -> 26 | AW1: =AV1 -> 26 | AX1: =AW1+1 -> 27 | AY1: =AX1 -> 27 | AZ1: =AY1 -> 27 | BA1: =AZ1 -> 27 | BB1: =BA1+1 -> 28 | BC1: =BB1 -> 28 | BD1: =BC1 -> 28 | BE1: =BD1 -> 28 | BF1: =BE1+1 -> 29 | BG1: =BF1 -> 29 | BH1: =BG1 -> 29 | BI1: =BH1 -> 29 | BK1: 16 | BL1: 17 | BM1: 18 | BN1: 19 | BO1: 20 | BP1: 21 | BQ1: 22 | BR1: 23 | BS1: 24 | BT1: 25 | BU1: 26 | BV1: 27 | BW1: 28 | BX1: 29
A2: Coca-Cola Consolidated, Inc. | F2: Q1 | G2: Q2 | H2: Q3 | I2: Q4 | J2: =F2 -> Q1 | K2: =G2 -> Q2 | L2: =H2 -> Q3 | M2: =I2 -> Q4 | N2: =J2 -> Q1 | O2: =K2 -> Q2 | P2: =L2 -> Q3 | Q2: =M2 -> Q4 | ... BI2: =BE2 -> Q4 | BK2: Q4 | BL2: Q4 | BM2: Q4 | BN2: Q4 | BO2: Q4 | BP2: Q4 | BQ2: Q4 | BR2: Q4 | BS2: Q4 | BT2: Q4 | BU2: Q4 | BV2: Q4 | BW2: Q4 | BX2: Q4
A3: ($ in mm, except per share values) | F3: 90 | G3: 91 | H3: 92 | I3: 92 | J3: 90 | K3: 91 | L3: 92 | M3: 92 | N3: 90 | O3: 91 | P3: 92 | Q3: 92 | R3: 90 | S3: 91 | T3: 92 | U3: 92 | V3: 90 | W3: 91 | X3: 92 | Y3: 92 | Z3: 90 | AA3: 91 | AB3: 92 | AC3: 92 | AD3: 90 | AE3: 91 | AF3: 92 | AG3: 92 | AH3: 90 | AI3: 91 | AJ3: 92 | AK3: 92 | AL3: 90 | AM3: 91 | AN3: 92 | AO3: 92 | AP3: 90 | AQ3: 91 | AR3: 92 | AS3: 92 | AT3: 90 | AU3: 91 | AV3: 92 | AW3: 92 | AX3: 90 | AY3: 91 | AZ3: 92 | BA3: 92 | BB3: 90 | BC3: 91 | BD3: 92 | BE3: 92 | BF3: 90 | BG3: 91 | BH3: 92 | BI3: 92
F4: 42460 | G4: =EOMONTH(F4,3) -> 42551 | H4: =EOMONTH(G4,3) -> 42643 | I4: =EOMONTH(H4,3) -> 42735 | J4: =EOMONTH(I4,3) -> 42825 | K4: =EOMONTH(J4,3) -> 42916 | L4: =EOMONTH(K4,3) -> 43008 | M4: =EOMONTH(L4,3) -> 43100 | N4: =EOMONTH(M4,3) -> 43190 | ... BI4: =EOMONTH(BH4,3) -> 47483
F5: Q1 16 | G5: =G2&" "&G1 -> Q2 16 | H5: =H2&" "&H1 -> Q3 16 | I5: =I2&" "&I1 -> Q4 16 | J5: =J2&" "&J1 -> Q1 17 | K5: =K2&" "&K1 -> Q2 17 | L5: =L2&" "&L1 -> Q3 17 | M5: =M2&" "&M1 -> Q4 17 | N5: =N2&" "&N1 -> Q1 18 | ... BI5: =BI2&" "&BI1 -> Q4 29 | BK5: 2016 | BL5: 2017 | BM5: 2018 | BN5: 2019 | BO5: 2020 | BP5: 2021 | BQ5: 2022 | BR5: 2023 | BS5: 2024 | BT5: 2025 | BU5: 2026 | BV5: 2027 | BW5: 2028 | BX5: 2029
A6: x | B6: Segments
B8: Total Revenue | F8: =F17+F30+F38+F42 -> 625.456 | G8: =G17+G30+G38+G42 -> 840.384 | H8: =H17+H30+H38+H42 -> 849.028 | I8: =I17+I30+I38+I42 -> 841.56 | J8: =J17+J30+J38+J42 -> 865.702 | K8: =K17+K30+K38+K42 -> 1169.291 | L8: =L17+L30+L38+L42 -> 1162.526 | M8: =M17+M30+M38+M42 -> 1126.149 | ... BI8: =BI17+BI30+BI38+BI42 -> 2087.2437 | BK8: =SUMIF($F$1:$BI$1,BK$1,$F8:$BI8) -> 3156.428 | BL8: =SUMIF($F$1:$BI$1,BL$1,$F8:$BI8) -> 4323.668 | BM8: =SUMIF($F$1:$BI$1,BM$1,$F8:$BI8) -> 4625.364 | BN8: =SUMIF($F$1:$BI$1,BN$1,$F8:$BI8) -> 4826.549 | BO8: =SUMIF($F$1:$BI$1,BO$1,$F8:$BI8) -> 5007.357 | BP8: =SUMIF($F$1:$BI$1,BP$1,$F8:$BI8) -> 5562.714 | BQ8: =SUMIF($F$1:$BI$1,BQ$1,$F8:$BI8) -> 6204.72 | BR8: =SUMIF($F$1:$BI$1,BR$1,$F8:$BI8) -> 6668.672 | ... BX8: =SUMIF($F$1:$BI$1,BX$1,$F8:$BI8) -> 8113.2062
B9: Total Cases | F9: =F12+F25 -> 0 | G9: =G12+G25 -> 0 | H9: =H12+H25 -> 0 | I9: =I12+I25 -> 0 | J9: =J12+J25 -> 65.2 | K9: =K12+K25 -> 88.5 | L9: =L12+L25 -> 86.8 | M9: =M12+M25 -> 83.3 | ... BI9: =BI12+BI25 -> 95.673771 | BK9: =SUMIF($F$1:$BI$1,BK$1,$F9:$BI9) -> 0 | BL9: =SUMIF($F$1:$BI$1,BL$1,$F9:$BI9) -> 323.8 | BM9: =SUMIF($F$1:$BI$1,BM$1,$F9:$BI9) -> 337.7 | BN9: =SUMIF($F$1:$BI$1,BN$1,$F9:$BI9) -> 343.2 | BO9: =SUMIF($F$1:$BI$1,BO$1,$F9:$BI9) -> 358.8 | BP9: =SUMIF($F$1:$BI$1,BP$1,$F9:$BI9) -> 366.036 | BQ9: =SUMIF($F$1:$BI$1,BQ$1,$F9:$BI9) -> 360.348 | BR9: =SUMIF($F$1:$BI$1,BR$1,$F9:$BI9) -> 355.367 | ... BX9: =SUMIF($F$1:$BI$1,BX$1,$F9:$BI9) -> 370.61448
BM10: =BM9/BL9-1 -> 0.042927733 | BN10: =BN9/BM9-1 -> 0.016286645 | BO10: =BO9/BN9-1 -> 0.045454545 | BP10: =BP9/BO9-1 -> 0.020167224 | BQ10: =BQ9/BP9-1 -> -0.015539455 | BR10: =BR9/BQ9-1 -> -0.013822749 | BS10: =BS9/BR9-1 -> -0.0063708786 | BT10: =BT9/BS9-1 -> 0.0026762729 | ... BX10: =BX9/BW9-1 -> 0.01
B11: Sparkling Beverages
C12: Case Volume (mm cases) | F12: ='Canalyst HC - Q'!C42 -> 0 | G12: ='Canalyst HC - Q'!D42 -> 0 | H12: ='Canalyst HC - Q'!E42 -> 0 | I12: ='Canalyst HC - Q'!F42 -> 0 | J12: ='Canalyst HC - Q'!G42 -> 46.5528 | K12: ='Canalyst HC - Q'!H42 -> 60.0915 | L12: ='Canalyst HC - Q'!I42 -> 56.5068 | M12: ='Canalyst HC - Q'!J42 -> 61.2423 | ... AC12: ='Canalyst HC - Q'!Z42 -> 64.2728 | AD12: 60.182 | AE12: 66.738 | AF12: 63.656 | AG12: 61.317 | AH12: ='Canalyst HC - Q'!AE42 -> 61.317 | AI12: ='Canalyst HC - Q'!AF42 -> 67.9 | AJ12: ='Canalyst HC - Q'!AG42 -> 66.251 | AK12: ='Canalyst HC - Q'!AH42 -> 68.404 | AL12: ='Canalyst HC - Q'!AI42 -> 61.785 | AM12: ='Canalyst HC - Q'!AJ42 -> 67.662 | AN12: ='Canalyst HC - Q'!AK42 -> 66.781 | AO12: ='Canalyst HC - Q'!AL42 -> 70.458 | ... AS12: ='Canalyst HC - Q'!AP42 -> 72.938 | AT12: =AP12*(1+AT13) -> 65.07819 | AU12: =AQ12*(1+AU13) -> 66.81213 | AV12: =AR12*(1+AV13) -> 67.01805 | AW12: =AS12*(1+AW13) -> 72.20862 | AX12: =AT12*(1+AX13) -> 65.728972 | AY12: =AU12*(1+AY13) -> 67.480251 | AZ12: =AV12*(1+AZ13) -> 67.68823 | BA12: =AW12*(1+BA13) -> 72.930706 | ... BI12: =BE12*(1+BI13) -> 74.396613 | BK12: =SUMIF($F$1:$BI$1,BK$1,$F12:$BI12) -> 0 | BL12: =SUMIF($F$1:$BI$1,BL$1,$F12:$BI12) -> 224.3934 | BM12: =SUMIF($F$1:$BI$1,BM$1,$F12:$BI12) -> 241.7932 | BN12: =SUMIF($F$1:$BI$1,BN$1,$F12:$BI12) -> 242.6424 | BO12: =SUMIF($F$1:$BI$1,BO$1,$F12:$BI12) -> 253.3128 | BP12: =SUMIF($F$1:$BI$1,BP$1,$F12:$BI12) -> 254.028 | BQ12: =SUMIF($F$1:$BI$1,BQ$1,$F12:$BI12) -> 251.893 | BR12: =SUMIF($F$1:$BI$1,BR$1,$F12:$BI12) -> 263.872 | ... BX12: =SUMIF($F$1:$BI$1,BX$1,$F12:$BI12) -> 279.33211
C13: YoY Growth % | J13: =IF(F12=0,0,J12/F12-1) -> 0 | K13: =IF(G12=0,0,K12/G12-1) -> 0 | L13: =IF(H12=0,0,L12/H12-1) -> 0 | M13: =IF(I12=0,0,M12/I12-1) -> 0 | N13: =IF(J12=0,0,N12/J12-1) -> 0.20637212 | O13: =IF(K12=0,0,O12/K12-1) -> 0.054064219 | P13: =IF(L12=0,0,P12/L12-1) -> 0.040274799 | Q13: =IF(M12=0,0,Q12/M12-1) -> 0.037033227 | ... AS13: =IF(AO12=0,0,AS12/AO12-1) -> 0.035198274 | AT13: =OFFSET(AT13,LEFT(Summary!$D$4,1),0) -> 0.11 | AU13: =OFFSET(AU13,LEFT(Summary!$D$4,1),0) -> -0.01 | AV13: =OFFSET(AV13,LEFT(Summary!$D$4,1),0) -> -0.01 | AW13: =OFFSET(AW13,LEFT(Summary!$D$4,1),0) -> -0.01 | AX13: =OFFSET(AX13,LEFT(Summary!$D$4,1),0) -> 0.01 | AY13: =OFFSET(AY13,LEFT(Summary!$D$4,1),0) -> 0.01 | AZ13: =OFFSET(AZ13,LEFT(Summary!$D$4,1),0) -> 0.01 | BA13: =OFFSET(BA13,LEFT(Summary!$D$4,1),0) -> 0.01 | ... BI13: =OFFSET(BI13,LEFT(Summary!$D$4,1),0) -> 0.01 | BM13: =BM12/BL12-1 -> 0.077541496 | BN13: =BN12/BM12-1 -> 0.0035120922 | BO13: =BO12/BN12-1 -> 0.043975826 | BP13: =BP12/BO12-1 -> 0.0028233867 | BQ13: =BQ12/BP12-1 -> -0.0084045853 | BR13: =BR12/BQ12-1 -> 0.047555907 | BS13: =BS12/BR12-1 -> 0.010664261 | BT13: =BT12/BS12-1 -> 0.00023623287 | ... BX13: =BX12/BW12-1 -> 0.01
D14: Bull | AT14: =AT15+0.01 -> 0.12 | AU14: =AU15+0.01 -> 0 | AV14: =AV15+0.01 -> 0 | AW14: =AW15+0.01 -> 0 | AX14: =AX15+0.01 -> 0.02 | AY14: =AY15+0.01 -> 0.02 | AZ14: =AZ15+0.01 -> 0.02 | BA14: =BA15+0.01 -> 0.02 | ... BI14: =BI15+0.01 -> 0.02
D15: Base | AO15: street --> | AP15: 0.0061 | AQ15: 0.0217 | AR15: -0.0265 | AT15: 0.11 | AU15: -0.01 | AV15: -0.01 | AW15: -0.01 | AX15: 0.01 | AY15: 0.01 | AZ15: 0.01 | BA15: 0.01 | BB15: 0.01 | BC15: 0.01 | BD15: 0.01 | BE15: 0.01 | BF15: 0.01 | BG15: 0.01 | BH15: 0.01 | BI15: 0.01
D16: Bear | AT16: =AT15-0.01 -> 0.1 | AU16: =AU15-0.01 -> -0.02 | AV16: =AV15-0.01 -> -0.02 | AW16: =AW15-0.01 -> -0.02 | AX16: =AX15-0.02 -> -0.01 | AY16: =AY15-0.02 -> -0.01 | AZ16: =AZ15-0.02 -> -0.01 | BA16: =BA15-0.02 -> -0.01 | BB16: =BB15-0.02 -> -0.01 | BC16: =BC15-0.02 -> -0.01 | BD16: =BD15-0.02 -> -0.01 | BE16: =BE15-0.02 -> -0.01 | ... BI16: =BI15-0.02 -> -0.01
C17: Revenue | F17: ='Canalyst HC - Q'!C19 -> 352.67 | G17: ='Canalyst HC - Q'!D19 -> 464.859 | H17: ='Canalyst HC - Q'!E19 -> 455.748 | I17: ='Canalyst HC - Q'!F19 -> 491.281 | J17: ='Canalyst HC - Q'!G19 -> 479.76 | K17: ='Canalyst HC - Q'!H19 -> 607.623 | L17: ='Canalyst HC - Q'!I19 -> 582.71 | M17: ='Canalyst HC - Q'!J19 -> 615.528 | ... AS17: ='Canalyst HC - Q'!AP19 -> 1152.9 | AT17: =AT18*AT12 -> 1046.9247 | AU17: =AU18*AU12 -> 1079.848 | AV17: =AV18*AV12 -> 1083.0307 | AW17: =AW18*AW12 -> 1152.7847 | AX17: =AX18*AX12 -> 1078.5418 | AY17: =AY18*AY12 -> 1112.4594 | AZ17: =AZ18*AZ12 -> 1115.7382 | BA17: =BA18*BA12 -> 1187.5988 | ... BI17: =BI18*BI12 -> 1260.4129 | BK17: =SUMIF($F$1:$BI$1,BK$1,$F17:$BI17) -> 1764.558 | BL17: =SUMIF($F$1:$BI$1,BL$1,$F17:$BI17) -> 2285.621 | BM17: =SUMIF($F$1:$BI$1,BM$1,$F17:$BI17) -> 2395.213 | BN17: =SUMIF($F$1:$BI$1,BN$1,$F17:$BI17) -> 2582.478 | BO17: =SUMIF($F$1:$BI$1,BO$1,$F17:$BI17) -> 2760.827 | BP17: =SUMIF($F$1:$BI$1,BP$1,$F17:$BI17) -> 3020.887 | BQ17: =SUMIF($F$1:$BI$1,BQ$1,$F17:$BI17) -> 3521.181 | BR17: =SUMIF($F$1:$BI$1,BR$1,$F17:$BI17) -> 3908.763 | ... BX17: =SUMIF($F$1:$BI$1,BX$1,$F17:$BI17) -> 4769.8953
C18: Avg Sales / Case ($) | F18: =IF(F12=0,0,F17/F12) -> 0 | G18: =IF(G12=0,0,G17/G12) -> 0 | H18: =IF(H12=0,0,H17/H12) -> 0 | I18: =IF(I12=0,0,I17/I12) -> 0 | J18: =IF(J12=0,0,J17/J12) -> 10.305717 | K18: =IF(K12=0,0,K17/K12) -> 10.11163 | L18: =IF(L12=0,0,L17/L12) -> 10.31221 | M18: =IF(M12=0,0,M17/M12) -> 10.0507 | ... AS18: =IF(AS12=0,0,AS17/AS12) -> 15.806575 | AT18: =AP18*(1+AT19) -> 16.087182 | AU18: =AQ18*(1+AU19) -> 16.162454 | AV18: =AR18*(1+AV19) -> 16.160283 | AW18: =AS18*(1+AW19) -> 15.964641 | AX18: =AT18*(1+AX19) -> 16.408925 | AY18: =AU18*(1+AY19) -> 16.485703 | AZ18: =AV18*(1+AZ19) -> 16.483489 | BA18: =AW18*(1+BA19) -> 16.283934 | ... BI18: =BE18*(1+BI19) -> 16.941805 | BM18: =BM17/BL17-1 -> 0.047948457 | BN18: =BN17/BM17-1 -> 0.078183026 | BO18: =BO17/BN17-1 -> 0.069061189 | BP18: =BP17/BO17-1 -> 0.094196413 | BQ18: =BQ17/BP17-1 -> 0.16561162 | BR18: =BR17/BQ17-1 -> 0.11007159 | BS18: =BS17/BR17-1 -> 0.053800397 | BT18: =BT17/BS17-1 -> 0.031749022 | ... BX18: =BX17/BW17-1 -> 0.0302
C19: YoY Growth % | J19: =IF(F18=0,0,J18/F18-1) -> 0 | K19: =IF(G18=0,0,K18/G18-1) -> 0 | L19: =IF(H18=0,0,L18/H18-1) -> 0 | M19: =IF(I18=0,0,M18/I18-1) -> 0 | N19: =IF(J18=0,0,N18/J18-1) -> -0.032247901 | O19: =IF(K18=0,0,O18/K18-1) -> -0.0050878951 | P19: =IF(L18=0,0,P18/L18-1) -> 0.022314337 | Q19: =IF(M18=0,0,Q18/M18-1) -> -0.094207775 | ... AS19: =IF(AO18=0,0,AS18/AO18-1) -> 0.027872352 | AT19: =OFFSET(AT19,LEFT(Summary!$D$4,1),0) -> 0.01 | AU19: =OFFSET(AU19,LEFT(Summary!$D$4,1),0) -> 0.01 | AV19: =OFFSET(AV19,LEFT(Summary!$D$4,1),0) -> 0.01 | AW19: =OFFSET(AW19,LEFT(Summary!$D$4,1),0) -> 0.01 | AX19: =OFFSET(AX19,LEFT(Summary!$D$4,1),0) -> 0.02 | AY19: =OFFSET(AY19,LEFT(Summary!$D$4,1),0) -> 0.02 | AZ19: =OFFSET(AZ19,LEFT(Summary!$D$4,1),0) -> 0.02 | BA19: =OFFSET(BA19,LEFT(Summary!$D$4,1),0) -> 0.02 | ... BI19: =OFFSET(BI19,LEFT(Summary!$D$4,1),0) -> 0.02
D20: Bull | AT20: =AT21+0.01 -> 0.02 | AU20: =AU21+0.01 -> 0.02 | AV20: =AV21+0.01 -> 0.02 | AW20: =AW21+0.01 -> 0.02 | AX20: =AX21+0.01 -> 0.03 | AY20: =AY21+0.01 -> 0.03 | AZ20: =AZ21+0.01 -> 0.03 | BA20: =BA21+0.01 -> 0.03 | ... BI20: =BI21+0.01 -> 0.03
D21: Base | AT21: 0.01 | AU21: 0.01 | AV21: 0.01 | AW21: 0.01 | AX21: 0.02 | AY21: 0.02 | AZ21: 0.02 | BA21: 0.02 | BB21: 0.02 | BC21: 0.02 | BD21: 0.02 | BE21: 0.02 | BF21: 0.02 | BG21: 0.02 | BH21: 0.02 | BI21: 0.02
D22: Bear | AT22: =AT21-0.01 -> 0 | AU22: =AU21-0.01 -> 0 | AV22: =AV21-0.01 -> 0 | AW22: =AW21-0.01 -> 0 | AX22: =AX21-0.01 -> 0.01 | AY22: =AY21-0.01 -> 0.01 | AZ22: =AZ21-0.01 -> 0.01 | BA22: =BA21-0.01 -> 0.01 | ... BI22: =BI21-0.01 -> 0.01
B24: Still Beverages
C25: Case Volume (mm cases) | F25: ='Canalyst HC - Q'!C43 -> 0 | G25: ='Canalyst HC - Q'!D43 -> 0 | H25: ='Canalyst HC - Q'!E43 -> 0 | I25: ='Canalyst HC - Q'!F43 -> 0 | J25: ='Canalyst HC - Q'!G43 -> 18.6472 | K25: ='Canalyst HC - Q'!H43 -> 28.4085 | L25: ='Canalyst HC - Q'!I43 -> 30.2932 | M25: ='Canalyst HC - Q'!J43 -> 22.0577 | ... AC25: ='Canalyst HC - Q'!Z43 -> 24.9632 | AD25: 26.22 | AE25: 30.67 | AF25: 30.412 | AG25: 21.153 | AH25: ='Canalyst HC - Q'!AE43 -> 21.153 | AI25: ='Canalyst HC - Q'!AF43 -> 24.655 | AJ25: ='Canalyst HC - Q'!AG43 -> 25.546 | AK25: ='Canalyst HC - Q'!AH43 -> 20.141 | AL25: ='Canalyst HC - Q'!AI43 -> 20.326 | AM25: ='Canalyst HC - Q'!AJ43 -> 23.791 | AN25: ='Canalyst HC - Q'!AK43 -> 23.078 | AO25: ='Canalyst HC - Q'!AL43 -> 19.222 | ... AS25: ='Canalyst HC - Q'!AP43 -> 20.86 | AT25: =AP25*(1+AT26) -> 20.08878 | AU25: =AQ25*(1+AU26) -> 22.98681 | AV25: =AR25*(1+AV26) -> 24.87078 | AW25: =AS25*(1+AW26) -> 20.6514 | AX25: =AT25*(1+AX26) -> 20.289668 | AY25: =AU25*(1+AY26) -> 23.216678 | AZ25: =AV25*(1+AZ26) -> 25.119488 | BA25: =AW25*(1+BA26) -> 20.857914 | ... BI25: =BE25*(1+BI26) -> 21.277158 | BK25: =SUMIF($F$1:$BI$1,BK$1,$F25:$BI25) -> 0 | BL25: =SUMIF($F$1:$BI$1,BL$1,$F25:$BI25) -> 99.4066 | BM25: =SUMIF($F$1:$BI$1,BM$1,$F25:$BI25) -> 95.9068 | BN25: =SUMIF($F$1:$BI$1,BN$1,$F25:$BI25) -> 100.5576 | BO25: =SUMIF($F$1:$BI$1,BO$1,$F25:$BI25) -> 105.4872 | BP25: =SUMIF($F$1:$BI$1,BP$1,$F25:$BI25) -> 112.008 | BQ25: =SUMIF($F$1:$BI$1,BQ$1,$F25:$BI25) -> 108.455 | BR25: =SUMIF($F$1:$BI$1,BR$1,$F25:$BI25) -> 91.495 | ... BX25: =SUMIF($F$1:$BI$1,BX$1,$F25:$BI25) -> 91.282371
C26: YoY Growth % | J26: =IF(F25=0,0,J25/F25-1) -> 0 | K26: =IF(G25=0,0,K25/G25-1) -> 0 | L26: =IF(H25=0,0,L25/H25-1) -> 0 | M26: =IF(I25=0,0,M25/I25-1) -> 0 | N26: =IF(J25=0,0,N25/J25-1) -> 0.17122142 | O26: =IF(K25=0,0,O25/K25-1) -> -0.058038967 | P26: =IF(L25=0,0,P25/L25-1) -> -0.078426842 | Q26: =IF(M25=0,0,Q25/M25-1) -> -0.12095549 | ... AS26: =IF(AO25=0,0,AS25/AO25-1) -> 0.085214858 | AT26: =OFFSET(AT26,LEFT(Summary!$D$4,1),0) -> 0.11 | AU26: =OFFSET(AU26,LEFT(Summary!$D$4,1),0) -> -0.01 | AV26: =OFFSET(AV26,LEFT(Summary!$D$4,1),0) -> -0.01 | AW26: =OFFSET(AW26,LEFT(Summary!$D$4,1),0) -> -0.01 | AX26: =OFFSET(AX26,LEFT(Summary!$D$4,1),0) -> 0.01 | AY26: =OFFSET(AY26,LEFT(Summary!$D$4,1),0) -> 0.01 | AZ26: =OFFSET(AZ26,LEFT(Summary!$D$4,1),0) -> 0.01 | BA26: =OFFSET(BA26,LEFT(Summary!$D$4,1),0) -> 0.01 | ... BI26: =OFFSET(BI26,LEFT(Summary!$D$4,1),0) -> 0.01 | BM26: =BM25/BL25-1 -> -0.035206918 | BN26: =BN25/BM25-1 -> 0.048492912 | BO26: =BO25/BN25-1 -> 0.04902265 | BP26: =BP25/BO25-1 -> 0.061816031 | BQ26: =BQ25/BP25-1 -> -0.031720949 | BR26: =BR25/BQ25-1 -> -0.15637822 | BS26: =BS25/BR25-1 -> -0.055500301 | BT26: =BT25/BS25-1 -> 0.010206325 | ... BX26: =BX25/BW25-1 -> 0.01
D27: Bull | AT27: =AT28+0.01 -> 0.12 | AU27: =AU28+0.01 -> 0 | AV27: =AV28+0.01 -> 0 | AW27: =AW28+0.01 -> 0 | AX27: =AX28+0.01 -> 0.02 | AY27: =AY28+0.01 -> 0.02 | AZ27: =AZ28+0.01 -> 0.02 | BA27: =BA28+0.01 -> 0.02 | ... BI27: =BI28+0.01 -> 0.02
D28: Base | AT28: 0.11 | AU28: -0.01 | AV28: -0.01 | AW28: -0.01 | AX28: 0.01 | AY28: 0.01 | AZ28: 0.01 | BA28: 0.01 | BB28: 0.01 | BC28: 0.01 | BD28: 0.01 | BE28: 0.01 | BF28: 0.01 | BG28: 0.01 | BH28: 0.01 | BI28: 0.01
D29: Bear | AT29: =AT28-0.01 -> 0.1 | AU29: =AU28-0.01 -> -0.02 | AV29: =AV28-0.01 -> -0.02 | AW29: =AW28-0.01 -> -0.02 | AX29: =AX28-0.02 -> -0.01 | AY29: =AY28-0.02 -> -0.01 | AZ29: =AZ28-0.02 -> -0.01 | BA29: =BA28-0.02 -> -0.01 | BB29: =BB28-0.02 -> -0.01 | BC29: =BC28-0.02 -> -0.01 | BD29: =BD28-0.02 -> -0.01 | BE29: =BE28-0.02 -> -0.01 | ... BI29: =BI28-0.02 -> -0.01
C30: Revenue | F30: ='Canalyst HC - Q'!C20 -> 166.19 | G30: ='Canalyst HC - Q'!D20 -> 246.371 | H30: ='Canalyst HC - Q'!E20 -> 261.508 | I30: ='Canalyst HC - Q'!F20 -> 218.056 | J30: ='Canalyst HC - Q'!G20 -> 256.058 | K30: ='Canalyst HC - Q'!H20 -> 368.955 | L30: ='Canalyst HC - Q'!I20 -> 384.495 | M30: ='Canalyst HC - Q'!J20 -> 316.461 | ... AS30: ='Canalyst HC - Q'!AP20 -> 584.4 | AT30: =AT31*AT25 -> 570.81591 | AU30: =AU31*AU25 -> 626.01539 | AV30: =AV31*AV25 -> 643.22267 | AW30: =AW31*AW25 -> 584.34156 | AX30: =AX31*AX25 -> 588.05455 | AY30: =AY31*AY25 -> 644.92106 | AZ30: =AZ31*AZ25 -> 662.648 | BA30: =BA31*BA25 -> 601.98868 | ... BI30: =BI31*BI25 -> 638.89783 | BK30: =SUMIF($F$1:$BI$1,BK$1,$F30:$BI30) -> 892.125 | BL30: =SUMIF($F$1:$BI$1,BL$1,$F30:$BI30) -> 1325.969 | BM30: =SUMIF($F$1:$BI$1,BM$1,$F30:$BI30) -> 1471.491 | BN30: =SUMIF($F$1:$BI$1,BN$1,$F30:$BI30) -> 1558.944 | BO30: =SUMIF($F$1:$BI$1,BO$1,$F30:$BI30) -> 1641.716 | BP30: =SUMIF($F$1:$BI$1,BP$1,$F30:$BI30) -> 1861.162 | BQ30: =SUMIF($F$1:$BI$1,BQ$1,$F30:$BI30) -> 2023.955 | BR30: =SUMIF($F$1:$BI$1,BR$1,$F30:$BI30) -> 2147.823 | ... BX30: =SUMIF($F$1:$BI$1,BX$1,$F30:$BI30) -> 2650.746
C31: Avg Sales / Case ($) | F31: =IF(F25=0,0,F30/F25) -> 0 | G31: =IF(G25=0,0,G30/G25) -> 0 | H31: =IF(H25=0,0,H30/H25) -> 0 | I31: =IF(I25=0,0,I30/I25) -> 0 | J31: =IF(J25=0,0,J30/J25) -> 13.731713 | K31: =IF(K25=0,0,K30/K25) -> 12.987486 | L31: =IF(L25=0,0,L30/L25) -> 12.692452 | M31: =IF(M25=0,0,M30/M25) -> 14.346963 | ... AS31: =IF(AS25=0,0,AS30/AS25) -> 28.01534 | AT31: =AP31*(1+AT32) -> 28.414663 | AU31: =AQ31*(1+AU32) -> 27.233678 | AV31: =AR31*(1+AV32) -> 25.862585 | AW31: =AS31*(1+AW32) -> 28.295494 | AX31: =AT31*(1+AX32) -> 28.982956 | AY31: =AU31*(1+AY32) -> 27.778352 | AZ31: =AV31*(1+AZ32) -> 26.379837 | BA31: =AW31*(1+BA32) -> 28.861404 | ... BI31: =BE31*(1+BI32) -> 30.027404 | BM31: =BM30/BL30-1 -> 0.10974766 | BN31: =BN30/BM30-1 -> 0.059431556 | BO31: =BO30/BN30-1 -> 0.053094916 | BP31: =BP30/BO30-1 -> 0.13366867 | BQ31: =BQ30/BP30-1 -> 0.087468474 | BR31: =BR30/BQ30-1 -> 0.061200965 | BS31: =BS30/BR30-1 -> 0.036376834 | BT31: =BT30/BS30-1 -> 0.061532269 | ... BX31: =BX30/BW30-1 -> 0.0302
C32: YoY Growth % | J32: =IF(F31=0,0,J31/F31-1) -> 0 | K32: =IF(G31=0,0,K31/G31-1) -> 0 | L32: =IF(H31=0,0,L31/H31-1) -> 0 | M32: =IF(I31=0,0,M31/I31-1) -> 0 | N32: =IF(J31=0,0,N31/J31-1) -> 0.070077838 | O32: =IF(K31=0,0,O31/K31-1) -> 0.13084424 | P32: =IF(L31=0,0,P31/L31-1) -> 0.13110203 | Q32: =IF(M31=0,0,Q31/M31-1) -> 0.28247812 | ... AS32: =IF(AO31=0,0,AS31/AO31-1) -> 0.01357213 | AT32: =OFFSET(AT32,LEFT(Summary!$D$4,1),0) -> 0.01 | AU32: =OFFSET(AU32,LEFT(Summary!$D$4,1),0) -> 0.01 | AV32: =OFFSET(AV32,LEFT(Summary!$D$4,1),0) -> 0.01 | AW32: =OFFSET(AW32,LEFT(Summary!$D$4,1),0) -> 0.01 | AX32: =OFFSET(AX32,LEFT(Summary!$D$4,1),0) -> 0.02 | AY32: =OFFSET(AY32,LEFT(Summary!$D$4,1),0) -> 0.02 | AZ32: =OFFSET(AZ32,LEFT(Summary!$D$4,1),0) -> 0.02 | BA32: =OFFSET(BA32,LEFT(Summary!$D$4,1),0) -> 0.02 | ... BI32: =OFFSET(BI32,LEFT(Summary!$D$4,1),0) -> 0.02
D33: Bull | AT33: =AT34+0.01 -> 0.02 | AU33: =AU34+0.01 -> 0.02 | AV33: =AV34+0.01 -> 0.02 | AW33: =AW34+0.01 -> 0.02 | AX33: =AX34+0.01 -> 0.03 | AY33: =AY34+0.01 -> 0.03 | AZ33: =AZ34+0.01 -> 0.03 | BA33: =BA34+0.01 -> 0.03 | ... BI33: =BI34+0.01 -> 0.03
D34: Base | AT34: 0.01 | AU34: 0.01 | AV34: 0.01 | AW34: 0.01 | AX34: 0.02 | AY34: 0.02 | AZ34: 0.02 | BA34: 0.02 | BB34: 0.02 | BC34: 0.02 | BD34: 0.02 | BE34: 0.02 | BF34: 0.02 | BG34: 0.02 | BH34: 0.02 | BI34: 0.02
D35: Bear | AT35: =AT34-0.01 -> 0 | AU35: =AU34-0.01 -> 0 | AV35: =AV34-0.01 -> 0 | AW35: =AW34-0.01 -> 0 | AX35: =AX34-0.01 -> 0.01 | AY35: =AY34-0.01 -> 0.01 | AZ35: =AZ34-0.01 -> 0.01 | BA35: =BA34-0.01 -> 0.01 | ... BI35: =BI34-0.01 -> 0.01
B37: Sales to Other Bottlers
C38: Revenue | F38: ='Canalyst HC - Q'!C22 -> 50.21 | G38: ='Canalyst HC - Q'!D22 -> 61.045 | H38: ='Canalyst HC - Q'!E22 -> 58.683 | I38: ='Canalyst HC - Q'!F22 -> 68.244 | J38: ='Canalyst HC - Q'!G22 -> 64.73 | K38: ='Canalyst HC - Q'!H22 -> 104.968 | L38: ='Canalyst HC - Q'!I22 -> 104.619 | M38: ='Canalyst HC - Q'!J22 -> 108.748 | ... AS38: ='Canalyst HC - Q'!AP22 -> 104.727 | AT38: =AP38*(1+AT39) -> 88.51408 | AU38: =AQ38*(1+AU39) -> 98.23419 | AV38: =AR38*(1+AV39) -> 100.55066 | AW38: =AS38*(1+AW39) -> 107.86881 | AX38: =AT38*(1+AX39) -> 91.169502 | AY38: =AU38*(1+AY39) -> 101.18122 | AZ38: =AV38*(1+AZ39) -> 103.56718 | BA38: =AW38*(1+BA39) -> 111.10487 | ... BI38: =BE38*(1+BI39) -> 117.87116 | BK38: =SUMIF($F$1:$BI$1,BK$1,$F38:$BI38) -> 238.182 | BL38: =SUMIF($F$1:$BI$1,BL$1,$F38:$BI38) -> 383.065 | BM38: =SUMIF($F$1:$BI$1,BM$1,$F38:$BI38) -> 387.716 | BN38: =SUMIF($F$1:$BI$1,BN$1,$F38:$BI38) -> 342.062 | BO38: =SUMIF($F$1:$BI$1,BO$1,$F38:$BI38) -> 329.574 | BP38: =SUMIF($F$1:$BI$1,BP$1,$F38:$BI38) -> 347.185 | BQ38: =SUMIF($F$1:$BI$1,BQ$1,$F38:$BI38) -> 349.837 | BR38: =SUMIF($F$1:$BI$1,BR$1,$F38:$BI38) -> 353.819 | ... BX38: =SUMIF($F$1:$BI$1,BX$1,$F38:$BI38) -> 431.81046
C39: YoY Growth % | J39: =IF(F38=0,0,J38/F38-1) -> 0.28918542 | K39: =IF(G38=0,0,K38/G38-1) -> 0.71951839 | L39: =IF(H38=0,0,L38/H38-1) -> 0.78278207 | M39: =IF(I38=0,0,M38/I38-1) -> 0.59351738 | N39: =IF(J38=0,0,N38/J38-1) -> 0.57166692 | O39: =IF(K38=0,0,O38/K38-1) -> 0.018843838 | P39: =IF(L38=0,0,P38/L38-1) -> -0.11929 | Q39: =IF(M38=0,0,Q38/M38-1) -> -0.20093243 | ... AS39: =IF(AO38=0,0,AS38/AO38-1) -> 0.21596015 | AT39: 0.03 | AU39: 0.03 | AV39: 0.03 | AW39: 0.03 | AX39: 0.03 | AY39: 0.03 | AZ39: 0.03 | BA39: 0.03 | BB39: 0.03 | BC39: 0.03 | BD39: 0.03 | BE39: 0.03 | BF39: 0.03 | BG39: 0.03 | BH39: 0.03 | BI39: 0.03
B41: Post-Mix and Other
C42: Revenue | F42: ='Canalyst HC - Q'!C23 -> 56.386 | G42: ='Canalyst HC - Q'!D23 -> 68.109 | H42: ='Canalyst HC - Q'!E23 -> 73.089 | I42: ='Canalyst HC - Q'!F23 -> 63.979 | J42: ='Canalyst HC - Q'!G23 -> 65.154 | K42: ='Canalyst HC - Q'!H23 -> 87.745 | L42: ='Canalyst HC - Q'!I23 -> 90.702 | M42: ='Canalyst HC - Q'!J23 -> 85.412 | ... AS42: ='Canalyst HC - Q'!AP23 -> 62.249 | AT42: =AP42*(1+AT43) -> 52.57841 | AU42: =AQ42*(1+AU43) -> 55.73536 | AV42: =AR42*(1+AV43) -> 66.19707 | AW42: =AS42*(1+AW43) -> 64.11647 | AX42: =AT42*(1+AX43) -> 54.155762 | AY42: =AU42*(1+AY43) -> 57.407421 | AZ42: =AV42*(1+AZ43) -> 68.182982 | BA42: =AW42*(1+BA43) -> 66.039964 | ... BI42: =BE42*(1+BI43) -> 70.061798 | BK42: =SUMIF($F$1:$BI$1,BK$1,$F42:$BI42) -> 261.563 | BL42: =SUMIF($F$1:$BI$1,BL$1,$F42:$BI42) -> 329.013 | BM42: =SUMIF($F$1:$BI$1,BM$1,$F42:$BI42) -> 370.944 | BN42: =SUMIF($F$1:$BI$1,BN$1,$F42:$BI42) -> 343.065 | BO42: =SUMIF($F$1:$BI$1,BO$1,$F42:$BI42) -> 275.24 | BP42: =SUMIF($F$1:$BI$1,BP$1,$F42:$BI42) -> 333.48 | BQ42: =SUMIF($F$1:$BI$1,BQ$1,$F42:$BI42) -> 309.747 | BR42: =SUMIF($F$1:$BI$1,BR$1,$F42:$BI42) -> 258.267 | ... BX42: =SUMIF($F$1:$BI$1,BX$1,$F42:$BI42) -> 260.7545
C43: YoY Growth % | J43: =IF(F42=0,0,J42/F42-1) -> 0.15549959 | K43: =IF(G42=0,0,K42/G42-1) -> 0.28830257 | L43: =IF(H42=0,0,L42/H42-1) -> 0.24098017 | M43: =IF(I42=0,0,M42/I42-1) -> 0.33500055 | N43: =IF(J42=0,0,N42/J42-1) -> 0.258572 | O43: =IF(K42=0,0,O42/K42-1) -> -0.056048778 | P43: =IF(L42=0,0,P42/L42-1) -> 0.0076293797 | Q43: =IF(M42=0,0,Q42/M42-1) -> 0.34316021 | ... AS43: =IF(AO42=0,0,AS42/AO42-1) -> 0.087090915 | AT43: 0.03 | AU43: 0.03 | AV43: 0.03 | AW43: 0.03 | AX43: 0.03 | AY43: 0.03 | AZ43: 0.03 | BA43: 0.03 | BB43: 0.03 | BC43: 0.03 | BD43: 0.03 | BE43: 0.03 | BF43: 0.03 | BG43: 0.03 | BH43: 0.03 | BI43: 0.03

Sheet COGS Sensitivity
B1: COKE — Aluminum Sensitivity
B2: ($ in mm except where noted)
F4: ='WH Model'!F4 -> 42460 | G4: ='WH Model'!G4 -> 42551 | H4: ='WH Model'!H4 -> 42643 | I4: ='WH Model'!I4 -> 42735 | J4: ='WH Model'!J4 -> 42825 | K4: ='WH Model'!K4 -> 42916 | L4: ='WH Model'!L4 -> 43008 | M4: ='WH Model'!M4 -> 43100 | ... BI4: ='WH Model'!BI4 -> 47483
F5: ='WH Model'!F5 -> Q1 16 | G5: ='WH Model'!G5 -> Q2 16 | H5: ='WH Model'!H5 -> Q3 16 | I5: ='WH Model'!I5 -> Q4 16 | J5: ='WH Model'!J5 -> Q1 17 | K5: ='WH Model'!K5 -> Q2 17 | L5: ='WH Model'!L5 -> Q3 17 | M5: ='WH Model'!M5 -> Q4 17 | ... BI5: ='WH Model'!BI5 -> Q4 29
AS6: =SUM(AP9:AS9)/SUM(AP7:AS7) -> 0.013433466
B7: Total COGS | F7: ='WH Model'!F40 -> 381.558 | G7: ='WH Model'!G40 -> 520.677 | H7: ='WH Model'!H40 -> 521.838 | I7: ='WH Model'!I40 -> 516.633 | J7: ='WH Model'!J40 -> 533.681 | K7: ='WH Model'!K40 -> 754.113 | L7: ='WH Model'!L40 -> 752.202 | M7: ='WH Model'!M40 -> 742.725 | ... AS7: ='WH Model'!AS40 -> 1149.996 | AT7: =SUM(AT8:AT10) -> 1129.9912 | AU7: =SUM(AU8:AU10) -> 1196.7167 | AV7: =SUM(AV8:AV10) -> 1206.5883 | AW7: =SUM(AW8:AW10) -> 1203.4099 | AX7: =SUM(AX8:AX10) -> 1177.6653 | AY7: =SUM(AY8:AY10) -> 1222.2684 | AZ7: =SUM(AZ8:AZ10) -> 1230.3595 | BA7: =SUM(BA8:BA10) -> 1223.1996 | ... BI7: =SUM(BI8:BI10) -> 1304.1289
C8: Aluminum COGS | R8: =R42 -> 39.834376 | S8: =S42 -> 44.688354 | T8: =T42 -> 43.660443 | U8: =U42 -> 39.225368 | V8: =V42 -> 37.791483 | W8: =W42 -> 35.558454 | X8: =X42 -> 42.978872 | Y8: =Y42 -> 45.330237 | ... BI8: =BI42 -> 137.6297
C9: PET Resin COGS | J9: =J55 -> 12.670813 | K9: =K55 -> 17.415217 | L9: =L55 -> 17.29287 | M9: =M55 -> 18.020964 | N9: =N55 -> 17.550387 | O9: =O55 -> 21.943438 | P9: =P55 -> 22.920517 | Q9: =Q55 -> 23.527539 | ... BI9: =BI55 -> 17.756567
C10: Other COGS | J10: =J7-J8-J9 -> 521.01019 | K10: =K7-K8-K9 -> 736.69778 | L10: =L7-L8-L9 -> 734.90913 | M10: =M7-M8-M9 -> 724.70404 | N10: =N7-N8-N9 -> 689.56561 | O10: =O7-O8-O9 -> 793.35156 | P10: =P7-P8-P9 -> 768.39648 | Q10: =Q7-Q8-Q9 -> 732.39646 | ... AS10: =AS7-AS8-AS9 -> 1020.3001 | AT10: =AT11*AT24 -> 993.41582 | AU10: =AU11*AU24 -> 1032.3049 | AV10: =AV11*AV24 -> 1040.2856 | AW10: =AW11*AW24 -> 1035.3496 | AX10: =AX11*AX24 -> 1028.4337 | AY10: =AY11*AY24 -> 1068.6936 | AZ10: =AZ11*AZ24 -> 1076.9557 | BA10: =BA11*BA24 -> 1071.8456 | ... BI10: =BI11*BI24 -> 1148.7426
J11: =J10/J24 -> 7.9909538 | K11: =K10/K24 -> 8.3242687 | L11: =L10/L24 -> 8.466695 | M11: =M10/M24 -> 8.6999284 | N11: =N10/N24 -> 8.8405848 | O11: =O10/O24 -> 8.8052338 | P11: =P10/P24 -> 8.8627045 | Q11: =Q10/Q24 -> 8.834698 | ... AS11: =AS10/AS24 -> 10.877632 | AT11: =AP11*(1+AT12) -> 11.664332 | AU11: =AQ11*(1+AU12) -> 11.495736 | AV11: =AR11*(1+AV12) -> 11.321132 | AW11: =AS11*(1+AW12) -> 11.149573 | AX11: =AT11*(1+AX12) -> 11.95594 | AY11: =AU11*(1+AY12) -> 11.783129 | AZ11: =AV11*(1+AZ12) -> 11.604161 | BA11: =AW11*(1+BA12) -> 11.428312 | ... BI11: =BE11*(1+BI12) -> 12.00687
N12: =N11/J11-1 -> 0.1063241 | O12: =O11/K11-1 -> 0.057778653 | P12: =P11/L11-1 -> 0.046772617 | Q12: =Q11/M11-1 -> 0.015490882 | R12: =R11/N11-1 -> -0.054318869 | S12: =S11/O11-1 -> -0.031298473 | T12: =T11/P11-1 -> -0.033632986 | U12: =U11/Q11-1 -> -0.041101029 | ... AS12: =AS11/AO11-1 -> 0.013418685 | AT12: 0.025 | AU12: 0.025 | AV12: 0.025 | AW12: 0.025 | AX12: 0.025 | AY12: 0.025 | AZ12: 0.025 | BA12: 0.025 | BB12: 0.025 | BC12: 0.025 | BD12: 0.025 | BE12: 0.025 | BF12: 0.025 | BG12: 0.025 | BH12: 0.025 | BI12: 0.025
B13: Bloomberg Quarterly Historical Pulls
D14: LME Aluminum ($/MT) | E14: LMAHDS03 Comdty | F14: =_xll.BDP("LMAHDS03 Comdty","INTERVAL_AVG","CALC_INTERVAL=1Q","END_DATE_OVERRIDE",F4) -> 1515.2661 | G14: =_xll.BDP("LMAHDS03 Comdty","INTERVAL_AVG","CALC_INTERVAL=1Q","END_DATE_OVERRIDE",G4) -> 1583.1587 | H14: =_xll.BDP("LMAHDS03 Comdty","INTERVAL_AVG","CALC_INTERVAL=1Q","END_DATE_OVERRIDE",H4) -> 1632.3984 | I14: =_xll.BDP("LMAHDS03 Comdty","INTERVAL_AVG","CALC_INTERVAL=1Q","END_DATE_OVERRIDE",I4) -> 1709.2222 | J14: =_xll.BDP("LMAHDS03 Comdty","INTERVAL_AVG","CALC_INTERVAL=1Q","END_DATE_OVERRIDE",J4) -> 1858.1172 | K14: =_xll.BDP("LMAHDS03 Comdty","INTERVAL_AVG","CALC_INTERVAL=1Q","END_DATE_OVERRIDE",K4) -> 1912.918 | L14: =_xll.BDP("LMAHDS03 Comdty","INTERVAL_AVG","CALC_INTERVAL=1Q","END_DATE_OVERRIDE",L4) -> 2026.7031 | M14: =_xll.BDP("LMAHDS03 Comdty","INTERVAL_AVG","CALC_INTERVAL=1Q","END_DATE_OVERRIDE",M4) -> 2121.8333 | ... AU14: =_xll.BDP("LMAHDS03 Comdty","INTERVAL_AVG","CALC_INTERVAL=1Q","END_DATE_OVERRIDE",AU4) -> 3545.6364 | AV14: =AU14 -> 3545.6364 | AW14: =AV14 -> 3545.6364 | AX14: =AW14*0.97 -> 3439.2673 | AY14: =AX14*0.97 -> 3336.0893 | AZ14: =AY14*0.97 -> 3236.0066 | BA14: =AZ14*0.97 -> 3138.9264 | BB14: =BA14*0.97 -> 3044.7586 | BC14: =BB14 -> 3044.7586 | BD14: =BC14 -> 3044.7586 | BE14: =BD14 -> 3044.7586 | BF14: =BE14 -> 3044.7586 | BG14: =BF14 -> 3044.7586 | BH14: =BG14 -> 3044.7586 | BI14: =BH14 -> 3044.7586
D15: Midwest Premium ($/MT) | E15: PUL1 Comdty | R15: =_xll.BDP("PUL1 Comdty","INTERVAL_AVG","CALC_INTERVAL=1Q","END_DATE_OVERRIDE",R4) -> 424.376 | S15: =_xll.BDP("PUL1 Comdty","INTERVAL_AVG","CALC_INTERVAL=1Q","END_DATE_OVERRIDE",S4) -> 417.35295 | T15: =_xll.BDP("PUL1 Comdty","INTERVAL_AVG","CALC_INTERVAL=1Q","END_DATE_OVERRIDE",T4) -> 392.13484 | U15: =_xll.BDP("PUL1 Comdty","INTERVAL_AVG","CALC_INTERVAL=1Q","END_DATE_OVERRIDE",U4) -> 357.24048 | V15: =_xll.BDP("PUL1 Comdty","INTERVAL_AVG","CALC_INTERVAL=1Q","END_DATE_OVERRIDE",V4) -> 305.07859 | W15: =_xll.BDP("PUL1 Comdty","INTERVAL_AVG","CALC_INTERVAL=1Q","END_DATE_OVERRIDE",W4) -> 198.95164 | X15: =_xll.BDP("PUL1 Comdty","INTERVAL_AVG","CALC_INTERVAL=1Q","END_DATE_OVERRIDE",X4) -> 280.21156 | Y15: =_xll.BDP("PUL1 Comdty","INTERVAL_AVG","CALC_INTERVAL=1Q","END_DATE_OVERRIDE",Y4) -> 283.84698 | ... AU15: =_xll.BDP("PUL1 Comdty","INTERVAL_AVG","CALC_INTERVAL=1Q","END_DATE_OVERRIDE",AU4) -> 2452.6036 | AV15: =600+0.5*AV14 -> 2372.8182 | AW15: =600+0.5*AW14 -> 2372.8182 | AX15: =600+0.5*AX14 -> 2319.6336 | AY15: =600+0.5*AY14 -> 2268.0446 | AZ15: =600+0.5*AZ14 -> 2218.0033 | BA15: =600+0.5*BA14 -> 2169.4632 | BB15: =600+0.5*BB14 -> 2122.3793 | BC15: =600+0.5*BC14 -> 2122.3793 | ... BI15: =600+0.5*BI14 -> 2122.3793
D16: All in US Price ($/MT) | R16: =SUM(R14:R15) -> 2307.0244 | S16: =SUM(S14:S15) -> 2236.3857 | T16: =SUM(T14:T15) -> 2182.5333 | U16: =SUM(U14:U15) -> 2117.4151 | V16: =SUM(V14:V15) -> 2018.2583 | W16: =SUM(W14:W15) -> 1730.1566 | X16: =SUM(X14:X15) -> 2024.5397 | Y16: =SUM(Y14:Y15) -> 2217.7914 | ... BI16: =SUM(BI14:BI15) -> 5167.1379
P17: CCK Markup --> | R17: =R16*2 -> 4614.0489 | S17: =S16*2 -> 4472.7715 | T17: =T16*2 -> 4365.0666 | U17: =U16*2 -> 4234.8302 | V17: =V16*2 -> 4036.5166 | W17: =W16*2 -> 3460.3131 | X17: =X16*2 -> 4049.0794 | Y17: =Y16*2 -> 4435.5829 | ... BI17: =BI16*2 -> 10334.276
D19: Y/Y Change — LME | J19: =IFERROR(J14/F14-1,0) -> 0.22626458 | K19: =IFERROR(K14/G14-1,0) -> 0.208292 | L19: =IFERROR(L14/H14-1,0) -> 0.24154929 | M19: =IFERROR(M14/I14-1,0) -> 0.24140285 | N19: =IFERROR(N14/J14-1,0) -> 0.16244996 | O19: =IFERROR(O14/K14-1,0) -> 0.18228006 | P19: =IFERROR(P14/L14-1,0) -> 0.019616989 | Q19: =IFERROR(Q14/M14-1,0) -> -0.070095118 | ... BI19: =IFERROR(BI14/BE14-1,0) -> 0
D20: Y/Y Change — MWP | J20: =IFERROR(J15/F15-1,0) -> 0 | K20: =IFERROR(K15/G15-1,0) -> 0 | L20: =IFERROR(L15/H15-1,0) -> 0 | M20: =IFERROR(M15/I15-1,0) -> 0 | N20: =IFERROR(N15/J15-1,0) -> 0 | O20: =IFERROR(O15/K15-1,0) -> 0 | P20: =IFERROR(P15/L15-1,0) -> 0 | Q20: =IFERROR(Q15/M15-1,0) -> 0 | ... BI20: =IFERROR(BI15/BE15-1,0) -> 0
D21: Y/Y Change — Combined ($/lb) | J21: =IFERROR(J16/F16-1,0) -> 0 | K21: =IFERROR(K16/G16-1,0) -> 0 | L21: =IFERROR(L16/H16-1,0) -> 0 | M21: =IFERROR(M16/I16-1,0) -> 0 | N21: =IFERROR(N16/J16-1,0) -> 0 | O21: =IFERROR(O16/K16-1,0) -> 0 | P21: =IFERROR(P16/L16-1,0) -> 0 | Q21: =IFERROR(Q16/M16-1,0) -> 0 | ... BI21: =IFERROR(BI16/BE16-1,0) -> 0
B23: Volume Mix & Aluminum Demand
D24: Total Physical Case Volume (mm cases) | J24: ='Canalyst HC - Q'!G44 -> 65.2 | K24: ='Canalyst HC - Q'!H44 -> 88.5 | L24: ='Canalyst HC - Q'!I44 -> 86.8 | M24: ='Canalyst HC - Q'!J44 -> 83.3 | N24: ='Canalyst HC - Q'!K44 -> 78 | O24: ='Canalyst HC - Q'!L44 -> 90.1 | P24: ='Canalyst HC - Q'!M44 -> 86.7 | Q24: ='Canalyst HC - Q'!N44 -> 82.9 | ... AS24: ='Canalyst HC - Q'!AP44 -> 93.798 | AT24: ='Segment Build'!AT12+'Segment Build'!AT25 -> 85.16697 | AU24: ='Segment Build'!AU12+'Segment Build'!AU25 -> 89.79894 | AV24: ='Segment Build'!AV12+'Segment Build'!AV25 -> 91.88883 | AW24: ='Segment Build'!AW12+'Segment Build'!AW25 -> 92.86002 | AX24: ='Segment Build'!AX12+'Segment Build'!AX25 -> 86.01864 | AY24: ='Segment Build'!AY12+'Segment Build'!AY25 -> 90.696929 | AZ24: ='Segment Build'!AZ12+'Segment Build'!AZ25 -> 92.807718 | BA24: ='Segment Build'!BA12+'Segment Build'!BA25 -> 93.78862 | ... BI24: ='Segment Build'!BI12+'Segment Build'!BI25 -> 95.673771
D25: % Volume in Aluminum Cans | J25: 0.45 | K25: 0.45 | L25: 0.45 | M25: 0.45 | N25: 0.46 | O25: 0.46 | P25: 0.46 | Q25: 0.46 | R25: 0.46 | S25: 0.46 | T25: 0.46 | U25: 0.46 | V25: 0.47 | W25: 0.47 | X25: 0.47 | Y25: 0.47 | Z25: 0.48 | AA25: 0.48 | AB25: 0.48 | AC25: 0.48 | AD25: 0.49 | AE25: 0.49 | AF25: 0.49 | AG25: 0.49 | AH25: 0.51 | AI25: 0.51 | AJ25: 0.51 | AK25: 0.51 | AL25: 0.53 | AM25: 0.53 | AN25: 0.53 | AO25: 0.53 | AP25: 0.54 | AQ25: 0.54 | AR25: 0.54 | AS25: 0.54 | AT25: 0.55 | AU25: 0.55 | AV25: 0.55 | AW25: 0.55 | AX25: 0.56 | AY25: 0.56 | AZ25: 0.56 | BA25: 0.56 | BB25: 0.57 | BC25: 0.57 | BD25: 0.57 | BE25: 0.57 | BF25: 0.58 | BG25: 0.58 | BH25: 0.58 | BI25: 0.58
D26: % Volume in Plastic Bottles | J26: =1-J25 -> 0.55 | K26: =1-K25 -> 0.55 | L26: =1-L25 -> 0.55 | M26: =1-M25 -> 0.55 | N26: =1-N25 -> 0.54 | O26: =1-O25 -> 0.54 | P26: =1-P25 -> 0.54 | Q26: =1-Q25 -> 0.54 | ... BI26: =1-BI25 -> 0.42
D27: Cases in Cans (mm) | J27: =J24*J25 -> 29.34 | K27: =K24*K25 -> 39.825 | L27: =L24*L25 -> 39.06 | M27: =M24*M25 -> 37.485 | N27: =N24*N25 -> 35.88 | O27: =O24*O25 -> 41.446 | P27: =P24*P25 -> 39.882 | Q27: =Q24*Q25 -> 38.134 | ... BI27: =BI24*BI25 -> 55.490787
D28: Cases in Bottles (mm) | J28: =J24*J26 -> 35.86 | K28: =K24*K26 -> 48.675 | L28: =L24*L26 -> 47.74 | M28: =M24*M26 -> 45.815 | N28: =N24*N26 -> 42.12 | O28: =O24*O26 -> 48.654 | P28: =P24*P26 -> 46.818 | Q28: =Q24*Q26 -> 44.766 | ... BI28: =BI24*BI26 -> 40.182984
B30: Aluminum Content per Case
D31: Standard Physical Case (fl oz) | E31: 192
D32: Standard Can Size (fl oz) | E32: 12
D33: Cans per physical case (all-can basis) | E33: =E31/E32 -> 16
D34: Aluminum per 12 oz can (g) | E34: 15
D35: Aluminum per all-can case (KG) | E35: =E33*E34/1000 -> 0.24
D37: Aluminum KG per total case (mix-adj.) | J37: =$E$35*J25 -> 0.108 | K37: =$E$35*K25 -> 0.108 | L37: =$E$35*L25 -> 0.108 | M37: =$E$35*M25 -> 0.108 | N37: =$E$35*N25 -> 0.1104 | O37: =$E$35*O25 -> 0.1104 | P37: =$E$35*P25 -> 0.1104 | Q37: =$E$35*Q25 -> 0.1104 | ... BI37: =$E$35*BI25 -> 0.1392
B39: Aluminum Demand & Cost
D40: Aluminum Volume (mm KG) | J40: =J24*J37 -> 7.0416 | K40: =K24*K37 -> 9.558 | L40: =L24*L37 -> 9.3744 | M40: =M24*M37 -> 8.9964 | N40: =N24*N37 -> 8.6112 | O40: =O24*O37 -> 9.94704 | P40: =P24*P37 -> 9.57168 | Q40: =Q24*Q37 -> 9.15216 | ... BI40: =BI24*BI37 -> 13.317789
D41: All-in Cost ($/KG) | R41: =R17 -> 4614.0489 | S41: =S17 -> 4472.7715 | T41: =T17 -> 4365.0666 | U41: =U17 -> 4234.8302 | V41: =V17 -> 4036.5166 | W41: =W17 -> 3460.3131 | X41: =X17 -> 4049.0794 | Y41: =Y17 -> 4435.5829 | ... BI41: =BI17 -> 10334.276
D42: Aluminum Spend ($M) | R42: =R40*R41/1000 -> 39.834376 | S42: =S40*S41/1000 -> 44.688354 | T42: =T40*T41/1000 -> 43.660443 | U42: =U40*U41/1000 -> 39.225368 | V42: =V40*V41/1000 -> 37.791483 | W42: =W40*W41/1000 -> 35.558454 | X42: =X40*X41/1000 -> 42.978872 | Y42: =Y40*Y41/1000 -> 45.330237 | ... BI42: =BI40*BI41/1000 -> 137.6297
D43: Y/Y Change in Spend ($M) | V43: =V42-R42 -> -2.0428932 | W43: =W42-S42 -> -9.1299 | X43: =X42-T42 -> -0.68157133 | Y43: =Y42-U42 -> 6.104869 | Z43: =Z42-V42 -> 11.396814 | AA43: =AA42-W42 -> 30.365637 | AB43: =AB42-X42 -> 29.701362 | AC43: =AC42-Y42 -> 24.965979 | ... BI43: =BI42-BE42 -> 3.712102
B45: PET Resin Cost ($ / MT) | F45: =_xll.BDP("PUSAPEBG Index","INTERVAL_AVG","CALC_INTERVAL=1Q","END_DATE_OVERRIDE",F4) -> 1111.5765 | G45: =_xll.BDP("PUSAPEBG Index","INTERVAL_AVG","CALC_INTERVAL=1Q","END_DATE_OVERRIDE",G4) -> 1146.4098 | H45: =_xll.BDP("PUSAPEBG Index","INTERVAL_AVG","CALC_INTERVAL=1Q","END_DATE_OVERRIDE",H4) -> 1139.061 | I45: =_xll.BDP("PUSAPEBG Index","INTERVAL_AVG","CALC_INTERVAL=1Q","END_DATE_OVERRIDE",I4) -> 1135.3866 | J45: =_xll.BDP("PUSAPEBG Index","INTERVAL_AVG","CALC_INTERVAL=1Q","END_DATE_OVERRIDE",J4) -> 1168.4561 | K45: =_xll.BDP("PUSAPEBG Index","INTERVAL_AVG","CALC_INTERVAL=1Q","END_DATE_OVERRIDE",K4) -> 1183.1537 | L45: =_xll.BDP("PUSAPEBG Index","INTERVAL_AVG","CALC_INTERVAL=1Q","END_DATE_OVERRIDE",L4) -> 1197.8512 | M45: =_xll.BDP("PUSAPEBG Index","INTERVAL_AVG","CALC_INTERVAL=1Q","END_DATE_OVERRIDE",M4) -> 1300.7341 | ... AT45: =_xll.BDP("PUSAPEBG Index","INTERVAL_AVG","CALC_INTERVAL=1Q","END_DATE_OVERRIDE",AT4) -> 1211.8 | AU45: =AT45*1.5 -> 1817.7 | AV45: =AU45 -> 1817.7 | AW45: =AV45 -> 1817.7 | AX45: =AVERAGE(F45:AW45) -> 1404.5418 | AY45: =AX45 -> 1404.5418 | AZ45: =AY45 -> 1404.5418 | BA45: =AZ45 -> 1404.5418 | BB45: =AX45*1.02 -> 1432.6327 | BC45: =AY45*1.02 -> 1432.6327 | BD45: =AZ45*1.02 -> 1432.6327 | BE45: =BA45*1.02 -> 1432.6327 | BF45: =BB45*1.02 -> 1461.2853 | BG45: =BC45*1.02 -> 1461.2853 | BH45: =BD45*1.02 -> 1461.2853 | BI45: =BE45*1.02 -> 1461.2853
E46: Markup --> | F46: =F45*1.5 -> 1667.3648 | G46: =G45*1.5 -> 1719.6146 | H46: =H45*1.5 -> 1708.5915 | I46: =I45*1.5 -> 1703.0799 | J46: =J45*1.5 -> 1752.6841 | K46: =K45*1.5 -> 1774.7305 | L46: =L45*1.5 -> 1796.7768 | M46: =M45*1.5 -> 1951.1012 | ... BI46: =BI45*1.5 -> 2191.928
B48: PET Resin Content per Case
D49: Standard Physical Case (fl oz) | E49: 192
D50: PET Resin g / oz | E50: 1.05
D51: PET Resin per all-bottle case (KG) | E51: =E49*E50/1000 -> 0.2016
B53: PET Resin Demand & Cost
D54: PET Resin Volume (mm KG) | J54: =J26*J24*$E$51 -> 7.229376 | K54: =K26*K24*$E$51 -> 9.81288 | L54: =L26*L24*$E$51 -> 9.624384 | M54: =M26*M24*$E$51 -> 9.236304 | N54: =N26*N24*$E$51 -> 8.491392 | O54: =O26*O24*$E$51 -> 9.8086464 | P54: =P26*P24*$E$51 -> 9.4385088 | Q54: =Q26*Q24*$E$51 -> 9.0248256 | ... BI54: =BI26*BI24*$E$51 -> 8.1008896
D55: PET Resin Spend ($M) | J55: =J54*J46/1000 -> 12.670813 | K55: =K54*K46/1000 -> 17.415217 | L55: =L54*L46/1000 -> 17.29287 | M55: =M54*M46/1000 -> 18.020964 | N55: =N54*N46/1000 -> 17.550387 | O55: =O54*O46/1000 -> 21.943438 | P55: =P54*P46/1000 -> 22.920517 | Q55: =Q54*Q46/1000 -> 23.527539 | ... BI55: =BI54*BI46/1000 -> 17.756567
D56: Y/Y Change in Spend ($M) | N56: =N55-J55 -> 4.8795742 | O56: =O55-K55 -> 4.5282205 | P56: =P55-L55 -> 5.6276472 | Q56: =Q55-M55 -> 5.5065747 | R56: =R55-N55 -> 2.4379737 | S56: =S55-O55 -> -0.68451909 | T56: =T55-P55 -> -3.7310142 | U56: =U55-Q55 -> -7.7607031 | ... BI56: =BI55-BE55 -> 0.11014649

Sheet Canalyst HC - Q
A1: Coca-Cola Consolidated
A2: COKE US | G2: Unrestated | H2: Unrestated | I2: Unrestated | J2: Unrestated | K2: Restated | L2: Restated | M2: Restated
A3: USD | C3: 91 | D3: 91 | E3: 91 | F3: 91 | G3: 91 | H3: 91 | I3: 91 | J3: 91 | K3: 91 | L3: 91 | M3: 91 | N3: 91 | O3: 91 | P3: 91 | Q3: 91 | R3: 91 | S3: 91 | T3: 91 | U3: 91 | V3: 95 | W3: 92 | X3: 91 | Y3: 91 | Z3: 91 | AA3: 91 | AB3: 92 | AC3: 90 | AD3: 92 | AE3: 90 | AF3: 91 | AG3: 91 | AH3: 93 | AI3: 89 | AJ3: 91 | AK3: 91 | AL3: 95 | AM3: 87 | AN3: 91 | AO3: 91 | AP3: 96
A4: Bloomberg | C4: 42463 | D4: 42554 | E4: 42645 | F4: 42736 | G4: 42827 | H4: 42918 | I4: 43009 | J4: 43100 | K4: 43191 | L4: 43282 | M4: 43373 | N4: 43464 | O4: 43555 | P4: 43646 | Q4: 43737 | R4: 43828 | S4: 43919 | T4: 44010 | U4: 44101 | V4: 44196 | W4: 44288 | X4: 44379 | Y4: 44470 | Z4: 44561 | AA4: 44652 | AB4: 44744 | AC4: 44834 | AD4: 44926 | AE4: 45016 | AF4: 45107 | AG4: 45198 | AH4: 45291 | AI4: 45380 | AJ4: 45471 | AK4: 45562 | AL4: 45657 | AM4: 45744 | AN4: 45835 | AO4: 45926 | AP4: 46022
A5: USD | C5: Q1-2016 | D5: Q2-2016 | E5: Q3-2016 | F5: Q4-2016 | G5: Q1-2017 | H5: Q2-2017 | I5: Q3-2017 | J5: Q4-2017 | K5: Q1-2018 | L5: Q2-2018 | M5: Q3-2018 | N5: Q4-2018 | O5: Q1-2019 | P5: Q2-2019 | Q5: Q3-2019 | R5: Q4-2019 | S5: Q1-2020 | T5: Q2-2020 | U5: Q3-2020 | V5: Q4-2020 | W5: Q1-2021 | X5: Q2-2021 | Y5: Q3-2021 | Z5: Q4-2021 | AA5: Q1-2022 | AB5: Q2-2022 | AC5: Q3-2022 | AD5: Q4-2022 | AE5: Q1-2023 | AF5: Q2-2023 | AG5: Q3-2023 | AH5: Q4-2023 | AI5: Q1-2024 | AJ5: Q2-2024 | AK5: Q3-2024 | AL5: Q4-2024 | AM5: Q1-2025 | AN5: Q2-2025 | AO5: Q3-2025 | AP5: Q4-2025
A6: Growth Analysis
A7: Sparkling beverages revenue growth, % | C7: 0.18417562 | D7: 0.17242971 | E7: 0.17474449 | F7: 0.16578354 | G7: 0.36036521 | H7: 0.30711248 | I7: 0.27857939 | J7: 0.25290414 | K7: 0.16746915 | L7: 0.048701251 | M7: 0.063487841 | N7: -0.060663365 | O7: 0.046184198 | P7: 0.053999043 | Q7: 0.060999992 | R7: 0.15425087 | S7: 0.077034266 | T7: 0.033557467 | U7: 0.07002511 | V7: 0.096840752 | W7: 0.099928222 | X7: 0.0871857 | Y7: 0.099410276 | Z7: 0.090891704 | AA7: 0.11726802 | AB7: 0.16596637 | AC7: 0.18574666 | AD7: 0.18779867 | AE7: 0.18692753 | AF7: 0.14149113 | AG7: 0.065965446 | AH7: 0.060727464 | AI7: 0.034142187 | AJ7: 0.044239664 | AK7: 0.058329915 | AL7: 0.076930723 | AM7: -0.019070538 | AN7: 0.029633683 | AO7: 0.046824653 | AP7: 0.064051684
A8: Still beverage revenue growth, % | C8: 1.3543662 | D8: 1.2102595 | E8: 1.1724986 | F8: 1.2839307 | G8: 0.54075456 | H8: 0.49755856 | I8: 0.47029919 | J8: 0.45128316 | K8: 0.25329808 | L8: 0.065211205 | M8: 0.042393269 | N8: 0.12735535 | O8: 0.070977854 | P8: 0.072350928 | Q8: 0.094100475 | R8: -0.0041343858 | S8: 0.086073408 | T8: -0.057907225 | U8: 0.060228957 | V8: 0.14406019 | W8: 0.12531679 | X8: 0.25675931 | Y8: 0.084033632 | Z8: 0.077874983 | AA8: 0.11397766 | AB8: 0.081362352 | AC8: 0.087983889 | AD8: 0.068414109 | AE8: 0.089104637 | AF8: 0.063107291 | AG8: 0.050372675 | AH8: 0.043794061 | AI8: 0.0039519022 | AJ8: 0.041566067 | AK8: 0.016621119 | AL8: 0.08739255 | AM8: -0.0048569117 | AN8: 0.047855595 | AO8: 0.098646177 | AP8: 0.099943535
A9: Total Bottle/Can Revenue Growth, % | C9: 0.40838801 | D9: 0.40017206 | E9: 0.41101299 | F9: 0.37231447 | G9: 0.41814362 | H9: 0.37308325 | I9: 0.34847948 | J9: 0.31388748 | K9: 0.19733684 | L9: 0.054938776 | M9: 0.055102072 | N9: 0.0031792221 | O9: 0.05521542 | P9: 0.060999971 | Q9: 0.074 | R9: 0.093813372 | S9: 0.080376005 | T9: -0.0017080271 | U9: 0.066105726 | V9: 0.11324552 | W9: 0.10936378 | X9: 0.14888651 | Y9: 0.093292083 | Z9: 0.086244318 | AA9: 0.11602759 | AB9: 0.13229207 | AC9: 0.14717737 | AD9: 0.14246011 | AE9: 0.15011697 | AF9: 0.11169589 | AG9: 0.060131218 | AH9: 0.047456996 | AI9: 0.023384306 | AJ9: 0.043267796 | AK9: 0.042867708 | AL9: 0.08326317 | AM9: -0.014101886 | AN9: 0.036246651 | AO9: 0.06555233 | AP9: 0.083687542
A10: Sales to other Coca-Cola bottlers revenue growth, % | C10: 0.32669238 | D10: 0.25710461 | E10: 0.25880561 | F10: 0.49157432 | G10: 0.28918542 | H10: 0.71951839 | I10: 0.78278207 | J10: 0.59351738 | K10: 0.57166692 | L10: 0.018843838 | M10: -0.11929 | N10: -0.20093243 | O10: -0.19719071 | P10: -0.16520487 | Q10: -0.096473806 | R10: 0.011093594 | S10: 0.04366192 | T10: -0.10499787 | U10: 0.019243243 | V10: -0.094262528 | W10: -0.042011286 | X10: 0.107504 | Y10: 0.056168387 | Z10: 0.098468189 | AA10: 0.032305469 | AB10: 0.064004339 | AC10: -0.066660715 | AD10: 0.0037064577 | AE10: 0.025493499 | AF10: -0.010100045 | AG10: 0.048610779 | AH10: -0.014611518 | AI10: -0.089559836 | AJ10: -0.0087332496 | AK10: 0.0074449892 | AL10: -0.0038169263 | AM10: 0.091902469 | AN10: 0.032253526 | AO10: 0.10478368 | AP10: 0.21596015
A11: Post-mix and other revenue growth, % | C11: 0.19970213 | D11: 0.17098205 | E11: 0.14450134 | F11: 0.12102257 | G11: 0.15549959 | H11: 0.28830257 | I11: 0.24098017 | J11: 0.33500055 | K11: 0.258572 | L11: -0.056048778 | M11: 0.0076293797 | N11: 0.34316021 | O11: 0.11670589 | P11: 0.10238207 | Q11: 0.0040265225 | R11: -0.40355817 | S11: -0.089329591 | T11: -0.38554547 | U11: -0.18090277 | V11: -0.11460723 | W11: -0.11304577 | X11: 0.62054399 | Y11: 0.20187063 | Z11: 0.29181454 | AA11: 0.034895354 | AB11: -0.10323475 | AC11: -0.12049593 | AD11: -0.077214996 | AE11: -0.28137697 | AF11: -0.17155017 | AG11: -0.10508496 | AH11: -0.10531854 | AI11: -0.10395041 | AJ11: -0.15330293 | AK11: -0.19731087 | AL11: -0.11376967 | AM11: 0.035667187 | AN11: -0.053837142 | AO11: 0.12610387 | AP11: 0.087090915
A12: Total Other Revenue Growth, % | C12: 0.25634679 | D12: 0.21016828 | E12: 0.19273346 | F12: 0.28590323 | G12: 0.21846974 | H12: 0.49211794 | I12: 0.48226482 | J12: 0.46842834 | K12: 0.41460842 | L12: -0.015255847 | M12: -0.060351933 | N12: 0.03841677 | O12: -0.057098539 | P12: -0.048415739 | Q12: -0.046427618 | R12: -0.22484488 | S12: -0.026632957 | T12: -0.24684774 | U12: -0.085696981 | V12: -0.10316983 | W12: -0.077139299 | X12: 0.31913564 | Y12: 0.12460785 | Z12: 0.18203935 | AA12: 0.033536389 | AB12: -0.020745431 | AC12: -0.093685573 | AD12: -0.034518974 | AE12: -0.12054762 | AF12: -0.085024276 | AG12: -0.026260929 | AH12: -0.055564586 | AI12: -0.095155954 | AJ12: -0.069479263 | AK12: -0.084225904 | AL12: -0.05084398 | AM12: 0.070246578 | AN12: -0.00066183549 | AO12: 0.1131502 | AP12: 0.16449658
A13: Total Revenue Growth, % | C13: 0.37992688 | D13: 0.36718276 | E13: 0.37204229 | F13: 0.35797688 | G13: 0.38411335 | H13: 0.39137704 | I13: 0.36924342 | J13: 0.3381684 | K13: 0.22993478 | L13: 0.043369871 | M13: 0.035704148 | N13: 0.009254548 | O13: 0.035834467 | P13: 0.04398022 | Q13: 0.055642993 | R13: 0.037285836 | S13: 0.063567175 | T13: -0.036465019 | U13: 0.045203532 | V13: 0.084556669 | W13: 0.082552657 | X13: 0.16775463 | Y13: 0.097064022 | Z13: 0.096745206 | AA13: 0.10591823 | AB13: 0.11313278 | AC13: 0.11743738 | AD13: 0.12155121 | AE13: 0.11911777 | AF13: 0.090029871 | AG13: 0.051479532 | AH13: 0.03697939 | AI13: 0.012715364 | AJ13: 0.032844461 | AK13: 0.031081015 | AL13: 0.070841273 | AM13: -0.0073189305 | AN13: 0.033172545 | AO13: 0.06947292 | AP13: 0.090322045
A15: Comparable Net Sales, % | D15: 0.045 | E15: 0.041 | F15: 0.063 | G15: 0.018 | H15: 0.028 | I15: 0.014 | J15: 0.067 | V15: 0.035 | Z15: 0.15
A16: Organic Net Sales Growth, % | K16: 0.024 | L16: 0.026 | M16: 0.043 | N16: 0.029
A18: Segmented Results - Revenue Breakdown (FS)
A19: Sparkling beverages revenue, mm | C19: 352.67 | D19: 464.859 | E19: 455.748 | F19: 491.281 | G19: 479.76 | H19: 607.623 | I19: 582.71 | J19: 615.528 | K19: 560.105 | L19: 637.215 | M19: 619.705 | N19: 578.188 | O19: 585.973 | P19: 671.624 | Q19: 657.507 | R19: 667.374 | S19: 631.113 | T19: 694.162 | U19: 703.549 | V19: 732.003 | W19: 694.179 | X19: 754.683 | Y19: 773.489 | Z19: 798.536 | AA19: 775.584 | AB19: 879.935 | AC19: 917.162 | AD19: 948.5 | AE19: 920.562 | AF19: 1004.438 | AG19: 977.663 | AH19: 1006.1 | AI19: 951.992 | AJ19: 1048.874 | AK19: 1034.69 | AL19: 1083.5 | AM19: 933.837 | AN19: 1079.956 | AO19: 1083.139 | AP19: 1152.9
A20: Still beverage revenue, mm | C20: 166.19 | D20: 246.371 | E20: 261.508 | F20: 218.056 | G20: 256.058 | H20: 368.955 | I20: 384.495 | J20: 316.461 | K20: 320.917 | L20: 393.015 | M20: 400.795 | N20: 356.764 | O20: 343.695 | P20: 421.45 | Q20: 438.51 | R20: 355.289 | S20: 373.278 | T20: 397.045 | U20: 464.921 | V20: 406.472 | W20: 420.056 | X20: 498.99 | Y20: 503.99 | Z20: 438.126 | AA20: 467.933 | AB20: 539.589 | AC20: 548.333 | AD20: 468.1 | AE20: 509.628 | AF20: 573.641 | AG20: 575.954 | AH20: 488.6 | AI20: 511.642 | AJ20: 597.485 | AK20: 585.527 | AL20: 531.3 | AM20: 509.157 | AN20: 626.078 | AO20: 643.287 | AP20: 584.4
A21: Total Bottle/Can Sales, mm | C21: 518.86 | D21: 711.23 | E21: 717.256 | F21: 709.337 | G21: 735.818 | H21: 976.578 | I21: 967.205 | J21: 931.989 | K21: 881.022 | L21: 1030.23 | M21: 1020.5 | N21: 934.952 | O21: 929.668 | P21: 1093.074 | Q21: 1096.017 | R21: 1022.663 | S21: 1004.391 | T21: 1091.207 | U21: 1168.47 | V21: 1138.475 | W21: 1114.235 | X21: 1253.673 | Y21: 1277.479 | Z21: 1236.662 | AA21: 1243.517 | AB21: 1419.524 | AC21: 1465.495 | AD21: 1412.837 | AE21: 1430.19 | AF21: 1578.079 | AG21: 1553.617 | AH21: 1479.886 | AI21: 1463.634 | AJ21: 1646.359 | AK21: 1620.217 | AL21: 1603.106 | AM21: 1442.994 | AN21: 1706.034 | AO21: 1726.426 | AP21: 1737.266
A22: Sales to other Coca-Cola bottlers revenue, mm | C22: 50.21 | D22: 61.045 | E22: 58.683 | F22: 68.244 | G22: 64.73 | H22: 104.968 | I22: 104.619 | J22: 108.748 | K22: 101.734 | L22: 106.946 | M22: 92.139 | N22: 86.897 | O22: 81.673 | P22: 89.278 | Q22: 83.25 | R22: 87.861 | S22: 85.239 | T22: 79.904 | U22: 84.852 | V22: 79.579 | W22: 81.658 | X22: 88.494 | Y22: 89.618 | Z22: 87.415 | AA22: 84.296 | AB22: 94.158 | AC22: 83.644 | AD22: 87.739 | AE22: 86.445 | AF22: 93.207 | AG22: 87.71 | AH22: 86.457 | AI22: 78.703 | AJ22: 92.393 | AK22: 88.363 | AL22: 86.127 | AM22: 85.936 | AN22: 95.373 | AO22: 97.622 | AP22: 104.727
A23: Post-mix and other revenue, mm | C23: 56.386 | D23: 68.109 | E23: 73.089 | F23: 63.979 | G23: 65.154 | H23: 87.745 | I23: 90.702 | J23: 85.412 | K23: 82.001 | L23: 82.827 | M23: 91.394 | N23: 114.722 | O23: 91.571 | P23: 91.307 | Q23: 91.762 | R23: 68.425 | S23: 83.391 | T23: 56.104 | U23: 75.162 | V23: 60.583 | W23: 73.964 | X23: 90.919 | Y23: 90.335 | Z23: 78.262 | AA23: 76.545 | AB23: 81.533 | AC23: 79.45 | AD23: 72.219 | AE23: 55.007 | AF23: 67.546 | AG23: 71.101 | AH23: 64.613 | AI23: 49.289 | AJ23: 57.191 | AK23: 57.072 | AL23: 57.262 | AM23: 51.047 | AN23: 54.112 | AO23: 64.269 | AP23: 62.249
A24: Total Other Sales, mm | C24: 106.596 | D24: 129.154 | E24: 131.772 | F24: 132.223 | G24: 129.884 | H24: 192.713 | I24: 195.321 | J24: 194.16 | K24: 183.735 | L24: 189.773 | M24: 183.533 | N24: 201.619 | O24: 173.244 | P24: 180.585 | Q24: 175.012 | R24: 156.286 | S24: 168.63 | T24: 136.008 | U24: 160.014 | V24: 140.162 | W24: 155.622 | X24: 179.413 | Y24: 179.953 | Z24: 165.677 | AA24: 160.841 | AB24: 175.691 | AC24: 163.094 | AD24: 159.958 | AE24: 141.452 | AF24: 160.753 | AG24: 158.811 | AH24: 151.07 | AI24: 127.992 | AJ24: 149.584 | AK24: 145.435 | AL24: 143.389 | AM24: 136.983 | AN24: 149.485 | AO24: 161.891 | AP24: 166.976
A25: Total Net Sales, mm | C25: 625.456 | D25: 840.384 | E25: 849.028 | F25: 841.56 | G25: 865.702 | H25: 1169.291 | I25: 1162.526 | J25: 1126.149 | K25: 1064.757 | L25: 1220.003 | M25: 1204.033 | N25: 1136.571 | O25: 1102.912 | P25: 1273.659 | Q25: 1271.029 | R25: 1178.949 | S25: 1173.021 | T25: 1227.215 | U25: 1328.484 | V25: 1278.637 | W25: 1269.857 | X25: 1433.086 | Y25: 1457.432 | Z25: 1402.339 | AA25: 1404.358 | AB25: 1595.215 | AC25: 1628.589 | AD25: 1572.795 | AE25: 1571.642 | AF25: 1738.832 | AG25: 1712.428 | AH25: 1630.956 | AI25: 1591.626 | AJ25: 1795.943 | AK25: 1765.652 | AL25: 1746.495 | AM25: 1579.977 | AN25: 1855.519 | AO25: 1888.317 | AP25: 1904.242
A27: Fountain sales, mm | O27: 42.8 | P27: 51.8 | Q27: 55.5 | R27: 46.9 | S27: 40.8 | T27: 22.5 | U27: 36 | V27: 32.5 | W27: 32.6 | X27: 43.3 | Y27: 45.3
A29: Sparkling beverages revenue as of total, % | C29: 0.56386061 | D29: 0.5531507 | E29: 0.53678795 | F29: 0.58377418 | G29: 0.55418608 | H29: 0.5196508 | I29: 0.5012447 | J29: 0.54657776 | K29: 0.52604021 | L29: 0.52230609 | M29: 0.51469104 | N29: 0.50871261 | O29: 0.53129624 | P29: 0.52731854 | Q29: 0.51730291 | R29: 0.56607538 | S29: 0.53802362 | T29: 0.56564009 | U29: 0.52958786 | V29: 0.57248695 | W29: 0.54665919 | X29: 0.52661389 | Y29: 0.53072047 | Z29: 0.5694315 | AA29: 0.55226944 | AB29: 0.55160903 | AC29: 0.56316357 | AD29: 0.60306652 | AE29: 0.58573263 | AF29: 0.57765097 | AG29: 0.57092211 | AH29: 0.61687746 | AI29: 0.59812544 | AJ29: 0.5840241 | AK29: 0.58601015 | AL29: 0.6203854 | AM29: 0.59104468 | AN29: 0.58202368 | AO29: 0.5736002 | AP29: 0.60543775
A30: Still beverage revenue as of total, % | C30: 0.26571014 | D30: 0.29316479 | E30: 0.30800869 | F30: 0.25910927 | G30: 0.29578077 | H30: 0.31553736 | I30: 0.33074099 | J30: 0.28101166 | K30: 0.30139929 | L30: 0.32214265 | M30: 0.33287709 | N30: 0.31389504 | O30: 0.31162504 | P30: 0.33089705 | Q30: 0.34500393 | R30: 0.30136079 | S30: 0.31821937 | T30: 0.32353337 | U30: 0.34996357 | V30: 0.31789476 | W30: 0.33079 | X30: 0.34819264 | Y30: 0.34580687 | Z30: 0.31242517 | AA30: 0.33320065 | AB30: 0.33825472 | AC30: 0.33669207 | AD30: 0.29762302 | AE30: 0.32426469 | AF30: 0.32990019 | AG30: 0.33633764 | AH30: 0.2995789 | AI30: 0.32145868 | AJ30: 0.33268595 | AK30: 0.33162084 | AL30: 0.30420929 | AM30: 0.32225596 | AN30: 0.33741395 | AO30: 0.34066685 | AP30: 0.30689377
A31: Total Bottle/Can Sales as of Total, % | C31: 0.82957075 | D31: 0.84631549 | E31: 0.84479664 | F31: 0.84288345 | G31: 0.84996685 | H31: 0.83518816 | I31: 0.83198569 | J31: 0.82758942 | K31: 0.8274395 | L31: 0.84444874 | M31: 0.84756813 | N31: 0.82260765 | O31: 0.84292128 | P31: 0.85821558 | Q31: 0.86230684 | R31: 0.86743617 | S31: 0.85624298 | T31: 0.88917345 | U31: 0.87955143 | V31: 0.89038171 | W31: 0.87744919 | X31: 0.87480654 | Y31: 0.87652734 | Z31: 0.88185667 | AA31: 0.88547009 | AB31: 0.88986375 | AC31: 0.89985564 | AD31: 0.90068954 | AE31: 0.90999731 | AF31: 0.90755116 | AG31: 0.90725975 | AH31: 0.91645636 | AI31: 0.91958412 | AJ31: 0.91671005 | AK31: 0.91763099 | AL31: 0.92459469 | AM31: 0.91330064 | AN31: 0.91943763 | AO31: 0.91426704 | AP31: 0.91233152
A32: Sales to other Coca-Cola bottlers revenue as of total, % | C32: 0.08027743 | D32: 0.072639412 | E32: 0.069117862 | F32: 0.081092257 | G32: 0.074771688 | H32: 0.089770639 | I32: 0.089992826 | J32: 0.096566263 | K32: 0.095546683 | L32: 0.08766044 | M32: 0.076525311 | N32: 0.076455408 | O32: 0.074052146 | P32: 0.070095685 | Q32: 0.065498112 | R32: 0.074524852 | S32: 0.072666218 | T32: 0.065110026 | U32: 0.0638713 | V32: 0.062237367 | W32: 0.064304878 | X32: 0.061750656 | Y32: 0.061490347 | Z32: 0.062335142 | AA32: 0.060024581 | AB32: 0.059025272 | AC32: 0.051359797 | AD32: 0.055785401 | AE32: 0.055002984 | AF32: 0.053603223 | AG32: 0.051219672 | AH32: 0.053010014 | AI32: 0.049448174 | AJ32: 0.051445397 | AK32: 0.050045536 | AL32: 0.049314198 | AM32: 0.054390665 | AN32: 0.051399635 | AO32: 0.051697888 | AP32: 0.054996686
A33: Post-mix and other revenue as of total, % | C33: 0.090151825 | D33: 0.081045094 | E33: 0.0860855 | F33: 0.076024288 | G33: 0.075261464 | H33: 0.0750412 | I33: 0.078021481 | J33: 0.075844315 | K33: 0.077013816 | L33: 0.067890817 | M33: 0.075906557 | N33: 0.10093694 | O33: 0.08302657 | P33: 0.071688733 | Q33: 0.072195048 | R33: 0.058038982 | S33: 0.071090799 | T33: 0.045716521 | U33: 0.056577272 | V33: 0.047380922 | W33: 0.058245928 | X33: 0.063442808 | Y33: 0.061982309 | Z33: 0.055808189 | AA33: 0.054505333 | AB33: 0.051110979 | AC33: 0.048784561 | AD33: 0.045917618 | AE33: 0.034999701 | AF33: 0.038845616 | AG33: 0.041520578 | AH33: 0.039616642 | AI33: 0.030967702 | AJ33: 0.031844552 | AK33: 0.03232347 | AL33: 0.03278681 | AM33: 0.032308698 | AN33: 0.02916273 | AO33: 0.034035069 | AP33: 0.032689648
A34: Total Other Sales as of Total, % | C34: 0.17042925 | D34: 0.15368451 | E34: 0.15520336 | F34: 0.15711655 | G34: 0.15003315 | H34: 0.16481184 | I34: 0.16801431 | J34: 0.17241058 | K34: 0.1725605 | L34: 0.15555126 | M34: 0.15243187 | N34: 0.17739235 | O34: 0.15707872 | P34: 0.14178442 | Q34: 0.13769316 | R34: 0.13256383 | S34: 0.14375702 | T34: 0.11082655 | U34: 0.12044857 | V34: 0.10961829 | W34: 0.12255081 | X34: 0.12519346 | Y34: 0.12347266 | Z34: 0.11814333 | AA34: 0.11452991 | AB34: 0.11013625 | AC34: 0.10014436 | AD34: 0.10170302 | AE34: 0.090002685 | AF34: 0.092448839 | AG34: 0.09274025 | AH34: 0.092626656 | AI34: 0.080415877 | AJ34: 0.083289949 | AK34: 0.082369006 | AL34: 0.082101008 | AM34: 0.086699363 | AN34: 0.080562366 | AO34: 0.085732957 | AP34: 0.087686334
A35: Total Net Sales as of Total, % | C35: 1 | D35: 1 | E35: 1 | F35: 1 | G35: 1 | H35: 1 | I35: 1 | J35: 1 | K35: 1 | L35: 1 | M35: 1 | N35: 1 | O35: 1 | P35: 1 | Q35: 1 | R35: 1 | S35: 1 | T35: 1 | U35: 1 | V35: 1 | W35: 1 | X35: 1 | Y35: 1 | Z35: 1 | AA35: 1 | AB35: 1 | AC35: 1 | AD35: 1.0023926 | AE35: 1 | AF35: 1 | AG35: 1 | AH35: 1.009083 | AI35: 1 | AJ35: 1 | AK35: 1 | AL35: 1.0066957 | AM35: 1 | AN35: 1 | AO35: 1 | AP35: 1.0000179
A37: Operating Stats - Bottle/Can Volume Price Analysis (PR/10Q) | AA37: Restated | AB37: Restated | AC37: Restated | AD37: Restated
A38: Sparkling category volume growth, % | K38: 0.20637212 | L38: 0.054064219 | M38: 0.040274799 | N38: 0.037033227 | O38: 0.0095263533 | P38: -0.0027044394 | Q38: 0.043441427 | R38: -0.032563222 | S38: 0.035029544 | T38: 0.038357422 | U38: 0.035563012 | V38: 0.0664055 | W38: 0.041064399 | X38: -0.00060983047 | Y38: -0.0063761955 | Z38: -0.019069843 | AA38: NMF | AB38: NMF | AC38: NMF | AD38: NMF | AE38: -0.0086977609 | AF38: -0.020936671 | AG38: 0.0017691354 | AH38: 0.014986497 | AI38: 0.0076324673 | AJ38: -0.0035051546 | AK38: 0.0079998792 | AL38: 0.030027484 | AM38: -0.051080359 | AN38: -0.0025863853 | AO38: 0.013686528 | AP38: 0.035198274
A39: Still beverages volume growth, % | K39: 0.17122142 | L39: -0.058038967 | M39: -0.078426842 | N39: -0.12095549 | O39: -0.015338828 | P39: 0.021349268 | Q39: 0.048227987 | R39: 0.1582335 | S39: 0.13085329 | T39: -0.066700816 | U39: 0.0450625 | V39: 0.1166588 | W39: 0.061281303 | X39: 0.20934609 | Y39: -0.0063761955 | Z39: -0.0045658095 | AA39: NMF | AB39: NMF | AC39: NMF | AD39: NMF | AE39: -0.089057319 | AF39: -0.088741869 | AG39: -0.054097086 | AH39: -0.0015367837 | AI39: -0.039096109 | AJ39: -0.035043602 | AK39: -0.096610037 | AL39: -0.04562832 | AM39: -0.1096133 | AN39: -0.024042705 | AO39: 0.0885692 | AP39: 0.085214858
A40: Physical Case Volume Growth, % | K40: 0.19631902 | L40: 0.018079096 | M40: -0.0011520737 | N40: -0.0048019208 | O40: 0.0025641026 | P40: 0.0044395117 | Q40: 0.044982699 | R40: 0.012062726 | S40: 0.061381074 | T40: 0.0066298343 | U40: 0.038631347 | V40: 0.079856973 | W40: 0.046987952 | X40: 0.058177827 | Y40: -0.0063761955 | Z40: -0.015055188 | AA40: NMF | AB40: NMF | AC40: NMF | AD40: NMF | AE40: -0.030631435 | AF40: -0.039965563 | AG40: -0.014429736 | AH40: 0.011180138 | AI40: -0.0043530981 | AJ40: -0.011906434 | AK40: -0.021111801 | AL40: 0.012818341 | AM40: -0.065569777 | AN40: -0.0081681301 | AO40: 0.032918239 | AP40: 0.045918822
A42: Sparkling beverages case volume, mm | G42: 46.5528 | H42: 60.0915 | I42: 56.5068 | J42: 61.2423 | K42: 56.16 | L42: 63.3403 | M42: 58.7826 | N42: 63.5103 | O42: 56.695 | P42: 63.169 | Q42: 61.3362 | R42: 61.4422 | S42: 58.681 | T42: 65.592 | U42: 63.5175 | V42: 65.5223 | W42: 61.0907 | X42: 65.552 | Y42: 63.1125 | Z42: 64.2728 | AA42: 61.855 | AB42: 69.352 | AC42: 66.134 | AD42: 67.394 | AE42: 61.317 | AF42: 67.9 | AG42: 66.251 | AH42: 68.404 | AI42: 61.785 | AJ42: 67.662 | AK42: 66.781 | AL42: 70.458 | AM42: 58.629 | AN42: 67.487 | AO42: 67.695 | AP42: 72.938
A43: Still beverages case volume, mm | G43: 18.6472 | H43: 28.4085 | I43: 30.2932 | J43: 22.0577 | K43: 21.84 | L43: 26.7597 | M43: 27.9174 | N43: 19.3897 | O43: 21.505 | P43: 27.331 | Q43: 29.2638 | R43: 22.4578 | S43: 24.319 | T43: 25.508 | U43: 30.5825 | V43: 25.0777 | W43: 25.8093 | X43: 30.848 | Y43: 30.3875 | Z43: 24.9632 | AA43: 23.221 | AB43: 27.056 | AC43: 27.007 | AD43: 20.172 | AE43: 21.153 | AF43: 24.655 | AG43: 25.546 | AH43: 20.141 | AI43: 20.326 | AJ43: 23.791 | AK43: 23.078 | AL43: 19.222 | AM43: 18.098 | AN43: 23.219 | AO43: 25.122 | AP43: 20.86
A44: Physical Case Volume, mm | G44: 65.2 | H44: 88.5 | I44: 86.8 | J44: 83.3 | K44: 78 | L44: 90.1 | M44: 86.7 | N44: 82.9 | O44: 78.2 | P44: 90.5 | Q44: 90.6 | R44: 83.9 | S44: 83 | T44: 91.1 | U44: 94.1 | V44: 90.6 | W44: 86.9 | X44: 96.4 | Y44: 93.5 | Z44: 89.236 | AA44: 85.076 | AB44: 96.408 | AC44: 93.141 | AD44: 87.566 | AE44: 82.47 | AF44: 92.555 | AG44: 91.797 | AH44: 88.545 | AI44: 82.111 | AJ44: 91.453 | AK44: 89.859 | AL44: 89.68 | AM44: 76.727 | AN44: 90.706 | AO44: 92.817 | AP44: 93.798
A45: Acquisition/divestiture related physical case volume, mm | K45: 12.2 | L45: 25.9 | M45: 10.6 | N45: 0
A46: Volume related to extra days in fiscal year, mm | V46: 4.6
A47: Comparable Physical Case Volume, mm | G47: 65.2 | H47: 88.5 | I47: 86.8 | J47: 83.3 | K47: 65.8 | L47: 64.2 | M47: 76.1 | N47: 82.9 | O47: 78.2 | P47: 90.5 | Q47: 90.6 | R47: 83.9 | S47: 83 | T47: 91.1 | U47: 94.1 | V47: 86 | W47: 86.9 | X47: 96.4 | Y47: 93.5 | Z47: 89.236 | AA47: 85.076 | AB47: 96.408 | AC47: 93.141 | AD47: 87.566 | AE47: 82.47 | AF47: 92.555 | AG47: 91.797 | AH47: 88.545 | AI47: 82.111 | AJ47: 91.453 | AK47: 89.859 | AL47: 89.68 | AM47: 76.727 | AN47: 90.706 | AO47: 92.817 | AP47: 93.798
A49: Sparkling beverages as % of total case volume, % | C49: 0.729 | D49: 0.697 | E49: 0.674 | G49: 0.714 | H49: 0.679 | I49: 0.651 | J49: 0.73520168 | K49: 0.72 | L49: 0.703 | M49: 0.678 | N49: 0.76610736 | O49: 0.725 | P49: 0.698 | Q49: 0.677 | R49: 0.73232658 | S49: 0.707 | T49: 0.72 | U49: 0.675 | V49: 0.72320419 | W49: 0.703 | X49: 0.68 | Y49: 0.675 | Z49: 0.7202564 | AA49: 0.72705581 | AB49: 0.71935939 | AC49: 0.71004176 | AD49: 0.76963662 | AE49: 0.74350673 | AF49: 0.73361785 | AG49: 0.72171204 | AH49: 0.77253374 | AI49: 0.75245704 | AJ49: 0.73985544 | AK49: 0.74317542 | AL49: 0.78566012 | AM49: 0.76412475 | AN49: 0.74401914 | AO49: 0.72933838 | AP49: 0.7776072
A50: Still beverages as % of total case volume, % | C50: 0.271 | D50: 0.303 | E50: 0.326 | G50: 0.286 | H50: 0.321 | I50: 0.349 | J50: 0.26479832 | K50: 0.28 | L50: 0.297 | M50: 0.322 | N50: 0.23389264 | O50: 0.275 | P50: 0.302 | Q50: 0.323 | R50: 0.26767342 | S50: 0.293 | T50: 0.28 | U50: 0.325 | V50: 0.27679581 | W50: 0.297 | X50: 0.32 | Y50: 0.325 | Z50: 0.2797436 | AA50: 0.27294419 | AB50: 0.28064061 | AC50: 0.28995824 | AD50: 0.23036338 | AE50: 0.25649327 | AF50: 0.26638215 | AG50: 0.27828796 | AH50: 0.22746626 | AI50: 0.24754296 | AJ50: 0.26014456 | AK50: 0.25682458 | AL50: 0.21433988 | AM50: 0.23587525 | AN50: 0.25598086 | AO50: 0.27066162 | AP50: 0.2223928
A51: Total Case Volume, % | C51: 1 | D51: 1 | E51: 1 | G51: 1 | H51: 1 | I51: 1 | J51: 1 | K51: 1 | L51: 1 | M51: 1 | N51: 1 | O51: 1 | P51: 1 | Q51: 1 | R51: 1 | S51: 1 | T51: 1 | U51: 1 | V51: 1 | W51: 1 | X51: 1 | Y51: 1 | Z51: 1 | AA51: 1 | AB51: 1 | AC51: 1 | AD51: 1 | AE51: 1 | AF51: 1 | AG51: 1 | AH51: 1 | AI51: 1 | AJ51: 1 | AK51: 1 | AL51: 1 | AM51: 1 | AN51: 1 | AO51: 1 | AP51: 1
A53: Sparkling category average sales per case growth, % | K53: -0.032247901 | L53: -0.0050878951 | M53: 0.022314337 | N53: -0.094207775 | O53: 0.036311924 | P53: 0.056857249 | Q53: 0.016827553 | R53: 0.19310212 | S53: 0.040583114 | T53: -0.0046226428 | U53: 0.033278611 | V53: 0.028540037 | W53: 0.056541961 | X53: 0.087849104 | Y53: 0.10646531 | Z53: 0.11209926 | AA53: NMF | AB53: NMF | AC53: NMF | AD53: NMF | AE53: 0.19734172 | AF53: 0.16590122 | AG53: 0.064082939 | AH53: 0.045065592 | AI53: 0.026308918 | AJ53: 0.047912761 | AK53: 0.049930597 | AL53: 0.04553591 | AM53: 0.03373291 | AN53: 0.032303618 | AO53: 0.032690703 | AP53: 0.027872352
A54: Still beverages average sales per case growth, % | K54: 0.070077838 | L54: 0.13084424 | M54: 0.13110203 | N54: 0.28247812 | O54: 0.087661304 | P54: 0.049935572 | Q54: 0.043761938 | R54: -0.14018579 | S54: -0.039598312 | T54: 0.0094220492 | U54: 0.014512488 | V54: 0.024538729 | W54: 0.0603379 | X54: 0.039205669 | Y54: 0.090989997 | Z54: 0.082818928 | AA54: NMF | AB54: NMF | AC54: NMF | AD54: NMF | AE54: 0.19557977 | AF54: 0.16663682 | AG54: 0.11044449 | AH54: 0.045400616 | AI54: 0.044799498 | AJ54: 0.079391844 | AK54: 0.12534029 | AL54: 0.13938057 | AM54: 0.11765269 | AN54: 0.073669514 | AO54: 0.0092570842 | AP54: 0.01357213
A55: Total Bottle/can Average Sales per Case Growth, % | K55: 0.00085079567 | L55: 0.036205124 | M55: 0.05631903 | N55: 0.0080196526 | O55: 0.05251666 | P55: 0.056310468 | Q55: 0.027768212 | R55: 0.080776264 | S55: 0.017896429 | T55: -0.0082829468 | U55: 0.026452485 | V55: 0.030919414 | W55: 0.059576456 | X55: 0.085721586 | Y55: 0.10030786 | Z55: 0.1028479 | AA55: NMF | AB55: NMF | AC55: NMF | AD55: NMF | AE55: 0.18645994 | AF55: 0.15797502 | AG55: 0.075652601 | AH55: 0.035875762 | AI55: 0.027858675 | AJ55: 0.055839074 | AK55: 0.065359363 | AL55: 0.069553272 | AM55: 0.055079438 | AN55: 0.044780554 | AO55: 0.031594071 | AP55: 0.036110564
A57: Sparkling beverages average sales per case, $/case | G57: 10.305717 | H57: 10.11163 | I57: 10.31221 | J57: 10.0507 | K57: 9.9733796 | L57: 10.060183 | M57: 10.54232 | N57: 9.1038461 | O57: 10.335532 | P57: 10.632177 | Q57: 10.719722 | R57: 10.861818 | S57: 10.75498 | T57: 10.583028 | U57: 11.076459 | V57: 11.171815 | W57: 11.363088 | X57: 11.512738 | Y57: 12.255718 | Z57: 12.424167 | AA57: 12.538744 | AB57: 12.687954 | AC57: 13.868237 | AD57: 14.073953 | AE57: 15.013161 | AF57: 14.792901 | AG57: 14.756955 | AH57: 14.708204 | AI57: 15.408141 | AJ57: 15.50167 | AK57: 15.493778 | AL57: 15.377956 | AM57: 15.927903 | AN57: 16.00243 | AO57: 16.000281 | AP57: 15.806575
A58: Still beverages average sales per case, $/case | G58: 13.731713 | H58: 12.987486 | I58: 12.692452 | J58: 14.346963 | K58: 14.694002 | L58: 14.686824 | M58: 14.356459 | N58: 18.399666 | O58: 15.982097 | P58: 15.420219 | Q58: 14.984725 | R58: 15.820294 | S58: 15.349233 | T58: 15.565509 | U58: 15.202191 | V58: 16.208504 | W58: 16.275374 | X58: 16.175765 | Y58: 16.585438 | Z58: 17.550875 | AA58: 20.151285 | AB58: 19.943414 | AC58: 20.303366 | AD58: 23.205433 | AE58: 24.092469 | AF58: 23.266721 | AG58: 22.545761 | AH58: 24.258974 | AI58: 25.1718 | AJ58: 25.113909 | AK58: 25.371653 | AL58: 27.640204 | AM58: 28.13333 | AN58: 26.964038 | AO58: 25.60652 | AP58: 28.01534
A59: Average Sales per Case, $/case | G59: 11.285552 | H59: 11.03478 | I59: 11.142915 | J59: 11.188343 | K59: 11.295154 | L59: 11.434295 | M59: 11.770473 | N59: 11.27807 | O59: 11.888338 | P59: 12.078166 | Q59: 12.097318 | R59: 12.18907 | S59: 12.101096 | T59: 11.978123 | U59: 12.417322 | V59: 12.565949 | W59: 12.822037 | X59: 13.004907 | Y59: 13.662877 | Z59: 13.858331 | AA59: 14.616543 | AB59: 14.724131 | AC59: 15.734156 | AD59: 16.134539 | AE59: 17.341943 | AF59: 17.050176 | AG59: 16.924486 | AH59: 16.713377 | AI59: 17.825066 | AJ59: 18.002242 | AK59: 18.030659 | AL59: 17.875847 | AM59: 18.806861 | AN59: 18.808392 | AO59: 18.600321 | AP59: 18.521354
A61: Segmented Results - Alternative Results Breakdown (FS)
A62: Nonalcoholic Beverages - point in time revenue, mm | K62: 1031.808 | L62: 1183.083 | M62: 1160.648 | N62: 1092.406 | O62: 1060.271 | P62: 1227.977 | Q62: 1224.653 | R62: 1136.136 | S62: 1132.475 | T62: 1188.485 | U62: 1286.542 | V62: 1235.432 | W62: 1225.212 | X62: 1388.991 | Y62: 1415.643 | Z62: 1359.598 | AA62: 1362.251 | AB62: 1550.255 | AC62: 1587.771 | AD62: 1534.637 | AE62: 1533.288 | AF62: 1701.49 | AG62: 1677.221 | AH62: 1598.156 | AI62: 1561.145 | AJ62: 1766.391 | AK62: 1736.286 | AL62: 1717.922 | AM62: 1555.765 | AN62: 1831.13 | AO62: 1861.794 | AP62: 1877.615
A63: Nonalcoholic Beverages - over time revenue, mm | K63: 8.614 | L63: 9.199 | M63: 11.936 | N63: 14.624 | O63: 11.956 | P63: 10.908 | Q63: 11.608 | R63: 10.919 | S63: 10.106 | T63: 7.039 | U63: 8.729 | V63: 10.362 | W63: 9.878 | X63: 10.924 | Y63: 11.328 | Z63: 11.095 | AA63: 10.97 | AB63: 11.759 | AC63: 12.294 | AD63: 11.42 | AE63: 12.124 | AF63: 13.372 | AG63: 13.839 | AH63: 13.132 | AI63: 13.567 | AJ63: 13.761 | AK63: 15.209 | AL63: 14.764 | AM63: 13.235 | AN63: 13.931 | AO63: 15.205 | AP63: 15.107
A64: All Other - over time revenue, mm | K64: 24.335 | L64: 27.721 | M64: 31.449 | N64: 29.541 | O64: 30.685 | P64: 34.774 | Q64: 34.768 | R64: 31.894 | S64: 30.44 | T64: 31.691 | U64: 33.213 | V64: 32.843 | W64: 34.767 | X64: 33.171 | Y64: 30.461 | Z64: 31.646 | AA64: 31.137 | AB64: 33.201 | AC64: 28.524 | AD64: 26.738 | AE64: 26.23 | AF64: 23.97 | AG64: 21.368 | AH64: 19.668 | AI64: 16.914 | AJ64: 15.791 | AK64: 14.157 | AL64: 13.809 | AM64: 10.977 | AN64: 10.458 | AO64: 11.318 | AP64: 11.52
A65: Total over time net sales, mm | K65: 32.949 | L65: 36.92 | M65: 43.385 | N65: 44.165 | O65: 42.641 | P65: 45.682 | Q65: 46.376 | R65: 42.813 | S65: 40.546 | T65: 38.73 | U65: 41.942 | V65: 43.205 | W65: 44.645 | X65: 44.095 | Y65: 41.789 | Z65: 42.741 | AA65: 42.107 | AB65: 44.96 | AC65: 40.818 | AD65: 38.158 | AE65: 38.354 | AF65: 37.342 | AG65: 35.207 | AH65: 32.8 | AI65: 30.481 | AJ65: 29.552 | AK65: 29.366 | AL65: 28.573 | AM65: 24.212 | AN65: 24.389 | AO65: 26.523 | AP65: 26.627
A66: Total Net Sales by Contracts with Customers, mm | K66: 1064.757 | L66: 1220.003 | M66: 1204.033 | N66: 1136.571 | O66: 1102.912 | P66: 1273.659 | Q66: 1271.029 | R66: 1178.949 | S66: 1173.021 | T66: 1227.215 | U66: 1328.484 | V66: 1278.637 | W66: 1269.857 | X66: 1433.086 | Y66: 1457.432 | Z66: 1402.339 | AA66: 1404.358 | AB66: 1595.215 | AC66: 1628.589 | AD66: 1572.795 | AE66: 1571.642 | AF66: 1738.832 | AG66: 1712.428 | AH66: 1630.956 | AI66: 1591.626 | AJ66: 1795.943 | AK66: 1765.652 | AL66: 1746.495 | AM66: 1579.977 | AN66: 1855.519 | AO66: 1888.317 | AP66: 1904.242
A68: Nonalcoholic Beverages revenue, mm | C68: 606.928 | D68: 817.88 | E68: 826.683 | F68: 809.446 | G68: 832.395 | H68: 1108.175 | I68: 1103.017 | J68: 1199.42 | K68: 1040.422 | L68: 1192.282 | M68: 1172.584 | N68: 1107.03 | O68: 1072.227 | P68: 1238.885 | Q68: 1236.261 | R68: 1147.055 | S68: 1142.581 | T68: 1195.524 | U68: 1295.271 | V68: 1245.794 | W68: 1235.09 | X68: 1399.915 | Y68: 1426.971 | Z68: 1370.693 | AA68: 1373.221 | AB68: 1562.014 | AC68: 1600.065 | AD68: 1546.057 | AE68: 1545.412 | AF68: 1714.862 | AG68: 1691.06 | AH68: 1611.288 | AI68: 1574.712 | AJ68: 1780.152 | AK68: 1751.495 | AL68: 1732.686 | AM68: 1569 | AN68: 1845.061 | AO68: 1876.999 | AP68: 1892.722
A69: All Other revenue, mm | C69: 45.709 | D69: 58.397 | E69: 59.53 | F69: 71.096 | G69: 76.792 | H69: 119.669 | I69: 120.66 | J69: -15.32 | K69: 86.599 | L69: 93.398 | M69: 93.493 | N69: 85.135 | O69: 87.915 | P69: 94.942 | Q69: 92.501 | R69: 69.647 | S69: 81.301 | T69: 80.329 | U69: 84.776 | V69: 86.322 | W69: 89.949 | X69: 93.192 | Y69: 88.991 | Z69: 94.723 | AA69: 96.163 | AB69: 105.91 | AC69: 101.136 | AD69: 96.15 | AE69: 92.376 | AF69: 95.174 | AG69: 93.636 | AH69: 89.562 | AI69: 88.102 | AJ69: 86.598 | AK69: 86.23 | AL69: 85.447 | AM69: 75.988 | AN69: 81.21 | AO69: 85.702 | AP69: 83.069
A70: Eliminations in net sales, mm | C70: -27.181 | D70: -35.893 | E70: -37.185 | F70: -38.982 | G70: -43.485 | H70: -58.553 | I70: -61.151 | J70: -57.951 | K70: -62.264 | L70: -65.677 | M70: -62.044 | N70: -55.594 | O70: -57.23 | P70: -60.168 | Q70: -57.733 | R70: -37.753 | S70: -50.861 | T70: -48.638 | U70: -51.563 | V70: -53.479 | W70: -55.182 | X70: -60.021 | Y70: -58.53 | Z70: -63.077 | AA70: -65.026 | AB70: -72.709 | AC70: -72.612 | AD70: -69.412 | AE70: -66.146 | AF70: -71.204 | AG70: -72.268 | AH70: -69.894 | AI70: -71.188 | AJ70: -70.807 | AK70: -72.073 | AL70: -71.638 | AM70: -65.011 | AN70: -70.752 | AO70: -74.384 | AP70: -71.549
A71: Consolidated Net Sales, mm | C71: 625.456 | D71: 840.384 | E71: 849.028 | F71: 841.56 | G71: 865.702 | H71: 1169.291 | I71: 1162.526 | J71: 1126.149 | K71: 1064.757 | L71: 1220.003 | M71: 1204.033 | N71: 1136.571 | O71: 1102.912 | P71: 1273.659 | Q71: 1271.029 | R71: 1178.949 | S71: 1173.021 | T71: 1227.215 | U71: 1328.484 | V71: 1278.637 | W71: 1269.857 | X71: 1433.086 | Y71: 1457.432 | Z71: 1402.339 | AA71: 1404.358 | AB71: 1595.215 | AC71: 1628.589 | AD71: 1572.795 | AE71: 1571.642 | AF71: 1738.832 | AG71: 1712.428 | AH71: 1630.956 | AI71: 1591.626 | AJ71: 1795.943 | AK71: 1765.652 | AL71: 1746.495 | AM71: 1579.977 | AN71: 1855.519 | AO71: 1888.317 | AP71: 1904.242
A73: Nonalcoholic Beverages gross profit, mm | E73: 326.725
A74: All Other gross profit, mm | E74: 21.322
A75: Eliminations in gross profit, mm | E75: -20.857
A76: Consolidated Gross Profit, mm | E76: 327.19
A78: Nonalcoholic Beverages operating income, mm | C78: 10.968 | D78: 52.878 | E78: 38.421 | F78: 20.963 | G78: 11.534 | H78: 42.169 | I78: 32.525 | J78: -1.453 | K78: -22.745 | L78: 16.089 | M78: 39.361 | N78: 12.814 | O78: 14.641 | P78: 57.724 | Q78: 48.248 | R78: 53.52 | S78: 35.617 | T78: 83.907 | U78: 108.035 | V78: 97.157 | W78: 95.042 | X78: 124.372 | Y78: 144.13 | Z78: 93.169 | AA78: 134.558 | AB78: 144.012 | AC78: 189.218 | AD78: 171.348 | AE78: 209.779 | AF78: 234.211 | AG78: 217.405 | AH78: 180.096 | AI78: 212.142 | AJ78: 255.025 | AK78: 224.072 | AL78: 215.988 | AM78: 187.243 | AN78: 263.864 | AO78: 238.361 | AP78: 235.697
A79: All Other operating income, mm | C79: 1.433 | D79: 1.858 | E79: 1.38 | F79: -0.042 | G79: 2.074 | H79: 5.144 | I79: 3.605 | J79: 0.581 | K79: 3.748 | L79: 3.59 | M79: 5.043 | N79: 0.002 | O79: 5.513 | P79: 9.49 | Q79: 5.598 | R79: -13.98 | S79: -2.796 | T79: -0.789 | U79: -4.191 | V79: -3.562 | W79: -0.858 | X79: -3.511 | Y79: -7.099 | Z79: -6.074 | AA79: -3.573 | AB79: 3.281 | AC79: 0.712 | AD79: 1.491 | AE79: -3.725 | AF79: -0.541 | AG79: -1.145 | AH79: -1.629 | AI79: 3.264 | AJ79: 4.115 | AK79: 2.983 | AL79: 2.761 | AM79: 2.577 | AN79: 8.22 | AO79: 8.273 | AP79: 6.421
A80: Consolidated Operating Income, mm | C80: 12.401 | D80: 54.736 | E80: 39.801 | F80: 20.921 | G80: 13.608 | H80: 47.313 | I80: 36.13 | J80: -0.872 | K80: -18.997 | L80: 19.679 | M80: 44.404 | N80: 12.816 | O80: 20.154 | P80: 67.214 | Q80: 53.846 | R80: 39.54 | S80: 32.821 | T80: 83.118 | U80: 103.844 | V80: 93.595 | W80: 94.184 | X80: 120.861 | Y80: 137.031 | Z80: 87.095 | AA80: 130.985 | AB80: 147.293 | AC80: 189.93 | AD80: 172.839 | AE80: 206.054 | AF80: 233.67 | AG80: 216.26 | AH80: 178.467 | AI80: 215.406 | AJ80: 259.14 | AK80: 227.055 | AL80: 218.749 | AM80: 189.82 | AN80: 272.084 | AO80: 246.634 | AP80: 242.118
A82: Nonalcoholic Beverages operating margin, % | K82: -0.021861322 | L82: 0.013494291 | M82: 0.033567744 | N82: 0.011575115 | O82: 0.013654758 | P82: 0.046593509 | Q82: 0.039027357 | R82: 0.046658617 | S82: 0.031172407 | T82: 0.070184287 | U82: 0.083407256 | V82: 0.077988014 | W82: 0.076951477 | X82: 0.088842537 | Y82: 0.10100415 | Z82: 0.067972186 | AA82: 0.097987141 | AB82: 0.092196357 | AC82: 0.11825645 | AD82: 0.11082903 | AE82: 0.13574309 | AF82: 0.13657717 | AG82: 0.12856138 | AH82: 0.11177145 | AI82: 0.13471797 | AJ82: 0.14326024 | AK82: 0.12793185 | AL82: 0.12465502 | AM82: 0.11933907 | AN82: 0.14301099 | AO82: 0.12699048 | AP82: 0.12452806
A83: All Other operating margin, % | K83: 0.043279945 | L83: 0.038437654 | M83: 0.053939867 | N83: 2.3492101e-05 | O83: 0.062708298 | P83: 0.099955762 | Q83: 0.060518265 | R83: -0.20072652 | S83: -0.034390721 | T83: -0.0098221066 | U83: -0.049436161 | V83: -0.041264104 | W83: -0.0095387386 | X83: -0.037674908 | Y83: -0.079772112 | Z83: -0.064123814 | AA83: -0.037155663 | AB83: 0.030979133 | AC83: 0.0070400253 | AD83: 0.01550702 | AE83: -0.040324327 | AF83: -0.0056843256 | AG83: -0.012228203 | AH83: -0.018188517 | AI83: 0.037047967 | AJ83: 0.047518418 | AK83: 0.034593529 | AL83: 0.032312428 | AM83: 0.033913249 | AN83: 0.10121906 | AO83: 0.09653217 | AP83: 0.077297187
A84: Consolidated Operating Margin, % | K84: -0.01784163 | L84: 0.016130288 | M84: 0.036879388 | N84: 0.011276022 | O84: 0.018273443 | P84: 0.052772367 | Q84: 0.0423641 | R84: 0.033538346 | S84: 0.027979891 | T84: 0.067728964 | U84: 0.078167294 | V84: 0.073199039 | W84: 0.074168981 | X84: 0.084336181 | Y84: 0.094022225 | Z84: 0.062106951 | AA84: 0.093270377 | AB84: 0.092334262 | AC84: 0.11662243 | AD84: 0.1098929 | AE84: 0.13110747 | AF84: 0.13438331 | AG84: 0.12628852 | AH84: 0.10942478 | AI84: 0.13533707 | AJ84: 0.14429188 | AK84: 0.12859556 | AL84: 0.12525029 | AM84: 0.12014099 | AN84: 0.14663498 | AO84: 0.13061049 | AP84: 0.12714665
A86: Key Metrics - Revenue Walk (FS)
A87: Prior Period Net Sales, mm | C87: 453.253 | D87: 614.683 | E87: 618.806 | F87: 619.716 | G87: 625.456 | H87: 840.384 | I87: 849.028 | J87: 841.56 | K87: 865.702 | L87: 1169.291 | M87: 1162.526 | N87: 1126.149 | O87: 1064.757 | P87: 1220.003 | Q87: 1204.033 | R87: 1136.571 | S87: 1102.912 | T87: 1273.659 | U87: 1271.029 | V87: 1178.949 | W87: 1173.021 | X87: 1227.215 | Y87: 1328.484 | Z87: 1278.637 | AA87: 1269.857 | AB87: 1433.086 | AC87: 1457.432 | AD87: 1402.339 | AE87: 1404.358 | AF87: 1595.215 | AG87: 1628.589 | AH87: 1572.795 | AI87: 1571.642 | AJ87: 1738.832 | AK87: 1712.428 | AL87: 1630.956 | AM87: 1591.626 | AN87: 1795.943 | AO87: 1765.652 | AP87: 1746.495
A88: Net sales increase related to the Expansion Territories, mm | C88: 117.8 | D88: 211.7 | E88: 213.6 | F88: 230.5 | G88: 229.6 | H88: 309.8 | I88: 303.9 | J88: 247.9
A89: Increase in external transportation revenue, mm | C89: 6.8 | D89: 7.6 | E89: 6.6 | F89: 1.6 | H89: -3.1 | J89: 3.1 | AI89: -10
A90: Increase in sales of the Company's own brand products, mm | C90: -6.9 | D90: -9.8 | E90: -5.1 | F90: 0 | J90: 0
A91: Increase sales volume impact, mm | F91: 0 | J91: 0 | O91: 5.7 | P91: 7.8 | Q91: 46.9 | R91: 11.7 | S91: 53.8 | U91: 53.9 | V91: 83.5 | W91: 50.6 | X91: 77.2 | Z91: -32.3 | AA91: -7.7 | AB91: 10.7 | AC91: 4.9 | AD91: -7.9 | AE91: -30 | AF91: -60 | AG91: -25 | AH91: 5 | AI91: -5 | AM91: -85 | AO91: 60
A92: Increase in bottle/can sales volume to retail customers, mm | C92: 23 | D92: 19.8 | E92: 11.8 | F92: -0.2 | G92: 12.6 | H92: 7.6 | J92: 12.6
A93: Increase average bottle/can sales price per unit and product mix impact, mm | C93: 23.8 | D93: -2.6 | F93: -5.9 | H93: 12 | I93: 5.6 | J93: 11.3 | O93: 46.1 | P93: 56.6 | Q93: 25.9 | R93: 27.3 | S93: 12.9 | U93: 34.4 | V93: 27 | W93: 55.6 | X93: 96.5 | Y93: 115.3 | Z93: 145.1 | AA93: 140 | AB93: 148.1 | AC93: 180.9 | AD93: 141 | AE93: 175 | AF93: 185 | AG93: 95 | AH93: 60 | AI93: 40 | AJ93: 65 | AK93: 60 | AL93: 85 | AM93: 40 | AN93: 50 | AO93: 60 | AP93: 65
A94: Increase in post-mix sales volume, mm | C94: 1.1 | D94: 1 | F94: -2.1 | J94: 0
A95: Increase in post-mix sales price per unit, mm | F95: 0 | H95: 2.2 | J95: -2.2
A96: Increase in sales price per unit to other Coca-Cola bottlers, mm | C96: 1.1 | F96: -1.1 | G96: -2.4 | J96: 2.4
A97: Increase in sales volume to other Coca-Cola bottlers, mm | C97: 4.8 | F97: -4.8 | J97: 0 | O97: -20 | P97: -17.7 | Q97: -8.9 | R97: 0.9 | S97: 3.6 | T97: -9.4 | V97: -6.7 | X97: 8.6 | Z97: 9 | AB97: 5.7 | AD97: -5.7
A98: Increase in volume of external freight revenue to external customers, mm | F98: 0 | J98: 0 | R98: 20 | V98: 0 | X98: 1.4 | Z98: 0.1 | AD98: 0
A99: Increase in fountain syrup sales due to COVID-19, mm | F99: 0 | J99: 0 | R99: 0 | T99: -34.2 | U99: -30.8 | V99: -5.7 | W99: -9.4 | X99: 22.2 | Y99: 9.4 | Z99: 6.1 | AD99: 0
A100: Increase in data analysis and consulting services, mm | F100: 0 | J100: 0
A101: Increase in supply chain and logistics solutions consulting, mm | F101: 0 | J101: 0
A102: Refund in 2013 of 2012 cooperative trade marketing funds, mm | F102: 0 | J102: 0
A103: Increase in fees to facilitate distribution of certain brands, mm | F103: 0 | J103: 0
A104: Increase in freight revenue, mm | F104: 0 | J104: 0
A105: Other impact, mm | C105: 0.7 | D105: -2 | E105: 3.3 | F105: 3.9 | G105: 0.4 | H105: 0.4 | I105: 4 | J105: 9.5 | O105: 6.4 | P105: 7 | Q105: 3.1 | R105: -17.6 | S105: -0.2 | T105: -2.8 | V105: 1.5 | Y105: 4.2 | Z105: -4.2 | AA105: 2.2 | AB105: -2.4 | AC105: -14.6 | AD105: 43.043 | AE105: 22.284 | AF105: 18.617 | AG105: 13.839 | AH105: -6.839 | AI105: -5.016 | AJ105: -7.889 | AK105: -6.776 | AL105: 30.539 | AM105: 33.351 | AN105: 9.576 | AO105: 2.665 | AP105: 92.747
A106: Current Period Net Sales, mm | C106: 625.456 | D106: 840.384 | E106: 849.028 | F106: 841.56 | G106: 865.702 | H106: 1169.291 | I106: 1162.526 | J106: 1126.149 | K106: 1064.757 | L106: 1220.003 | M106: 1204.033 | N106: 1136.571 | O106: 1102.912 | P106: 1273.659 | Q106: 1271.029 | R106: 1178.949 | S106: 1173.021 | T106: 1227.215 | U106: 1328.484 | V106: 1278.637 | W106: 1269.857 | X106: 1433.086 | Y106: 1457.432 | Z106: 1402.339 | AA106: 1404.358 | AB106: 1595.215 | AC106: 1628.589 | AD106: 1572.795 | AE106: 1571.642 | AF106: 1738.832 | AG106: 1712.428 | AH106: 1630.956 | AI106: 1591.626 | AJ106: 1795.943 | AK106: 1765.652 | AL106: 1746.495 | AM106: 1579.977 | AN106: 1855.519 | AO106: 1888.317 | AP106: 1904.242
A108: Key Metrics - COGS Walk (FS)
A109: Prior Period COGS, mm | C109: 268.88 | D109: 377.366 | E109: 380.27 | F109: 378.91 | G109: 381.558 | H109: 520.677 | I109: 521.838 | J109: 516.633 | K109: 533.681 | L109: 754.113 | M109: 752.202 | N109: 742.725 | O109: 707.116 | P109: 815.295 | Q109: 791.317 | R109: 755.924 | S109: 713.604 | T109: 837.88 | U109: 838.805 | V109: 765.758 | W109: 767.726 | X109: 797.914 | Y109: 856.046 | Z109: 816.762 | AA109: 821.154 | AB109: 938.146 | AC109: 939.72 | AD109: 909.507 | AE109: 896.782 | AF109: 1044.556 | AG109: 1007.482 | AH109: 974.183 | AI109: 947.536 | AJ109: 1067.255 | AK109: 1050.878 | AL109: 989.478 | AM109: 951.067 | AN109: 1079.233 | AO109: 1067.616 | AP109: 1048.621
A110: Net sales increase related to the Expansion Territories, mm | C110: 76.2 | D110: 134.9 | E110: 135.7 | F110: 147.1 | G110: 146.9 | H110: 216.7 | I110: 215.8 | J110: 186.4
A111: Increase in bottle/can sales volume to retail customers, mm | C111: 13.2 | D111: 11.3 | E111: 6.8 | F111: -0.6 | G111: 7.3 | H111: 4.5 | J111: 7.2
A112: Increase in raw material costs and increased purchases of finished products, mm | C112: 18.3 | D112: 2.7 | F112: -1.7 | H112: 9.7 | I112: 11.5 | J112: 25.2
A113: Increase in marketing funding support received for the Legacy Territories, mm | C113: -4.5 | D113: -3.8 | F113: -4.9 | J113: 0
A114: Increase in manufacturing cost, mm | J114: 0 | AH114: 0 | AI114: 35 | AJ114: 30 | AK114: 30 | AL114: 25 | AN114: 35 | AO114: 25 | AP114: 75
A115: Increase in cost of sales of the Company’s own brand products, mm | C115: -3.8 | D115: -4.7 | F115: -3.1 | J115: 0
A116: Decrease in fountain syrup sales due to COVID-19, mm | F116: 0 | J116: 0 | R116: 0 | T116: -26 | U116: -24.3 | V116: 2.2 | W116: -9.6 | X116: 16.2 | Y116: 6.6 | Z116: 7.8
...

Sheet Canalyst Model
A1: Coca-Cola Consolidated
A2: =CHOOSE(MO.DataSourceIndex,MO.Ticker.Bloomberg,MO.Ticker.CapIQ,MO.Ticker.FactSet,MO.Ticker.Thomson) -> #NAME? | AA2: Unrestated | AB2: Unrestated | AC2: Unrestated | AD2: Unrestated | AE2: Unrestated | AF2: Restated | AG2: Restated | AH2: Restated
A3: =HP.TradeCurrency -> #NAME? | B3: =IF(MO.RealTime="OFF",MO.LastPriceHardcoded,MO.LastPriceFormula) -> #NAME? | C3: 371 | D3: =D4-C4 -> 364 | E3: =E4-D4 -> 364 | F3: =F4-E4 -> 364 | G3: =G4-F4 -> 91 | H3: =H4-G4 -> 91 | I3: =I4-H4 -> 91 | J3: =J4-I4 -> 91 | K3: =K4-F4 -> 364 | L3: =L4-K4 -> 91 | M3: =M4-L4 -> 91 | N3: =N4-M4 -> 91 | O3: =O4-N4 -> 91 | P3: =P4-K4 -> 364 | Q3: =Q4-P4 -> 91 | R3: =R4-Q4 -> 91 | S3: =S4-R4 -> 91 | T3: =T4-S4 -> 98 | U3: =U4-P4 -> 371 | V3: =V4-U4 -> 91 | W3: =W4-V4 -> 91 | X3: =X4-W4 -> 91 | Y3: =Y4-X4 -> 91 | Z3: =Z4-U4 -> 364 | AA3: =AA4-Z4 -> 91 | AB3: =AB4-AA4 -> 91 | AC3: =AC4-AB4 -> 91 | AD3: =AD4-AC4 -> 91 | AE3: =AE4-Z4 -> 364 | AF3: =AF4-AE4 -> 91 | AG3: =AG4-AF4 -> 91 | AH3: =AH4-AG4 -> 91 | AI3: =AI4-AH4 -> 91 | AJ3: =AJ4-AE4 -> 364 | AK3: =AK4-AJ4 -> 91 | AL3: =AL4-AK4 -> 91 | AM3: =AM4-AL4 -> 91 | AN3: =AN4-AM4 -> 91 | AO3: =AO4-AJ4 -> 364 | AP3: =AP4-AO4 -> 91 | AQ3: =AQ4-AP4 -> 91 | AR3: =AR4-AQ4 -> 91 | AS3: =AS4-AR4 -> 95 | AT3: =AT4-AO4 -> 368 | AU3: =AU4-AT4 -> 92 | AV3: =AV4-AU4 -> 91 | AW3: =AW4-AV4 -> 91 | AX3: =AX4-AW4 -> 91 | AY3: =AY4-AT4 -> 365 | AZ3: =AZ4-AY4 -> 91 | BA3: =BA4-AZ4 -> 92 | BB3: =BB4-BA4 -> 90 | BC3: =BC4-BB4 -> 92 | BD3: =BD4-AY4 -> 365 | BE3: =BE4-BD4 -> 90 | BF3: =BF4-BE4 -> 91 | BG3: =BG4-BF4 -> 91 | BH3: =BH4-BG4 -> 93 | BI3: =BI4-BD4 -> 365 | BJ3: =BJ4-BI4 -> 89 | BK3: =BK4-BJ4 -> 91 | BL3: =BL4-BK4 -> 91 | BM3: =BM4-BL4 -> 95 | BN3: =BN4-BI4 -> 366 | BO3: =BO4-BN4 -> 87 | BP3: =BP4-BO4 -> 91 | BQ3: =BQ4-BP4 -> 91 | BR3: =BR4-BQ4 -> 96 | BS3: =BS4-BN4 -> 365 | BT3: 91 | BU3: 91 | BV3: 91 | BW3: 92 | BX3: =BX4-BS4 -> 365 | BY3: 91 | BZ3: 91 | CA3: 91 | CB3: 92 | CC3: =CC4-BX4 -> 365 | CD3: 366 | CE3: 365 | CF3: 365
A4: =FP.DataSourceName -> #NAME? | B4: =IF(AND(MO.RealTimeStockPriceToggle,MO.LastPriceFormula<>"N/A"),"ON","OFF") -> #NAME? | C4: 40181 | D4: 40545 | E4: 40909 | F4: 41273 | G4: 41364 | H4: 41455 | I4: 41546 | J4: 41637 | K4: =J4 -> 41637 | L4: 41728 | M4: 41819 | N4: 41910 | O4: 42001 | P4: =O4 -> 42001 | Q4: 42092 | R4: 42183 | S4: 42274 | T4: 42372 | U4: =T4 -> 42372 | V4: 42463 | W4: 42554 | X4: 42645 | Y4: 42736 | Z4: =Y4 -> 42736 | AA4: 42827 | AB4: 42918 | AC4: 43009 | AD4: 43100 | AE4: =AD4 -> 43100 | AF4: 43191 | AG4: 43282 | AH4: 43373 | AI4: 43464 | AJ4: =AI4 -> 43464 | AK4: 43555 | AL4: 43646 | AM4: 43737 | AN4: 43828 | AO4: =AN4 -> 43828 | AP4: 43919 | AQ4: 44010 | AR4: 44101 | AS4: 44196 | AT4: =AS4 -> 44196 | AU4: 44288 | AV4: 44379 | AW4: 44470 | AX4: 44561 | AY4: =AX4 -> 44561 | AZ4: 44652 | BA4: 44744 | BB4: 44834 | BC4: 44926 | BD4: =BC4 -> 44926 | BE4: 45016 | BF4: 45107 | BG4: 45198 | BH4: 45291 | BI4: =BH4 -> 45291 | BJ4: 45380 | BK4: 45471 | BL4: 45562 | BM4: 45657 | BN4: =BM4 -> 45657 | BO4: 45744 | BP4: 45835 | BQ4: 45926 | BR4: 46022 | BS4: =BR4 -> 46022 | BT4: =BT3+BS4 -> 46113 | BU4: =BU3+BT4 -> 46204 | BV4: =BV3+BU4 -> 46295 | BW4: =BW3+BV4 -> 46387 | BX4: =BW4 -> 46387 | BY4: =BY3+BX4 -> 46478 | BZ4: =BZ3+BY4 -> 46569 | CA4: =CA3+BZ4 -> 46660 | CB4: =CB3+CA4 -> 46752 | CC4: =CB4 -> 46752 | CD4: =CD3+CC4 -> 47118 | CE4: =CE3+CD4 -> 47483 | CF4: =CF3+CE4 -> 47848
A5: =MO.ReportCurrency -> #NAME? | C5: FY2009 | D5: =CONCATENATE("FY",RIGHT(C5,4)+1) -> FY2010 | E5: =CONCATENATE("FY",RIGHT(D5,4)+1) -> FY2011 | F5: =CONCATENATE("FY",RIGHT(E5,4)+1) -> FY2012 | G5: =CONCATENATE("Q1","-",RIGHT(F5,4)+1) -> Q1-2013 | H5: =CONCATENATE("Q2","-",RIGHT(G5,4)) -> Q2-2013 | I5: =CONCATENATE("Q3","-",RIGHT(H5,4)) -> Q3-2013 | J5: =CONCATENATE("Q4","-",RIGHT(I5,4)) -> Q4-2013 | K5: =CONCATENATE("FY",RIGHT(F5,4)+1) -> FY2013 | L5: =CONCATENATE("Q1","-",RIGHT(K5,4)+1) -> Q1-2014 | M5: =CONCATENATE("Q2","-",RIGHT(L5,4)) -> Q2-2014 | N5: =CONCATENATE("Q3","-",RIGHT(M5,4)) -> Q3-2014 | O5: =CONCATENATE("Q4","-",RIGHT(N5,4)) -> Q4-2014 | P5: =CONCATENATE("FY",RIGHT(K5,4)+1) -> FY2014 | Q5: =CONCATENATE("Q1","-",RIGHT(P5,4)+1) -> Q1-2015 | R5: =CONCATENATE("Q2","-",RIGHT(Q5,4)) -> Q2-2015 | S5: =CONCATENATE("Q3","-",RIGHT(R5,4)) -> Q3-2015 | T5: =CONCATENATE("Q4","-",RIGHT(S5,4)) -> Q4-2015 | U5: =CONCATENATE("FY",RIGHT(P5,4)+1) -> FY2015 | V5: =CONCATENATE("Q1","-",RIGHT(U5,4)+1) -> Q1-2016 | W5: =CONCATENATE("Q2","-",RIGHT(V5,4)) -> Q2-2016 | X5: =CONCATENATE("Q3","-",RIGHT(W5,4)) -> Q3-2016 | Y5: =CONCATENATE("Q4","-",RIGHT(X5,4)) -> Q4-2016 | Z5: =CONCATENATE("FY",RIGHT(U5,4)+1) -> FY2016 | AA5: =CONCATENATE("Q1","-",RIGHT(Z5,4)+1) -> Q1-2017 | AB5: =CONCATENATE("Q2","-",RIGHT(AA5,4)) -> Q2-2017 | AC5: =CONCATENATE("Q3","-",RIGHT(AB5,4)) -> Q3-2017 | AD5: =CONCATENATE("Q4","-",RIGHT(AC5,4)) -> Q4-2017 | AE5: =CONCATENATE("FY",RIGHT(Z5,4)+1) -> FY2017 | AF5: =CONCATENATE("Q1","-",RIGHT(AE5,4)+1) -> Q1-2018 | AG5: =CONCATENATE("Q2","-",RIGHT(AF5,4)) -> Q2-2018 | AH5: =CONCATENATE("Q3","-",RIGHT(AG5,4)) -> Q3-2018 | AI5: =CONCATENATE("Q4","-",RIGHT(AH5,4)) -> Q4-2018 | AJ5: =CONCATENATE("FY",RIGHT(AE5,4)+1) -> FY2018 | AK5: =CONCATENATE("Q1","-",RIGHT(AJ5,4)+1) -> Q1-2019 | AL5: =CONCATENATE("Q2","-",RIGHT(AK5,4)) -> Q2-2019 | AM5: =CONCATENATE("Q3","-",RIGHT(AL5,4)) -> Q3-2019 | AN5: =CONCATENATE("Q4","-",RIGHT(AM5,4)) -> Q4-2019 | AO5: =CONCATENATE("FY",RIGHT(AJ5,4)+1) -> FY2019 | AP5: =CONCATENATE("Q1","-",RIGHT(AO5,4)+1) -> Q1-2020 | AQ5: =CONCATENATE("Q2","-",RIGHT(AP5,4)) -> Q2-2020 | AR5: =CONCATENATE("Q3","-",RIGHT(AQ5,4)) -> Q3-2020 | AS5: =CONCATENATE("Q4","-",RIGHT(AR5,4)) -> Q4-2020 | AT5: =CONCATENATE("FY",RIGHT(AO5,4)+1) -> FY2020 | AU5: =CONCATENATE("Q1","-",RIGHT(AT5,4)+1) -> Q1-2021 | AV5: =CONCATENATE("Q2","-",RIGHT(AU5,4)) -> Q2-2021 | AW5: =CONCATENATE("Q3","-",RIGHT(AV5,4)) -> Q3-2021 | AX5: =CONCATENATE("Q4","-",RIGHT(AW5,4)) -> Q4-2021 | AY5: =CONCATENATE("FY",RIGHT(AT5,4)+1) -> FY2021 | AZ5: =CONCATENATE("Q1","-",RIGHT(AY5,4)+1) -> Q1-2022 | BA5: =CONCATENATE("Q2","-",RIGHT(AZ5,4)) -> Q2-2022 | BB5: =CONCATENATE("Q3","-",RIGHT(BA5,4)) -> Q3-2022 | BC5: =CONCATENATE("Q4","-",RIGHT(BB5,4)) -> Q4-2022 | BD5: =CONCATENATE("FY",RIGHT(AY5,4)+1) -> FY2022 | BE5: =CONCATENATE("Q1","-",RIGHT(BD5,4)+1) -> Q1-2023 | BF5: =CONCATENATE("Q2","-",RIGHT(BE5,4)) -> Q2-2023 | BG5: =CONCATENATE("Q3","-",RIGHT(BF5,4)) -> Q3-2023 | BH5: =CONCATENATE("Q4","-",RIGHT(BG5,4)) -> Q4-2023 | BI5: =CONCATENATE("FY",RIGHT(BD5,4)+1) -> FY2023 | BJ5: =CONCATENATE("Q1","-",RIGHT(BI5,4)+1) -> Q1-2024 | BK5: =CONCATENATE("Q2","-",RIGHT(BJ5,4)) -> Q2-2024 | BL5: =CONCATENATE("Q3","-",RIGHT(BK5,4)) -> Q3-2024 | BM5: =CONCATENATE("Q4","-",RIGHT(BL5,4)) -> Q4-2024 | BN5: =CONCATENATE("FY",RIGHT(BI5,4)+1) -> FY2024 | BO5: =CONCATENATE("Q1","-",RIGHT(BN5,4)+1) -> Q1-2025 | BP5: =CONCATENATE("Q2","-",RIGHT(BO5,4)) -> Q2-2025 | BQ5: =CONCATENATE("Q3","-",RIGHT(BP5,4)) -> Q3-2025 | BR5: =CONCATENATE("Q4","-",RIGHT(BQ5,4)) -> Q4-2025 | BS5: =CONCATENATE("FY",RIGHT(BN5,4)+1) -> FY2025 | BT5: =CONCATENATE("Q1","-",RIGHT(BS5,4)+1) -> Q1-2026 | BU5: =CONCATENATE("Q2","-",RIGHT(BT5,4)) -> Q2-2026 | BV5: =CONCATENATE("Q3","-",RIGHT(BU5,4)) -> Q3-2026 | BW5: =CONCATENATE("Q4","-",RIGHT(BV5,4)) -> Q4-2026 | BX5: =CONCATENATE("FY",RIGHT(BS5,4)+1) -> FY2026 | BY5: =CONCATENATE("Q1","-",RIGHT(BX5,4)+1) -> Q1-2027 | BZ5: =CONCATENATE("Q2","-",RIGHT(BY5,4)) -> Q2-2027 | CA5: =CONCATENATE("Q3","-",RIGHT(BZ5,4)) -> Q3-2027 | CB5: =CONCATENATE("Q4","-",RIGHT(CA5,4)) -> Q4-2027 | CC5: =CONCATENATE("FY",RIGHT(BX5,4)+1) -> FY2027 | CD5: =CONCATENATE("FY",RIGHT(CC5,4)+1) -> FY2028 | CE5: =CONCATENATE("FY",RIGHT(CD5,4)+1) -> FY2029 | CF5: =CONCATENATE("FY",RIGHT(CE5,4)+1) -> FY2030
A6: Growth Analysis
A7: Sparkling beverages revenue growth, % | D7: =D19/C19-1 -> 0.02490868 | E7: =E19/D19-1 -> 0.020109111 | F7: =F19/E19-1 -> 0.019870476 | K7: =K19/F19-1 -> -0.0092416998 | L7: =L19/G19-1 -> 0.0019569856 | M7: =M19/H19-1 -> 0.066426325 | N7: =N19/I19-1 -> 0.047187894 | O7: =O19/J19-1 -> 0.1143788 | P7: =P19/K19-1 -> 0.057985955 | Q7: =Q19/L19-1 -> 0.16805048 | R7: =R19/M19-1 -> 0.37756453 | ... CC7: =CC19/BX19-1 -> 0.005 | CD7: =CD19/CC19-1 -> 0.005 | CE7: =CE19/CD19-1 -> 0.005 | CF7: =CF19/CE19-1 -> 0.005
A8: Still beverage revenue growth, % | D8: =D20/C20-1 -> 0.0568639 | E8: =E20/D20-1 -> 0.028365407 | F8: =F20/E20-1 -> 0.064959841 | K8: =K20/F20-1 -> 0.058427927 | L8: =L20/G20-1 -> 0.086027022 | M8: =M20/H20-1 -> 0.1249414 | N8: =N20/I20-1 -> 0.11186866 | O8: =O20/J20-1 -> 0.19627409 | P8: =P20/K20-1 -> 0.1275524 | Q8: =Q20/L20-1 -> 0.23513561 | R8: =R20/M20-1 -> 0.40762489 | ... CC8: =CC20/BX20-1 -> 0.015 | CD8: =CD20/CC20-1 -> 0.02 | CE8: =CE20/CD20-1 -> 0.02 | CF8: =CF20/CE20-1 -> 0.02
A9: Total Bottle/Can Revenue Growth, % | D9: =D21/C21-1 -> 0.030252351 | E9: =E21/D21-1 -> 0.021525422 | F9: =F21/E21-1 -> 0.027657038 | K9: =K21/F21-1 -> 0.0028684755 | L9: =L21/G21-1 -> 0.016362961 | M9: =M21/H21-1 -> 0.078531 | N9: =N21/I21-1 -> 0.060848229 | O9: =O21/J21-1 -> 0.12764638 | P9: =P21/K21-1 -> 0.071125302 | Q9: =Q21/L21-1 -> 0.18033391 | R9: =R21/M21-1 -> 0.38405053 | ... CC9: =CC21/BX21-1 -> 0.0086956925 | CD9: =CD21/CC21-1 -> 0.010578186 | CE9: =CE21/CD21-1 -> 0.010630192 | CF9: =CF21/CE21-1 -> 0.010682391
A10: Sales to other Coca-Cola bottlers revenue growth, % | D10: =D22/C22-1 -> 0.073608686 | E10: =E22/D22-1 -> 0.067233873 | F10: =F22/E22-1 -> 0.014154145 | K10: =K22/F22-1 -> 0.092355037 | L10: =L22/G22-1 -> -0.074935207 | M10: =M22/H22-1 -> 0.018104941 | N10: =N22/I22-1 -> -0.017582679 | O10: =O22/J22-1 -> -0.029833145 | P10: =P22/K22-1 -> -0.024808381 | Q10: =Q22/L22-1 -> 0.019530724 | R10: =R22/M22-1 -> 0.072722453 | ... BS10: =BS22/BN22-1 -> 0.1101665 | BT10: 0.02 | BU10: 0.02 | BV10: 0.02 | BW10: 0.02 | BX10: =BX22/BS22-1 -> 0.02 | BY10: 0.02 | BZ10: 0.02 | CA10: 0.02 | CB10: 0.02 | CC10: =CC22/BX22-1 -> 0.02 | CD10: 0.02 | CE10: 0.02 | CF10: 0.02
A11: Post-mix and other revenue growth, % | D11: =D23/C23-1 -> 0.24566239 | E11: =E23/D23-1 -> 0.080544104 | F11: =F23/E23-1 -> 0.114196 | K11: =K23/F23-1 -> 0.058517019 | L11: =L23/G23-1 -> 0.082941063 | M11: =M23/H23-1 -> 0.067058558 | N11: =N23/I23-1 -> 0.062443299 | O11: =O23/J23-1 -> 0.18603803 | P11: =P23/K23-1 -> 0.097130498 | Q11: =Q23/L23-1 -> 0.19471276 | R11: =R23/M23-1 -> 0.23239258 | ... BS11: =BS23/BN23-1 -> 0.04919525 | BT11: 0.02 | BU11: 0.02 | BV11: 0.02 | BW11: 0.02 | BX11: =BX23/BS23-1 -> 0.02 | BY11: 0.02 | BZ11: 0.02 | CA11: 0.02 | CB11: 0.02 | CC11: =CC23/BX23-1 -> 0.02 | CD11: 0.02 | CE11: 0.02 | CF11: 0.02
A12: Total Other Revenue Growth, % | D12: =D24/C24-1 -> 0.14945577 | E12: =E24/D24-1 -> 0.073592576 | F12: =F24/E24-1 -> 0.062256648 | K12: =K24/F24-1 -> 0.075289381 | L12: =L24/G24-1 -> 7.8477536e-05 | M12: =M24/H24-1 -> 0.042517448 | N12: =N24/I24-1 -> 0.023881316 | O12: =O24/J24-1 -> 0.076081539 | P12: =P24/K24-1 -> 0.035730273 | Q12: =Q24/L24-1 -> 0.10966375 | R12: =R24/M24-1 -> 0.15422218 | ... CC12: =CC24/BX24-1 -> 0.02 | CD12: =CD24/CC24-1 -> 0.02 | CE12: =CE24/CD24-1 -> 0.02 | CF12: =CF24/CE24-1 -> 0.02
A13: Total Revenue Growth, % | D13: =D401/C401-1 -> 0.04962834 | E13: =E401/D401-1 -> 0.030793629 | F13: =F401/E401-1 -> 0.034071657 | K13: =K401/F401-1 -> 0.016660958 | L13: =L401/G401-1 -> 0.0131169 | M13: =M401/H401-1 -> 0.071085065 | N13: =N401/I401-1 -> 0.053426751 | O13: =O401/J401-1 -> 0.1174148 | P13: =P401/K401-1 -> 0.063995623 | Q13: =Q401/L401-1 -> 0.16642819 | R13: =R401/M401-1 -> 0.33780004 | ... CC13: =CC401/BX401-1 -> 0.0096559218 | CD13: =CD401/CC401-1 -> 0.011386709 | CE13: =CE401/CD401-1 -> 0.0114411 | CF13: =CF401/CE401-1 -> 0.011495605
A15: Comparable Net Sales, % | P15: 0.037 | Q15: 0.029 | U15: 0.1 | W15: 0.045 | X15: 0.041 | Y15: 0.063 | Z15: 0.07 | AA15: 0.018 | AB15: 0.028 | AC15: 0.014 | AD15: 0.067 | AE15: 0.031 | AS15: 0.035 | AX15: 0.15
A16: Organic Net Sales Growth, % | AF16: 0.024 | AG16: 0.026 | AH16: 0.043 | AI16: 0.029 | AJ16: 0.034
A18: Segmented Results - Revenue Breakdown (FS)
A19: Sparkling beverages revenue, mm | C19: 1006.356 | D19: 1031.423 | E19: 1052.164 | F19: 1073.071 | G19: 254.473 | H19: 269.893 | I19: 273.905 | J19: =K19-SUM(G19,H19,I19) -> 264.883 | K19: 1063.154 | L19: 254.971 | M19: 287.821 | N19: 286.83 | O19: =P19-SUM(L19,M19,N19) -> 295.18 | P19: 1124.802 | Q19: 297.819 | R19: 396.492 | S19: 387.955 | T19: =U19-SUM(Q19,R19,S19) -> 421.417 | U19: 1503.683 | V19: 352.67 | W19: 464.859 | X19: 455.748 | Y19: =Z19-SUM(V19,W19,X19) -> 491.281 | Z19: 1764.558 | AA19: 479.76 | AB19: 607.623 | AC19: 582.71 | AD19: =AE19-SUM(AA19,AB19,AC19) -> 615.528 | AE19: 2285.621 | AF19: 560.105 | AG19: 637.215 | AH19: 619.705 | AI19: =AJ19-SUM(AF19,AG19,AH19) -> 578.188 | AJ19: 2395.213 | AK19: 585.973 | AL19: 671.624 | AM19: 657.507 | AN19: =AO19-SUM(AK19,AL19,AM19) -> 667.374 | AO19: 2582.478 | AP19: 631.113 | AQ19: 694.162 | AR19: 703.549 | AS19: =AT19-SUM(AP19,AQ19,AR19) -> 732.003 | AT19: 2760.827 | AU19: 694.179 | AV19: 754.683 | AW19: 773.489 | AX19: =AY19-SUM(AU19,AV19,AW19) -> 798.536 | AY19: 3020.887 | AZ19: 775.584 | BA19: 879.935 | BB19: 917.162 | BC19: 948.5 | BD19: 3521.273 | BE19: 920.562 | BF19: 1004.438 | BG19: 977.663 | BH19: 1006.1 | BI19: 3892.133 | BJ19: 951.992 | BK19: 1048.874 | BL19: 1034.69 | BM19: 1083.5 | BN19: 4106.073 | BO19: 933.837 | BP19: 1079.956 | BQ19: 1083.139 | BR19: 1152.9 | BS19: 4249.847 | BT19: =BT57*BT42 -> 936.86211 | BU19: =BU57*BU42 -> 1078.4085 | BV19: =BV57*BV42 -> 1081.7323 | BW19: =BW57*BW42 -> 1165.5128 | BX19: =SUM(BT19,BU19,BV19,BW19) -> 4262.5156 | BY19: =BY57*BY42 -> 941.54642 | BZ19: =BZ57*BZ42 -> 1083.8006 | CA19: =CA57*CA42 -> 1087.1409 | CB19: =CB57*CB42 -> 1171.3403 | CC19: =SUM(BY19,BZ19,CA19,CB19) -> 4283.8282 | CD19: =CD57*CD42 -> 4305.2474 | CE19: =CE57*CE42 -> 4326.7736 | CF19: =CF57*CF42 -> 4348.4075
A20: Still beverage revenue, mm | C20: 202.079 | D20: 213.57 | E20: 219.628 | F20: 233.895 | G20: 52.623 | H20: 70.393 | I20: 73.336 | J20: =K20-SUM(G20,H20,I20) -> 51.209 | K20: 247.561 | L20: 57.15 | M20: 79.188 | N20: 81.54 | O20: =P20-SUM(L20,M20,N20) -> 61.26 | P20: 279.138 | Q20: 70.588 | R20: 111.467 | S20: 120.372 | T20: =U20-SUM(Q20,R20,S20) -> 95.474 | U20: 397.901 | V20: 166.19 | W20: 246.371 | X20: 261.508 | Y20: =Z20-SUM(V20,W20,X20) -> 218.056 | Z20: 892.125 | AA20: 256.058 | AB20: 368.955 | AC20: 384.495 | AD20: =AE20-SUM(AA20,AB20,AC20) -> 316.461 | AE20: 1325.969 | AF20: 320.917 | AG20: 393.015 | AH20: 400.795 | AI20: =AJ20-SUM(AF20,AG20,AH20) -> 356.764 | AJ20: 1471.491 | AK20: 343.695 | AL20: 421.45 | AM20: 438.51 | AN20: =AO20-SUM(AK20,AL20,AM20) -> 355.289 | AO20: 1558.944 | AP20: 373.278 | AQ20: 397.045 | AR20: 464.921 | AS20: =AT20-SUM(AP20,AQ20,AR20) -> 406.472 | AT20: 1641.716 | AU20: 420.056 | AV20: 498.99 | AW20: 503.99 | AX20: =AY20-SUM(AU20,AV20,AW20) -> 438.126 | AY20: 1861.162 | AZ20: 467.933 | BA20: 539.589 | BB20: 548.333 | BC20: 468.1 | BD20: 2020.1 | BE20: 509.628 | BF20: 573.641 | BG20: 575.954 | BH20: 488.6 | BI20: 2149.639 | BJ20: 511.642 | BK20: 597.485 | BL20: 585.527 | BM20: 531.3 | BN20: 2227.243 | BO20: 509.157 | BP20: 626.078 | BQ20: 643.287 | BR20: 584.4 | BS20: 2362.873 | BT20: =BT58*BT43 -> 518.01905 | BU20: =BU58*BU43 -> 664.59744 | BV20: =BV58*BV43 -> 719.06701 | BW20: =BW58*BW43 -> 597.07578 | BX20: =SUM(BT20,BU20,BV20,BW20) -> 2498.7593 | BY20: =BY58*BY43 -> 525.78934 | BZ20: =BZ58*BZ43 -> 674.5664 | CA20: =CA58*CA43 -> 729.85301 | CB20: =CB58*CB43 -> 606.03192 | CC20: =SUM(BY20,BZ20,CA20,CB20) -> 2536.2407 | CD20: =CD58*CD43 -> 2586.9655 | CE20: =CE58*CE43 -> 2638.7048 | CF20: =CF58*CF43 -> 2691.4789
A21: Total Bottle/Can Sales, mm | C21: =SUM(C19:C20) -> 1208.435 | D21: =SUM(D19:D20) -> 1244.993 | E21: =SUM(E19:E20) -> 1271.792 | F21: =SUM(F19:F20) -> 1306.966 | G21: =SUM(G19:G20) -> 307.096 | H21: =SUM(H19:H20) -> 340.286 | I21: =SUM(I19:I20) -> 347.241 | J21: =SUM(J19:J20) -> 316.092 | ... BB21: =SUM(BB19:BB20) -> 1465.495 | BC21: =BD21-AZ21-BA21-BB21 -> 1412.837 | BD21: =SUM(BD19:BD20) -> 5541.373 | BE21: =SUM(BE19:BE20) -> 1430.19 | BF21: =SUM(BF19:BF20) -> 1578.079 | BG21: =SUM(BG19:BG20) -> 1553.617 | BH21: =BI21-BE21-BF21-BG21 -> 1479.886 | BI21: =SUM(BI19:BI20) -> 6041.772 | BJ21: =SUM(BJ19:BJ20) -> 1463.634 | BK21: =SUM(BK19:BK20) -> 1646.359 | BL21: =SUM(BL19:BL20) -> 1620.217 | BM21: =BN21-BJ21-BK21-BL21 -> 1603.106 | BN21: =SUM(BN19:BN20) -> 6333.316 | BO21: =SUM(BO19:BO20) -> 1442.994 | BP21: =SUM(BP19:BP20) -> 1706.034 | BQ21: =SUM(BQ19:BQ20) -> 1726.426 | BR21: =BS21-BO21-BP21-BQ21 -> 1737.266 | BS21: =SUM(BS19:BS20) -> 6612.72 | BT21: =SUM(BT19:BT20) -> 1454.8812 | BU21: =SUM(BU19:BU20) -> 1743.006 | BV21: =SUM(BV19:BV20) -> 1800.7993 | BW21: =SUM(BW19:BW20) -> 1762.5886 | BX21: =SUM(BX19:BX20) -> 6761.2749 | BY21: =SUM(BY19:BY20) -> 1467.3358 | BZ21: =SUM(BZ19:BZ20) -> 1758.367 | ... CF21: =SUM(CF19:CF20) -> 7039.8864
A22: Sales to other Coca-Cola bottlers revenue, mm | C22: 131.153 | D22: 140.807 | E22: 150.274 | F22: 152.401 | G22: 40.128 | H22: 44.463 | I22: 42.03 | J22: =K22-SUM(G22,H22,I22) -> 39.855 | K22: 166.476 | L22: 37.121 | M22: 45.268 | N22: 41.291 | O22: =P22-SUM(L22,M22,N22) -> 38.666 | P22: 162.346 | Q22: 37.846 | R22: 48.56 | S22: 46.618 | T22: =U22-SUM(Q22,R22,S22) -> 45.753 | U22: 178.777 | V22: 50.21 | W22: 61.045 | X22: 58.683 | Y22: =Z22-SUM(V22,W22,X22) -> 68.244 | Z22: 238.182 | AA22: 64.73 | AB22: 104.968 | AC22: 104.619 | AD22: =AE22-SUM(AA22,AB22,AC22) -> 108.748 | AE22: 383.065 | AF22: 101.734 | AG22: 106.946 | AH22: 92.139 | AI22: =AJ22-SUM(AF22,AG22,AH22) -> 86.897 | AJ22: 387.716 | AK22: 81.673 | AL22: 89.278 | AM22: 83.25 | AN22: =AO22-SUM(AK22,AL22,AM22) -> 87.861 | AO22: 342.062 | AP22: 85.239 | AQ22: 79.904 | AR22: 84.852 | AS22: =AT22-SUM(AP22,AQ22,AR22) -> 79.579 | AT22: 329.574 | AU22: 81.658 | AV22: 88.494 | AW22: 89.618 | AX22: =AY22-SUM(AU22,AV22,AW22) -> 87.415 | AY22: 347.185 | AZ22: 84.296 | BA22: 94.158 | BB22: 83.644 | BC22: =BD22-SUM(AZ22,BA22,BB22) -> 87.739 | BD22: 349.837 | BE22: 86.445 | BF22: 93.207 | BG22: 87.71 | BH22: =BI22-SUM(BE22,BF22,BG22) -> 86.457 | BI22: 353.819 | BJ22: 78.703 | BK22: 92.393 | BL22: 88.363 | BM22: =BN22-SUM(BJ22,BK22,BL22) -> 86.127 | BN22: 345.586 | BO22: 85.936 | BP22: 95.373 | BQ22: 97.622 | BR22: =BS22-SUM(BO22,BP22,BQ22) -> 104.727 | BS22: 383.658 | BT22: =BO22*(1+BT10) -> 87.65472 | BU22: =BP22*(1+BU10) -> 97.28046 | BV22: =BQ22*(1+BV10) -> 99.57444 | BW22: =BR22*(1+BW10) -> 106.82154 | BX22: =SUM(BT22,BU22,BV22,BW22) -> 391.33116 | BY22: =BT22*(1+BY10) -> 89.407814 | BZ22: =BU22*(1+BZ10) -> 99.226069 | CA22: =BV22*(1+CA10) -> 101.56593 | CB22: =BW22*(1+CB10) -> 108.95797 | CC22: =SUM(BY22,BZ22,CA22,CB22) -> 399.15778 | CD22: =CC22*(1+CD10) -> 407.14094 | CE22: =CD22*(1+CE10) -> 415.28376 | CF22: =CE22*(1+CF10) -> 423.58943
A23: Post-mix and other revenue, mm | C23: 103.398 | D23: 128.799 | E23: 139.173 | F23: 155.066 | G23: 36.327 | H23: 44.23 | I23: 45.193 | J23: =K23-SUM(G23,H23,I23) -> 38.39 | K23: 164.14 | L23: 39.34 | M23: 47.196 | N23: 48.015 | O23: =P23-SUM(L23,M23,N23) -> 45.532 | P23: 180.083 | Q23: 47 | R23: 58.164 | S23: 63.861 | T23: =U23-SUM(Q23,R23,S23) -> 57.072 | U23: 226.097 | V23: 56.386 | W23: 68.109 | X23: 73.089 | Y23: =Z23-SUM(V23,W23,X23) -> 63.979 | Z23: 261.563 | AA23: 65.154 | AB23: 87.745 | AC23: 90.702 | AD23: =AE23-SUM(AA23,AB23,AC23) -> 85.412 | AE23: 329.013 | AF23: 82.001 | AG23: 82.827 | AH23: 91.394 | AI23: =AJ23-SUM(AF23,AG23,AH23) -> 114.722 | AJ23: 370.944 | AK23: 91.571 | AL23: 91.307 | AM23: 91.762 | AN23: =AO23-SUM(AK23,AL23,AM23) -> 68.425 | AO23: 343.065 | AP23: 83.391 | AQ23: 56.104 | AR23: 75.162 | AS23: =AT23-SUM(AP23,AQ23,AR23) -> 60.583 | AT23: 275.24 | AU23: 73.964 | AV23: 90.919 | AW23: 90.335 | AX23: =AY23-SUM(AU23,AV23,AW23) -> 78.262 | AY23: 333.48 | AZ23: 76.545 | BA23: 81.533 | BB23: 79.45 | BC23: =BD23-SUM(AZ23,BA23,BB23) -> 72.219 | BD23: 309.747 | BE23: 55.007 | BF23: 67.546 | BG23: 71.101 | BH23: =BI23-SUM(BE23,BF23,BG23) -> 64.613 | BI23: 258.267 | BJ23: 49.289 | BK23: 57.191 | BL23: 57.072 | BM23: =BN23-SUM(BJ23,BK23,BL23) -> 57.262 | BN23: 220.814 | BO23: 51.047 | BP23: 54.112 | BQ23: 64.269 | BR23: =BS23-SUM(BO23,BP23,BQ23) -> 62.249 | BS23: 231.677 | BT23: =BO23*(1+BT11) -> 52.06794 | BU23: =BP23*(1+BU11) -> 55.19424 | BV23: =BQ23*(1+BV11) -> 65.55438 | BW23: =BR23*(1+BW11) -> 63.49398 | BX23: =SUM(BT23,BU23,BV23,BW23) -> 236.31054 | BY23: =BT23*(1+BY11) -> 53.109299 | BZ23: =BU23*(1+BZ11) -> 56.298125 | CA23: =BV23*(1+CA11) -> 66.865468 | CB23: =BW23*(1+CB11) -> 64.76386 | CC23: =SUM(BY23,BZ23,CA23,CB23) -> 241.03675 | CD23: =CC23*(1+CD11) -> 245.85749 | CE23: =CD23*(1+CE11) -> 250.77464 | CF23: =CE23*(1+CF11) -> 255.79013
A24: Total Other Sales, mm | C24: =SUM(C22:C23) -> 234.551 | D24: =SUM(D22:D23) -> 269.606 | E24: =SUM(E22:E23) -> 289.447 | F24: =SUM(F22:F23) -> 307.467 | G24: =SUM(G22:G23) -> 76.455 | H24: =SUM(H22:H23) -> 88.693 | I24: =SUM(I22:I23) -> 87.223 | J24: =SUM(J22:J23) -> 78.245 | ... CF24: =SUM(CF22:CF23) -> 679.37956
A25: Total Net Sales, mm | C25: =C21+C24 -> 1442.986 | D25: =D21+D24 -> 1514.599 | E25: =E21+E24 -> 1561.239 | F25: =F21+F24 -> 1614.433 | G25: =G21+G24 -> 383.551 | H25: =H21+H24 -> 428.979 | I25: =I21+I24 -> 434.464 | J25: =J21+J24 -> 394.337 | ... CF25: =CF21+CF24 -> 7719.2659
A27: Fountain sales, mm | AK27: =AO27-AL27-AM27-AN27 -> 42.8 | AL27: 51.8 | AM27: 55.5 | AN27: 46.9 | AO27: 197 | AP27: =AT27-AQ27-AR27-AS27 -> 40.8 | AQ27: 22.5 | AR27: 36 | AS27: 32.5 | AT27: 131.8 | AU27: 32.6 | AV27: 43.3 | AW27: 45.3
A29: Sparkling beverages revenue as of total, % | C29: =C19/C$25 -> 0.69741217 | D29: =D19/D$25 -> 0.68098751 | E29: =E19/E$25 -> 0.67392885 | F29: =F19/F$25 -> 0.6646736 | G29: =G19/G$25 -> 0.66346588 | H29: =H19/H$25 -> 0.62915201 | I29: =I19/I$25 -> 0.63044349 | J29: =J19/J$25 -> 0.67171734 | ... CF29: =CF19/CF$25 -> 0.56331878
A30: Still beverage revenue as of total, % | C30: =C20/C$25 -> 0.14004225 | D30: =D20/D$25 -> 0.14100762 | E30: =E20/E$25 -> 0.14067545 | F30: =F20/F$25 -> 0.14487749 | G30: =G20/G$25 -> 0.13719949 | H30: =H20/H$25 -> 0.16409428 | I30: =I20/I$25 -> 0.16879649 | J30: =J20/J$25 -> 0.12986101 | ... CF30: =CF20/CF$25 -> 0.34867032
A31: Total Bottle/Can Sales as of Total, % | C31: =SUM(C29:C30) -> 0.83745442 | D31: =SUM(D29:D30) -> 0.82199513 | E31: =SUM(E29:E30) -> 0.8146043 | F31: =SUM(F29:F30) -> 0.80955109 | G31: =SUM(G29:G30) -> 0.80066536 | H31: =SUM(H29:H30) -> 0.79324629 | I31: =SUM(I29:I30) -> 0.79923998 | J31: =SUM(J29:J30) -> 0.80157835 | ... CF31: =SUM(CF29:CF30) -> 0.9119891
A32: Sales to other Coca-Cola bottlers revenue as of total, % | C32: =C22/C$25 -> 0.090890002 | D32: =D22/D$25 -> 0.092966521 | E32: =E22/E$25 -> 0.09625304 | F32: =F22/F$25 -> 0.094399086 | G32: =G22/G$25 -> 0.10462233 | H32: =H22/H$25 -> 0.10364843 | I32: =I22/I$25 -> 0.096739891 | J32: =J22/J$25 -> 0.10106838 | ... CF32: =CF22/CF$25 -> 0.054874315
A33: Post-mix and other revenue as of total, % | C33: =C23/C$25 -> 0.071655581 | D33: =D23/D$25 -> 0.08503835 | E33: =E23/E$25 -> 0.089142662 | F33: =F23/F$25 -> 0.096049821 | G33: =G23/G$25 -> 0.094712307 | H33: =H23/H$25 -> 0.10310528 | I33: =I23/I$25 -> 0.10402013 | J33: =J23/J$25 -> 0.097353279 | ... CF33: =CF23/CF$25 -> 0.033136587
A34: Total Other Sales as of Total, % | C34: =C24/C$25 -> 0.16254558 | D34: =D24/D$25 -> 0.17800487 | E34: =E24/E$25 -> 0.1853957 | F34: =F24/F$25 -> 0.19044891 | G34: =G24/G$25 -> 0.19933464 | H34: =H24/H$25 -> 0.20675371 | I34: =I24/I$25 -> 0.20076002 | J34: =J24/J$25 -> 0.19842165 | ... CF34: =CF24/CF$25 -> 0.088010903
A35: Total Net Sales as of Total, % | C35: =C31+C34 -> 1 | D35: =D31+D34 -> 1 | E35: =E31+E34 -> 1 | F35: =F31+F34 -> 1 | G35: =G31+G34 -> 1 | H35: =H31+H34 -> 1 | I35: =I31+I34 -> 1 | J35: =J31+J34 -> 1 | ... CF35: =CF31+CF34 -> 1
A37: Operating Stats - Bottle/Can Volume Price Analysis (PR/10Q) | AZ37: Restated | BA37: Restated | BB37: Restated | BC37: Restated | BD37: Restated
A38: Sparkling category volume growth, % | AF38: =AF42/AA42-1 -> 0.20637212 | AG38: =AG42/AB42-1 -> 0.054064219 | AH38: =AH42/AC42-1 -> 0.040274799 | AI38: =AI42/AD42-1 -> 0.037033227 | AJ38: =AJ42/AE42-1 -> 0.077541496 | AK38: =AK42/AF42-1 -> 0.0095263533 | AL38: =AL42/AG42-1 -> -0.0027044394 | AM38: =AM42/AH42-1 -> 0.043441427 | ... AY38: =AY42/AT42-1 -> 0.0028233867 | AZ38: ="NMF" -> NMF | BA38: ="NMF" -> NMF | BB38: ="NMF" -> NMF | BC38: ="NMF" -> NMF | BD38: ="NMF" -> NMF | BE38: =BE42/AZ42-1 -> -0.0086977609 | BF38: =BF42/BA42-1 -> -0.020936671 | BG38: =BG42/BB42-1 -> 0.0017691354 | BH38: =BH42/BC42-1 -> 0.014986497 | BI38: =BI42/BD42-1 -> -0.0032598636 | BJ38: =BJ42/BE42-1 -> 0.0076324673 | BK38: =BK42/BF42-1 -> -0.0035051546 | BL38: =BL42/BG42-1 -> 0.0079998792 | ... BS38: =BS42/BN42-1 -> 0.00023623287 | BT38: 0.005 | BU38: 0.005 | BV38: 0.005 | BW38: 0.005 | BX38: =BX42/BS42-1 -> 0.005 | BY38: 0.005 | BZ38: 0.005 | CA38: 0.005 | CB38: 0.005 | CC38: =CC42/BX42-1 -> 0.005 | CD38: 0.005 | CE38: 0.005 | CF38: 0.005
A39: Still beverages volume growth, % | AF39: =AF43/AA43-1 -> 0.17122142 | AG39: =AG43/AB43-1 -> -0.058038967 | AH39: =AH43/AC43-1 -> -0.078426842 | AI39: =AI43/AD43-1 -> -0.12095549 | AJ39: =AJ43/AE43-1 -> -0.035206918 | AK39: =AK43/AF43-1 -> -0.015338828 | AL39: =AL43/AG43-1 -> 0.021349268 | AM39: =AM43/AH43-1 -> 0.048227987 | ... AY39: =AY43/AT43-1 -> 0.061816031 | AZ39: ="NMF" -> NMF | BA39: ="NMF" -> NMF | BB39: ="NMF" -> NMF | BC39: ="NMF" -> NMF | BD39: ="NMF" -> NMF | BE39: =BE43/AZ43-1 -> -0.089057319 | BF39: =BF43/BA43-1 -> -0.088741869 | BG39: =BG43/BB43-1 -> -0.054097086 | BH39: =BH43/BC43-1 -> -0.0015367837 | BI39: =BI43/BD43-1 -> -0.061166065 | BJ39: =BJ43/BE43-1 -> -0.039096109 | BK39: =BK43/BF43-1 -> -0.035043602 | BL39: =BL43/BG43-1 -> -0.096610037 | ... BS39: =BS43/BN43-1 -> 0.010206325 | BT39: 0.015 | BU39: 0.015 | BV39: 0.015 | BW39: 0.015 | BX39: =BX43/BS43-1 -> 0.015 | BY39: 0.015 | BZ39: 0.015 | CA39: 0.015 | CB39: 0.015 | CC39: =CC43/BX43-1 -> 0.015 | CD39: 0.02 | CE39: 0.02 | CF39: 0.02
A40: Physical Case Volume Growth, % | AF40: =AF44/AA44-1 -> 0.19631902 | AG40: =AG44/AB44-1 -> 0.018079096 | AH40: =AH44/AC44-1 -> -0.0011520737 | AI40: =AI44/AD44-1 -> -0.0048019208 | AJ40: =AJ44/AE44-1 -> 0.042927733 | AK40: =AK44/AF44-1 -> 0.0025641026 | AL40: =AL44/AG44-1 -> 0.0044395117 | AM40: =AM44/AH44-1 -> 0.044982699 | ... AY40: =AY44/AT44-1 -> 0.020167224 | AZ40: ="NMF" -> NMF | BA40: ="NMF" -> NMF | BB40: ="NMF" -> NMF | BC40: ="NMF" -> NMF | BD40: ="NMF" -> NMF | BE40: =BE44/AZ44-1 -> -0.030631435 | BF40: =BF44/BA44-1 -> -0.039965563 | BG40: =BG44/BB44-1 -> -0.014429736 | BH40: =BH44/BC44-1 -> 0.011180138 | BI40: =BI44/BD44-1 -> -0.018840888 | BJ40: =BJ44/BE44-1 -> -0.0043530981 | BK40: =BK44/BF44-1 -> -0.011906434 | BL40: =BL44/BG44-1 -> -0.021111801 | ... CC40: =CC44/BX44-1 -> 0.007484179 | CD40: =CD44/CC44-1 -> 0.0087540664 | CE40: =CE44/CD44-1 -> 0.008795918 | CF40: =CF44/CE44-1 -> 0.0088380769
A42: Sparkling beverages case volume, mm | AA42: =AA$44*AA49 -> 46.5528 | AB42: =AB$44*AB49 -> 60.0915 | AC42: =AC$44*AC49 -> 56.5068 | AD42: =AE42-SUM(AA42,AB42,AC42) -> 61.2423 | AE42: =AE$44*AE49 -> 224.3934 | AF42: =AF$44*AF49 -> 56.16 | AG42: =AG$44*AG49 -> 63.3403 | AH42: =AH$44*AH49 -> 58.7826 | AI42: =AJ42-SUM(AF42,AG42,AH42) -> 63.5103 | AJ42: =AJ$44*AJ49 -> 241.7932 | AK42: =AK$44*AK49 -> 56.695 | AL42: =AL$44*AL49 -> 63.169 | AM42: =AM$44*AM49 -> 61.3362 | AN42: =AO42-SUM(AK42,AL42,AM42) -> 61.4422 | AO42: =AO$44*AO49 -> 242.6424 | AP42: =AP$44*AP49 -> 58.681 | AQ42: =AQ$44*AQ49 -> 65.592 | AR42: =AR$44*AR49 -> 63.5175 | AS42: =AT42-SUM(AP42,AQ42,AR42) -> 65.5223 | AT42: =AT$44*AT49 -> 253.3128 | AU42: =AU$44*AU49 -> 61.0907 | AV42: =AV$44*AV49 -> 65.552 | AW42: =AW$44*AW49 -> 63.1125 | AX42: =AY42-SUM(AU42,AV42,AW42) -> 64.2728 | AY42: 254.028 | AZ42: 61.855 | BA42: 69.352 | BB42: 66.134 | BC42: =BD42-SUM(AZ42,BA42,BB42) -> 67.394 | BD42: 264.735 | BE42: 61.317 | BF42: 67.9 | BG42: 66.251 | BH42: =BI42-SUM(BE42,BF42,BG42) -> 68.404 | BI42: 263.872 | BJ42: 61.785 | BK42: 67.662 | BL42: 66.781 | BM42: =BN42-SUM(BJ42,BK42,BL42) -> 70.458 | BN42: 266.686 | BO42: 58.629 | BP42: 67.487 | BQ42: 67.695 | BR42: =BS42-SUM(BO42,BP42,BQ42) -> 72.938 | BS42: 266.749 | BT42: =BO42*(1+BT38) -> 58.922145 | BU42: =BP42*(1+BU38) -> 67.824435 | BV42: =BQ42*(1+BV38) -> 68.033475 | BW42: =BR42*(1+BW38) -> 73.30269 | BX42: =SUM(BT42,BU42,BV42,BW42) -> 268.08275 | BY42: =BT42*(1+BY38) -> 59.216756 | BZ42: =BU42*(1+BZ38) -> 68.163557 | CA42: =BV42*(1+CA38) -> 68.373642 | CB42: =BW42*(1+CB38) -> 73.669203 | CC42: =SUM(BY42,BZ42,CA42,CB42) -> 269.42316 | CD42: =CC42*(1+CD38) -> 270.77027 | CE42: =CD42*(1+CE38) -> 272.12413 | CF42: =CE42*(1+CF38) -> 273.48475
A43: Still beverages case volume, mm | AA43: =AA$44*AA50 -> 18.6472 | AB43: =AB$44*AB50 -> 28.4085 | AC43: =AC$44*AC50 -> 30.2932 | AD43: =AE43-SUM(AA43,AB43,AC43) -> 22.0577 | AE43: =AE$44*AE50 -> 99.4066 | AF43: =AF$44*AF50 -> 21.84 | AG43: =AG$44*AG50 -> 26.7597 | AH43: =AH$44*AH50 -> 27.9174 | AI43: =AJ43-SUM(AF43,AG43,AH43) -> 19.3897 | AJ43: =AJ$44*AJ50 -> 95.9068 | AK43: =AK$44*AK50 -> 21.505 | AL43: =AL$44*AL50 -> 27.331 | AM43: =AM$44*AM50 -> 29.2638 | AN43: =AO43-SUM(AK43,AL43,AM43) -> 22.4578 | AO43: =AO$44*AO50 -> 100.5576 | AP43: =AP$44*AP50 -> 24.319 | AQ43: =AQ$44*AQ50 -> 25.508 | AR43: =AR$44*AR50 -> 30.5825 | AS43: =AT43-SUM(AP43,AQ43,AR43) -> 25.0777 | AT43: =AT$44*AT50 -> 105.4872 | AU43: =AU$44*AU50 -> 25.8093 | AV43: =AV$44*AV50 -> 30.848 | AW43: =AW$44*AW50 -> 30.3875 | AX43: =AY43-SUM(AU43,AV43,AW43) -> 24.9632 | AY43: 112.008 | AZ43: 23.221 | BA43: 27.056 | BB43: 27.007 | BC43: =BD43-SUM(AZ43,BA43,BB43) -> 20.172 | BD43: 97.456 | BE43: 21.153 | BF43: 24.655 | BG43: 25.546 | BH43: =BI43-SUM(BE43,BF43,BG43) -> 20.141 | BI43: 91.495 | BJ43: 20.326 | BK43: 23.791 | BL43: 23.078 | BM43: =BN43-SUM(BJ43,BK43,BL43) -> 19.222 | BN43: 86.417 | BO43: 18.098 | BP43: 23.219 | BQ43: 25.122 | BR43: =BS43-SUM(BO43,BP43,BQ43) -> 20.86 | BS43: 87.299 | BT43: =BO43*(1+BT39) -> 18.36947 | BU43: =BP43*(1+BU39) -> 23.567285 | BV43: =BQ43*(1+BV39) -> 25.49883 | BW43: =BR43*(1+BW39) -> 21.1729 | BX43: =SUM(BT43,BU43,BV43,BW43) -> 88.608485 | BY43: =BT43*(1+BY39) -> 18.645012 | BZ43: =BU43*(1+BZ39) -> 23.920794 | CA43: =BV43*(1+CA39) -> 25.881312 | CB43: =BW43*(1+CB39) -> 21.490494 | CC43: =SUM(BY43,BZ43,CA43,CB43) -> 89.937612 | CD43: =CC43*(1+CD39) -> 91.736365 | CE43: =CD43*(1+CE39) -> 93.571092 | CF43: =CE43*(1+CF39) -> 95.442514
A44: Physical Case Volume, mm | AA44: 65.2 | AB44: 88.5 | AC44: 86.8 | AD44: 83.3 | AE44: 323.8 | AF44: 78 | AG44: 90.1 | AH44: 86.7 | AI44: =IFERROR(AJ44-SUM(AF44,AG44,AH44),"N/A") -> 82.9 | AJ44: 337.7 | AK44: 78.2 | AL44: 90.5 | AM44: 90.6 | AN44: =IFERROR(AO44-SUM(AK44,AL44,AM44),"N/A") -> 83.9 | AO44: 343.2 | AP44: 83 | AQ44: 91.1 | AR44: 94.1 | AS44: =IFERROR(AT44-SUM(AP44,AQ44,AR44),"N/A") -> 90.6 | AT44: 358.8 | AU44: 86.9 | AV44: 96.4 | AW44: 93.5 | AX44: =IFERROR(AY44-SUM(AU44,AV44,AW44),"N/A") -> 89.236 | AY44: =SUM(AY42:AY43) -> 366.036 | AZ44: =SUM(AZ42:AZ43) -> 85.076 | BA44: =SUM(BA42:BA43) -> 96.408 | BB44: =SUM(BB42:BB43) -> 93.141 | BC44: =IFERROR(BD44-SUM(AZ44,BA44,BB44),"N/A") -> 87.566 | BD44: =SUM(BD42:BD43) -> 362.191 | BE44: =SUM(BE42:BE43) -> 82.47 | BF44: =SUM(BF42:BF43) -> 92.555 | BG44: =SUM(BG42:BG43) -> 91.797 | BH44: =IFERROR(BI44-SUM(BE44,BF44,BG44),"N/A") -> 88.545 | BI44: =SUM(BI42:BI43) -> 355.367 | BJ44: =SUM(BJ42:BJ43) -> 82.111 | BK44: =SUM(BK42:BK43) -> 91.453 | BL44: =SUM(BL42:BL43) -> 89.859 | BM44: =IFERROR(BN44-SUM(BJ44,BK44,BL44),"N/A") -> 89.68 | BN44: =SUM(BN42:BN43) -> 353.103 | BO44: =SUM(BO42:BO43) -> 76.727 | BP44: =SUM(BP42:BP43) -> 90.706 | BQ44: =SUM(BQ42:BQ43) -> 92.817 | BR44: =IFERROR(BS44-SUM(BO44,BP44,BQ44),"N/A") -> 93.798 | BS44: =SUM(BS42:BS43) -> 354.048 | BT44: =SUM(BT42:BT43) -> 77.291615 | BU44: =SUM(BU42:BU43) -> 91.39172 | BV44: =SUM(BV42:BV43) -> 93.532305 | BW44: =SUM(BW42:BW43) -> 94.47559 | BX44: =SUM(BX42:BX43) -> 356.69123 | BY44: =SUM(BY42:BY43) -> 77.861768 | BZ44: =SUM(BZ42:BZ43) -> 92.084351 | ... CF44: =SUM(CF42:CF43) -> 368.92726
A45: Acquisition/divestiture related physical case volume, mm | AF45: =AJ45-AG45-AH45 -> 12.2 | AG45: 25.9 | AH45: 10.6 | AI45: 0 | AJ45: 48.7
A46: Volume related to extra days in fiscal year, mm | AS46: 4.6 | AT46: 4.6
A47: Comparable Physical Case Volume, mm | AA47: =AA44-AA46-AA45 -> 65.2 | AB47: =AB44-AB46-AB45 -> 88.5 | AC47: =AC44-AC46-AC45 -> 86.8 | AD47: =AD44-AD46-AD45 -> 83.3 | AE47: =AE44-AE46-AE45 -> 323.8 | AF47: =AF44-AF46-AF45 -> 65.8 | AG47: =AG44-AG46-AG45 -> 64.2 | AH47: =AH44-AH46-AH45 -> 76.1 | ... CF47: =CF44-CF46-CF45 -> 368.92726
A49: Sparkling beverages as % of total case volume, % | C49: 0.865 | D49: 0.85 | E49: 0.841 | F49: 0.828 | G49: 0.835 | H49: 0.796 | I49: 0.787 | K49: 0.813 | L49: 0.819 | M49: 0.777 | N49: 0.774 | P49: 0.799 | Q49: 0.81 | R49: 0.715 | S49: 0.692 | U49: 0.734 | V49: 0.729 | W49: 0.697 | X49: 0.674 | Z49: 0.712 | AA49: 0.714 | AB49: 0.679 | AC49: 0.651 | AD49: =AD42/AD44 -> 0.73520168 | AE49: 0.693 | AF49: 0.72 | AG49: 0.703 | AH49: 0.678 | AI49: =AI42/AI44 -> 0.76610736 | AJ49: 0.716 | AK49: 0.725 | AL49: 0.698 | AM49: 0.677 | AN49: =AN42/AN44 -> 0.73232658 | AO49: 0.707 | AP49: 0.707 | AQ49: 0.72 | AR49: 0.675 | AS49: =AS42/AS44 -> 0.72320419 | AT49: 0.706 | AU49: 0.703 | AV49: 0.68 | AW49: 0.675 | AX49: =AX42/AX44 -> 0.7202564 | AY49: =AY42/AY44 -> 0.69399731 | AZ49: =AZ42/AZ44 -> 0.72705581 | BA49: =BA42/BA44 -> 0.71935939 | BB49: =BB42/BB44 -> 0.71004176 | BC49: =BC42/BC44 -> 0.76963662 | BD49: =BD42/BD44 -> 0.7309265 | BE49: =BE42/BE44 -> 0.74350673 | ... CF49: =CF42/CF44 -> 0.7412972
